Workbook
Name ContractValue: 'بيانات العقد'!$C$16
Name VOApproved: 'بيانات العقد'!$C$17
Name RevisedContract: 'بيانات العقد'!$C$18
Name AdvPct: 'بيانات العقد'!$C$20
Name AdvAmount: 'بيانات العقد'!$C$21
Name RecRate: 'بيانات العقد'!$C$23
Name RecStart: 'بيانات العقد'!$C$24
Name RecFull: 'بيانات العقد'!$C$25
Name RetPct: 'بيانات العقد'!$C$27
Name RetCap: 'بيانات العقد'!$C$29
Name VATPct: 'بيانات العقد'!$C$31
Name VATBeforeRet: 'بيانات العقد'!$C$32
Name WHTPct: 'بيانات العقد'!$C$33
Name PenInVAT: 'بيانات العقد'!$C$34
Name PenCap: 'بيانات العقد'!$C$45
Name StartDate: 'بيانات العقد'!$C$11
Name EndDate: 'بيانات العقد'!$C$13
Name AdvDate: 'بيانات العقد'!$C$22
Name L_Sections: 'بيانات العقد'!$F$6:$F$17
Name L_IPCStatus: 'بيانات العقد'!$G$6:$G$17
Name L_VOStatus: 'بيانات العقد'!$H$6:$H$17
Name L_TDType: 'بيانات العقد'!$I$6:$I$17
Name GAPct: 'الموازنة والتكاليف'!$E$6
Name ContPct: 'الموازنة والتكاليف'!$E$7
Name BAC: 'الموازنة والتكاليف'!$J$26

Sheet التعليمات
B1: 📘 ملف مستخلصات المشروع رقم 01 — 20 مستخلص مترابط
B2: =IF('بيانات العقد'!$C$5="","مشروع رقم 01 — أدخل بيانات العقد",'بيانات العقد'!$C$5&" | عقد رقم: "&'بيانات العقد'!$C$6)&" | المبالغ بـ "&'بيانات العقد'!$C$14
B3: ⚙ ابدأ ببيانات العقد | C3: 🧾 الانتقال إلى المستخلص الأول
B5: دليل الألوان
B6: إدخال يدوي | C6: خلايا صفراء بخط أزرق — هي الخلايا الوحيدة التي تُعدّل.
B7: معادلة محسوبة | C7: خط أسود — لا تكتب فوقها.
B8: ربط | C8: خط أخضر — قيمة مسحوبة من شيت آخر (مثل «السابق» من المستخلص الذي قبله).
B9: تنبيه | C9: تظليل أحمر: تجاوز الكمية التعاقدية، كود مكرر، تأخر عن البرنامج.
B11: خطوات العمل
B12: بيانات العقد | C12: أدخل بيانات المشروع والنسب التعاقدية (مرة واحدة).
B13: جدول الكميات | C13: أدخل بنود جدول الكميات والأسعار (حتى 100 بند).
B14: مستخلص 01 | C14: في كل مستخلص: أدخل الفترة والتواريخ والحالة والنسبة المخططة، ثم «الكمية الحالية» لكل بند، ورصيد المواد والغرامات والإفراج عن الضمان إن وجد، وبيانات التحصيل. «السابق» يُسحب آلياً من المستخلص الذي قبله، والتراكمي = السابق + الحالي.
B15: الأوامر التغييرية | C15: سجل الأوامر التغييرية واختر رقم المستخلص الذي تُدرج به.
B16: الاستقطاعات الفنية | C16: سجل الاستقطاعات الفنية برقم المستخلص، وحدد مستخلص الإفراج عند المعالجة.
B17: الموازنة والتكاليف | C17: أدخل الموازنة التقديرية لكل قسم حسب عناصر التكلفة مرة واحدة، ثم التكاليف الفعلية المباشرة لكل فترة مستخلص؛ يحسب الشيت الربح والهامش وCPI والتكلفة المتوقعة عند الإنجاز والموقف النقدي (شيت داخلي لا يُطبع مع المستخلص).
B18: سجل المستخلصات | C18: يتجمع كل شيء آلياً في السجل، ومنه ينتقل إلى ملف التقارير المجمع لكل المشاريع.
B20: التوافق مع الأنظمة السعودية
B21: ضريبة القيمة المضافة | C21: 15% (نظام ضريبة القيمة المضافة). وعاء الضريبة = صافي المستخلص بعد استرداد الدفعة المقدمة، ويشمل المحتجزات إذا فُوترت مع المستخلص، ولا تُخفضه غرامات التأخير افتراضياً — كلها قابلة للضبط في «بيانات العقد».
B22: الفاتورة الضريبية | C22: يُسجل رقم وتاريخ الفاتورة الضريبية لكل مستخلص. الفاتورة نفسها تُصدر من نظام فوترة إلكترونية متوافق مع متطلبات «فاتورة» لهيئة الزكاة والضريبة والجمارك (رمز QR والربط في المرحلة الثانية) — المستخلص ليس بديلاً عنها.
B23: الرقم الضريبي | C23: 15 رقماً يبدأ وينتهي بالرقم 3 — مع تحقق آلي من الصيغة للمقاول وصاحب العمل.
B24: الدفعة المقدمة | C24: في العقود الحكومية لا تتجاوز 10% من قيمة العقد وبمقابل ضمان بنكي مساوٍ لها، وتُسترد من المستخلصات.
B25: الضمان النهائي | C25: 5% من قيمة العقد (خطاب ضمان بنكي) مع تنبيه آلي قبل انتهاء الصلاحية بـ 30 يوماً.
B26: غرامات التأخير | C26: حد أقصى قابل للضبط (افتراضياً 10% من قيمة العقد) مع تنبيه عند تجاوزه.
B27: ضريبة الاستقطاع | C27: لا تُطبق على المقاول المقيم (0%)، وتُستخدم فقط للمدفوعات لغير المقيم وفق نظام ضريبة الدخل.
B28: المستندات النظامية | C28: قائمة تحقق لكل مستخلص: الزكاة، التأمينات الاجتماعية (GOSI)، نطاقات، السجل التجاري والغرفة، الضمانات، التأمين (CAR).
B29: التاريخ الهجري | C29: تظهر فترة كل مستخلص بالتاريخ الهجري بجوار الميلادي.
B30: تنبيه مهم | C30: النسب والحدود الافتراضية مبنية على الممارسة الشائعة؛ تُراجع مع شروط عقدك والمستشار القانوني والضريبي قبل الاعتماد.
B32: الربط مع ملف التقارير
B33: • | C33: اسم هذا الملف يجب أن يبقى «IPC_Project_01.xlsx» داخل فولدر «Project_01»، والفولدر بجوار ملف «Projects_Billing_Reports.xlsx».
B34: • | C34: بعد حفظ هذا الملف، افتح ملف التقارير واضغط «تمكين المحتوى / تحديث» ليتم سحب الأرقام الجديدة.
B35: • | C35: لا تحذف صفوفاً أو أعمدة ولا تغيّر أسماء الشيتات حتى لا ينقطع الربط.

Sheet بيانات العقد
B1: ⚙ بيانات العقد والإعدادات التعاقدية — مشروع رقم 01
B2: =IF('بيانات العقد'!$C$5="","مشروع رقم 01 — أدخل بيانات العقد",'بيانات العقد'!$C$5&" | عقد رقم: "&'بيانات العقد'!$C$6)&" | المبالغ بـ "&'بيانات العقد'!$C$14
B3: 🗂 سجل المستخلصات | C3: 📋 جدول الكميات | D3: 🔁 التغييرية | F3: ✂ الاستقطاعات | G3: 💰 الموازنة | H3: 🧾 مستخلص 01
B4: البيان | C4: القيمة | D4: ملاحظات / الأساس التعاقدي | F4: القوائم المنسدلة (قابلة للتعديل)
B5: اسم المشروع | C5: مشروع إنشاء مبنى إداري - الرياض | D5: يظهر في جميع الشيتات وفي ملف التقارير المجمع | F5: أقسام الأعمال | G5: حالة المستخلص | H5: حالة الأمر التغييري | I5: نوع الاستقطاع الفني
B6: رقم العقد | C6: CT-2026-014 | F6: أعمال الحفر والردم | G6: مسودة | H6: معتمد | I6: أعمال غير مطابقة
B7: صاحب العمل (المالك) | C7: شركة رؤية للتطوير العقاري | F7: الخرسانة العادية والمسلحة | G7: مقدم للاستشاري | H7: قيد الدراسة | I7: أعمال ناقصة
B8: الاستشاري / المهندس | C8: مكتب البنيان للاستشارات الهندسية | F8: أعمال المباني | G8: تحت المراجعة | H8: مرفوض | I8: ملاحظات فنية
B9: المقاول | C9: شركة البناء الحديث للمقاولات | F9: أعمال العزل | G9: معتمد | I9: اختبارات غير مستكملة
B10: تاريخ توقيع العقد | C10: 46068 | F10: أعمال التشطيبات | G10: مرفوض | I10: مستندات غير مستكملة
B11: تاريخ بدء الأعمال (أمر المباشرة) | C11: 46082 | D11: بداية احتساب المدة الزمنية | F11: الأعمال الكهربائية | I11: أخرى
B12: مدة العقد (بالشهور) | C12: 18 | F12: الأعمال الصحية
B13: تاريخ الانتهاء التعاقدي | C13: =IF(OR(C11="",C12=""),"",EDATE(C11,C12)-1) | D13: محسوب = البدء + المدة | F13: أعمال التكييف
B14: العملة | C14: ريال سعودي | F14: أعمال الموقع العام
B15: القيم التعاقدية
B16: قيمة العقد الأصلية | C16: ='جدول الكميات'!H106 | D16: مرتبطة تلقائياً بإجمالي جدول الكميات
B17: صافي الأوامر التغييرية المعتمدة | C17: =SUMIFS('الأوامر التغييرية'!$G$6:$G$55,'الأوامر التغييرية'!$H$6:$H$55,"معتمد") | D17: مرتبطة بشيت الأوامر التغييرية (المعتمدة فقط)
B18: قيمة العقد المعدلة | C18: =C16+C17 | D18: الأصلية + صافي التغييرية المعتمدة
B19: الدفعة المقدمة واستردادها
B20: نسبة الدفعة المقدمة | C20: 0.1 | D20: من قيمة العقد الأصلية — في العقود الحكومية لا تتجاوز 10% وبمقابل ضمان بنكي مساوٍ لها
B21: قيمة الدفعة المقدمة | C21: =C16*C20 | D21: محسوبة
B22: تاريخ صرف الدفعة المقدمة | C22: 46091 | D22: تُصدر عنها فاتورة ضريبية عند الاستلام، ويُخفض الاسترداد وعاء الضريبة في المستخلصات التالية
B23: نسبة الاسترداد من قيمة الأعمال | C23: 0.125 | D23: تُخصم من كل مستخلص كنسبة من (الأعمال المنفذة + التغييرية)
B24: بدء الاسترداد عند نسبة إنجاز | C24: 0 | D24: مثال FIDIC: يبدأ الاسترداد بعد تجاوز 10% من قيمة العقد
B25: استرداد كامل الرصيد عند نسبة إنجاز | C25: 0.8 | D25: عند بلوغ هذه النسبة يُسترد كامل الرصيد المتبقي
B26: ضمان الأعمال
B27: نسبة ضمان الأعمال (المحتجزات) | C27: 0.1 | D27: تُحتجز من إجمالي قيمة الأعمال التراكمية
B28: الحد الأقصى للضمان (% من العقد المعدل) | C28: 0.05 | D28: يتوقف الاحتجاز عند بلوغ الحد
B29: الحد الأقصى للضمان (قيمة) | C29: =C18*C28 | D29: محسوب
B30: الضرائب (هيئة الزكاة والضريبة والجمارك)
B31: نسبة ضريبة القيمة المضافة | C31: 0.15 | D31: 15% وفق نظام ضريبة القيمة المضافة في المملكة (منذ يوليو 2020)
B32: احتساب الضريبة قبل خصم الضمان؟ | C32: نعم | D32: نعم: الفاتورة الضريبية تصدر بكامل قيمة المستخلص شاملة المحتجزات — لا: تُفوتر المحتجزات وتُحتسب ضريبتها عند الإفراج
B33: نسبة ضريبة الاستقطاع (للمقاول غير المقيم فقط) | C33: 0 | D33: 0% للمقاول المقيم بالمملكة — تُطبق فقط على المدفوعات لغير المقيم وفق نظام ضريبة الدخل
B34: خصم الغرامات من وعاء ض.ق.م؟ | C34: لا | D34: لا: غرامات التأخير تعويض وليست تخفيضاً لقيمة التوريد فلا تُخفض وعاء الضريبة (راجع مستشارك الضريبي)
B35: البيانات النظامية والضمانات البنكية (المملكة العربية السعودية)
B36: نوع العقد | C36: خاص - FIDIC | D36: يحدد المرجعية: نظام المنافسات والمشتريات الحكومية ولائحته التنفيذية أو شروط العقد الخاص (FIDIC)
B37: الرقم الضريبي للمقاول | C37: 310123456700003 | D37: 15 رقماً يبدأ وينتهي بالرقم 3 (يظهر في الفاتورة الضريبية)
B38: السجل التجاري للمقاول | C38: 1010123456
B39: الرقم الضريبي لصاحب العمل | C39: 300987654300003 | D39: مطلوب في الفاتورة الضريبية بين المنشآت (B2B)
B40: نسبة الضمان النهائي | C40: 0.05 | D40: خطاب ضمان بنكي — 5% من قيمة العقد في العقود الحكومية (أو حسب العقد)
B41: قيمة الضمان النهائي | C41: =C18*C40 | D41: محسوبة على قيمة العقد المعدلة
B42: تاريخ انتهاء الضمان النهائي | C42: 46997 | D42: تنبيه أحمر إذا تبقى أقل من 30 يوماً
B43: تاريخ انتهاء ضمان الدفعة المقدمة | C43: 46446 | D43: يجب أن يظل سارياً حتى استرداد الدفعة بالكامل
B44: الحد الأقصى لغرامات التأخير (% من العقد) | C44: 0.1 | D44: حسب العقد / نظام المنافسات والمشتريات الحكومية ولائحته
B45: قيمة الحد الأقصى للغرامات | C45: =C18*C44 | D45: محسوبة
B46: الغرامات المحتسبة حتى تاريخه | C46: =-'مستخلص 20'!$L$27 | D46: تراكمي من آخر مستخلص
B47: حالة الغرامات | C47: =IF(C46>C45,"⚠ تجاوزت الحد الأقصى","✔ ضمن الحد المسموح")

Sheet جدول الكميات
A1: 📋 جدول الكميات والأسعار التعاقدي (BOQ)
A2: =IF('بيانات العقد'!$C$5="","مشروع رقم 01 — أدخل بيانات العقد",'بيانات العقد'!$C$5&" | عقد رقم: "&'بيانات العقد'!$C$6)&" | المبالغ بـ "&'بيانات العقد'!$C$14
A3: 🗂 سجل المستخلصات | B3: ⚙ بيانات العقد | C3: 🔁 التغييرية | D3: ✂ الاستقطاعات | F3: 💰 الموازنة | G3: 🧾 مستخلص 01
A4: أدخل بنود العقد في الخلايا الصفراء فقط (حتى 100 بند) — الإجمالي يغذي قيمة العقد وكل المستخلصات تلقائياً.
A5: م | B5: كود البند | C5: القسم | D5: وصف البند | E5: الوحدة | F5: الكمية التعاقدية | G5: سعر الوحدة | H5: الإجمالي | I5: الوزن النسبي
A6: =IF(B6="","",COUNTA($B$6:B6)) | B6: 01-001 | C6: أعمال الحفر والردم | D6: حفر عام للأساسات حتى المنسوب التصميمي مع نقل الناتج خارج الموقع | E6: م3 | F6: 4500 | G6: 25 | H6: =F6*G6 | I6: =IF($H$106>0,H6/$H$106,0)
A7: =IF(B7="","",COUNTA($B$6:B7)) | B7: 01-002 | C7: أعمال الحفر والردم | D7: ردم بالتربة المختارة على طبقات مع الدمك حتى 95% بروكتور معدل | E7: م3 | F7: 2200 | G7: 18 | H7: =F7*G7 | I7: =IF($H$106>0,H7/$H$106,0)
A8: =IF(B8="","",COUNTA($B$6:B8)) | B8: 01-003 | C8: أعمال الحفر والردم | D8: إحلال تربة بمواد مختارة (Sub-base) مع الدمك والاختبارات | E8: م3 | F8: 1800 | G8: 75 | H8: =F8*G8 | I8: =IF($H$106>0,H8/$H$106,0)
A9: =IF(B9="","",COUNTA($B$6:B9)) | B9: 02-001 | C9: الخرسانة العادية والمسلحة | D9: خرسانة عادية للنظافة قوة 20 ميجا باسكال | E9: م3 | F9: 380 | G9: 380 | H9: =F9*G9 | I9: =IF($H$106>0,H9/$H$106,0)
A10: =IF(B10="","",COUNTA($B$6:B10)) | B10: 02-002 | C10: الخرسانة العادية والمسلحة | D10: خرسانة مسلحة للقواعد والميد قوة 35 ميجا باسكال (بدون حديد) | E10: م3 | F10: 950 | G10: 950 | H10: =F10*G10 | I10: =IF($H$106>0,H10/$H$106,0)
A11: =IF(B11="","",COUNTA($B$6:B11)) | B11: 02-003 | C11: الخرسانة العادية والمسلحة | D11: خرسانة مسلحة للأعمدة والجدران الخرسانية قوة 35 ميجا باسكال | E11: م3 | F11: 420 | G11: 1150 | H11: =F11*G11 | I11: =IF($H$106>0,H11/$H$106,0)
A12: =IF(B12="","",COUNTA($B$6:B12)) | B12: 02-004 | C12: الخرسانة العادية والمسلحة | D12: خرسانة مسلحة للأسقف والكمرات والدرج قوة 35 ميجا باسكال | E12: م3 | F12: 1650 | G12: 1050 | H12: =F12*G12 | I12: =IF($H$106>0,H12/$H$106,0)
A13: =IF(B13="","",COUNTA($B$6:B13)) | B13: 02-005 | C13: الخرسانة العادية والمسلحة | D13: توريد وتركيب حديد تسليح عالي المقاومة (مطابق للمواصفات السعودية) | E13: طن | F13: 480 | G13: 3400 | H13: =F13*G13 | I13: =IF($H$106>0,H13/$H$106,0)
A14: =IF(B14="","",COUNTA($B$6:B14)) | B14: 03-001 | C14: أعمال المباني | D14: مباني بلوك أسمنتي مصمت سماكة 20 سم | E14: م2 | F14: 7800 | G14: 75 | H14: =F14*G14 | I14: =IF($H$106>0,H14/$H$106,0)
A15: =IF(B15="","",COUNTA($B$6:B15)) | B15: 03-002 | C15: أعمال المباني | D15: مباني بلوك أسمنتي سماكة 15 سم للقواطع | E15: م2 | F15: 3600 | G15: 60 | H15: =F15*G15 | I15: =IF($H$106>0,H15/$H$106,0)
A16: =IF(B16="","",COUNTA($B$6:B16)) | B16: 04-001 | C16: أعمال العزل | D16: عزل مائي للأساسات بالبيتومين على وجهين | E16: م2 | F16: 2400 | G16: 30 | H16: =F16*G16 | I16: =IF($H$106>0,H16/$H$106,0)
A17: =IF(B17="","",COUNTA($B$6:B17)) | B17: 04-002 | C17: أعمال العزل | D17: عزل مائي وحراري للأسطح بالممبرين والبوليسترين | E17: م2 | F17: 1900 | G17: 120 | H17: =F17*G17 | I17: =IF($H$106>0,H17/$H$106,0)
... A35: =IF(B35="","",COUNTA($B$6:B35)) | B35: 09-002 | C35: أعمال الموقع العام | D35: أعمال بلاط متداخل (إنترلوك) سماكة 8 سم | E35: م2 | F35: 3500 | G35: 70 | H35: =F35*G35 | I35: =IF($H$106>0,H35/$H$106,0)
A36: =IF(B36="","",COUNTA($B$6:B36)) | H36: =F36*G36 | I36: =IF($H$106>0,H36/$H$106,0)
A37: =IF(B37="","",COUNTA($B$6:B37)) | H37: =F37*G37 | I37: =IF($H$106>0,H37/$H$106,0)
A38: =IF(B38="","",COUNTA($B$6:B38)) | H38: =F38*G38 | I38: =IF($H$106>0,H38/$H$106,0)
A39: =IF(B39="","",COUNTA($B$6:B39)) | H39: =F39*G39 | I39: =IF($H$106>0,H39/$H$106,0)
A40: =IF(B40="","",COUNTA($B$6:B40)) | H40: =F40*G40 | I40: =IF($H$106>0,H40/$H$106,0)
A41: =IF(B41="","",COUNTA($B$6:B41)) | H41: =F41*G41 | I41: =IF($H$106>0,H41/$H$106,0)
A42: =IF(B42="","",COUNTA($B$6:B42)) | H42: =F42*G42 | I42: =IF($H$106>0,H42/$H$106,0)
A43: =IF(B43="","",COUNTA($B$6:B43)) | H43: =F43*G43 | I43: =IF($H$106>0,H43/$H$106,0)
A44: =IF(B44="","",COUNTA($B$6:B44)) | H44: =F44*G44 | I44: =IF($H$106>0,H44/$H$106,0)
A45: =IF(B45="","",COUNTA($B$6:B45)) | H45: =F45*G45 | I45: =IF($H$106>0,H45/$H$106,0)
A46: =IF(B46="","",COUNTA($B$6:B46)) | H46: =F46*G46 | I46: =IF($H$106>0,H46/$H$106,0)
A47: =IF(B47="","",COUNTA($B$6:B47)) | H47: =F47*G47 | I47: =IF($H$106>0,H47/$H$106,0)
... A105: =IF(B105="","",COUNTA($B$6:B105)) | H105: =F105*G105 | I105: =IF($H$106>0,H105/$H$106,0)
A106: إجمالي قيمة العقد الأصلية | H106: =SUM(H6:H105) | I106: =SUM(I6:I105)

Sheet الأوامر التغييرية
A1: 🔁 سجل الأوامر التغييرية (Variation Orders)
A2: =IF('بيانات العقد'!$C$5="","مشروع رقم 01 — أدخل بيانات العقد",'بيانات العقد'!$C$5&" | عقد رقم: "&'بيانات العقد'!$C$6)&" | المبالغ بـ "&'بيانات العقد'!$C$14
A3: 🗂 سجل المستخلصات | B3: ⚙ بيانات العقد | C3: 📋 جدول الكميات | D3: ✂ الاستقطاعات | F3: 💰 الموازنة | G3: 🧾 مستخلص 01
A4: «قيمة الأمر» تعدّل قيمة العقد عند الاعتماد — «القيمة المدرجة» تُصرف في المستخلص المحدد (للصرف على دفعات: كرر الأمر في سطر جديد بقيمة أمر = 0 ومستخلص مختلف).
A5: م | B5: رقم الأمر | C5: تاريخ الأمر | D5: وصف الأمر التغييري | E5: النوع | F5: قيمة الأمر | G5: الأثر على العقد (±) | H5: الحالة | I5: القيمة المدرجة بالمستخلص | J5: الأثر على المستخلص (±) | K5: رقم المستخلص المدرج به | L5: ملاحظات
A6: =IF(B6="","",COUNTA($B$6:B6)) | B6: VO-01 | C6: 46160 | D6: إضافة غرفة محولات ولوحة جهد متوسط خارجية | E6: إضافة | F6: 250000 | G6: =IF(E6="خصم",-1,1)*N(F6) | H6: معتمد | I6: 250000 | J6: =IF(E6="خصم",-1,1)*N(I6) | K6: 4
A7: =IF(B7="","",COUNTA($B$6:B7)) | B7: VO-02 | C7: 46205 | D7: تعديل مواصفة البورسلين بموافقة المالك | E7: خصم | F7: 64000 | G7: =IF(E7="خصم",-1,1)*N(F7) | H7: معتمد | I7: 64000 | J7: =IF(E7="خصم",-1,1)*N(I7) | K7: 5
A8: =IF(B8="","",COUNTA($B$6:B8)) | B8: VO-03 | C8: 46259 | D8: أعمال تنسيق موقع وزراعة إضافية | E8: إضافة | F8: 180000 | G8: =IF(E8="خصم",-1,1)*N(F8) | H8: قيد الدراسة | J8: =IF(E8="خصم",-1,1)*N(I8)
A9: =IF(B9="","",COUNTA($B$6:B9)) | G9: =IF(E9="خصم",-1,1)*N(F9) | J9: =IF(E9="خصم",-1,1)*N(I9)
A10: =IF(B10="","",COUNTA($B$6:B10)) | G10: =IF(E10="خصم",-1,1)*N(F10) | J10: =IF(E10="خصم",-1,1)*N(I10)
A11: =IF(B11="","",COUNTA($B$6:B11)) | G11: =IF(E11="خصم",-1,1)*N(F11) | J11: =IF(E11="خصم",-1,1)*N(I11)
A12: =IF(B12="","",COUNTA($B$6:B12)) | G12: =IF(E12="خصم",-1,1)*N(F12) | J12: =IF(E12="خصم",-1,1)*N(I12)
A13: =IF(B13="","",COUNTA($B$6:B13)) | G13: =IF(E13="خصم",-1,1)*N(F13) | J13: =IF(E13="خصم",-1,1)*N(I13)
A14: =IF(B14="","",COUNTA($B$6:B14)) | G14: =IF(E14="خصم",-1,1)*N(F14) | J14: =IF(E14="خصم",-1,1)*N(I14)
A15: =IF(B15="","",COUNTA($B$6:B15)) | G15: =IF(E15="خصم",-1,1)*N(F15) | J15: =IF(E15="خصم",-1,1)*N(I15)
A16: =IF(B16="","",COUNTA($B$6:B16)) | G16: =IF(E16="خصم",-1,1)*N(F16) | J16: =IF(E16="خصم",-1,1)*N(I16)
A17: =IF(B17="","",COUNTA($B$6:B17)) | G17: =IF(E17="خصم",-1,1)*N(F17) | J17: =IF(E17="خصم",-1,1)*N(I17)
A18: =IF(B18="","",COUNTA($B$6:B18)) | G18: =IF(E18="خصم",-1,1)*N(F18) | J18: =IF(E18="خصم",-1,1)*N(I18)
A19: =IF(B19="","",COUNTA($B$6:B19)) | G19: =IF(E19="خصم",-1,1)*N(F19) | J19: =IF(E19="خصم",-1,1)*N(I19)
A20: =IF(B20="","",COUNTA($B$6:B20)) | G20: =IF(E20="خصم",-1,1)*N(F20) | J20: =IF(E20="خصم",-1,1)*N(I20)
... A55: =IF(B55="","",COUNTA($B$6:B55)) | G55: =IF(E55="خصم",-1,1)*N(F55) | J55: =IF(E55="خصم",-1,1)*N(I55)
A56: الإجمالي | F56: =SUM(F6:F55) | G56: =SUM(G6:G55) | H56: ="معتمد: "&COUNTIF(H6:H55,"معتمد") | I56: =SUM(I6:I55) | J56: =SUM(J6:J55)

Sheet الاستقطاعات الفنية
A1: ✂ سجل الاستقطاعات الفنية (Technical Deductions)
A2: =IF('بيانات العقد'!$C$5="","مشروع رقم 01 — أدخل بيانات العقد",'بيانات العقد'!$C$5&" | عقد رقم: "&'بيانات العقد'!$C$6)&" | المبالغ بـ "&'بيانات العقد'!$C$14
A3: 🗂 سجل المستخلصات | B3: ⚙ بيانات العقد | C3: 📋 جدول الكميات | D3: 🔁 التغييرية | F3: 💰 الموازنة | G3: 🧾 مستخلص 01
A4: يُخصم المبلغ من المستخلص المحدد ويستمر محتجزاً تراكمياً حتى يتم الإفراج عنه في «مستخلص الإفراج».
A5: م | B5: رقم الاستقطاع | C5: التاريخ | D5: رقم المستخلص | E5: كود البند | F5: وصف البند (آلي) | G5: سبب الاستقطاع | H5: نوع الاستقطاع | I5: المبلغ المستقطع | J5: تم الإفراج؟ | K5: مستخلص الإفراج | L5: الرصيد المحتجز | M5: ملاحظات
A6: =IF(B6="","",COUNTA($B$6:B6)) | B6: TD-01 | C6: 46145 | D6: 2 | E6: 02-002 | F6: =IF(E6="","",IFERROR(INDEX('جدول الكميات'!$D$6:$D$105,MATCH(E6,'جدول الكميات'!$B$6:$B$105,0)),"⚠ كود غير موجود")) | G6: تعشيش في خرسانة بعض القواعد يلزم معالجته | H6: أعمال غير مطابقة | I6: 17000 | J6: نعم | K6: 4 | L6: =IF(J6="نعم",0,N(I6))
A7: =IF(B7="","",COUNTA($B$6:B7)) | B7: TD-02 | C7: 46177 | D7: 3 | E7: 04-001 | F7: =IF(E7="","",IFERROR(INDEX('جدول الكميات'!$D$6:$D$105,MATCH(E7,'جدول الكميات'!$B$6:$B$105,0)),"⚠ كود غير موجود")) | G7: عدم تقديم نتائج اختبار التصاق العزل | H7: اختبارات غير مستكملة | I7: 8000 | J7: لا | L7: =IF(J7="نعم",0,N(I7))
A8: =IF(B8="","",COUNTA($B$6:B8)) | B8: TD-03 | C8: 46238 | D8: 5 | E8: 02-004 | F8: =IF(E8="","",IFERROR(INDEX('جدول الكميات'!$D$6:$D$105,MATCH(E8,'جدول الكميات'!$B$6:$B$105,0)),"⚠ كود غير موجود")) | G8: ملاحظات على استواء أسطح بلاطات الدور الأول | H8: ملاحظات فنية | I8: 24000 | J8: لا | L8: =IF(J8="نعم",0,N(I8))
A9: =IF(B9="","",COUNTA($B$6:B9)) | B9: TD-04 | C9: 46268 | D9: 6 | E9: 03-001 | F9: =IF(E9="","",IFERROR(INDEX('جدول الكميات'!$D$6:$D$105,MATCH(E9,'جدول الكميات'!$B$6:$B$105,0)),"⚠ كود غير موجود")) | G9: مباني بلوك غير مطابقة للمواصفات (عدم ضبط الرأسية) | H9: أعمال غير مطابقة | I9: 13000 | J9: لا | L9: =IF(J9="نعم",0,N(I9))
A10: =IF(B10="","",COUNTA($B$6:B10)) | F10: =IF(E10="","",IFERROR(INDEX('جدول الكميات'!$D$6:$D$105,MATCH(E10,'جدول الكميات'!$B$6:$B$105,0)),"⚠ كود غير موجود")) | L10: =IF(J10="نعم",0,N(I10))
A11: =IF(B11="","",COUNTA($B$6:B11)) | F11: =IF(E11="","",IFERROR(INDEX('جدول الكميات'!$D$6:$D$105,MATCH(E11,'جدول الكميات'!$B$6:$B$105,0)),"⚠ كود غير موجود")) | L11: =IF(J11="نعم",0,N(I11))
A12: =IF(B12="","",COUNTA($B$6:B12)) | F12: =IF(E12="","",IFERROR(INDEX('جدول الكميات'!$D$6:$D$105,MATCH(E12,'جدول الكميات'!$B$6:$B$105,0)),"⚠ كود غير موجود")) | L12: =IF(J12="نعم",0,N(I12))
A13: =IF(B13="","",COUNTA($B$6:B13)) | F13: =IF(E13="","",IFERROR(INDEX('جدول الكميات'!$D$6:$D$105,MATCH(E13,'جدول الكميات'!$B$6:$B$105,0)),"⚠ كود غير موجود")) | L13: =IF(J13="نعم",0,N(I13))
A14: =IF(B14="","",COUNTA($B$6:B14)) | F14: =IF(E14="","",IFERROR(INDEX('جدول الكميات'!$D$6:$D$105,MATCH(E14,'جدول الكميات'!$B$6:$B$105,0)),"⚠ كود غير موجود")) | L14: =IF(J14="نعم",0,N(I14))
A15: =IF(B15="","",COUNTA($B$6:B15)) | F15: =IF(E15="","",IFERROR(INDEX('جدول الكميات'!$D$6:$D$105,MATCH(E15,'جدول الكميات'!$B$6:$B$105,0)),"⚠ كود غير موجود")) | L15: =IF(J15="نعم",0,N(I15))
A16: =IF(B16="","",COUNTA($B$6:B16)) | F16: =IF(E16="","",IFERROR(INDEX('جدول الكميات'!$D$6:$D$105,MATCH(E16,'جدول الكميات'!$B$6:$B$105,0)),"⚠ كود غير موجود")) | L16: =IF(J16="نعم",0,N(I16))
A17: =IF(B17="","",COUNTA($B$6:B17)) | F17: =IF(E17="","",IFERROR(INDEX('جدول الكميات'!$D$6:$D$105,MATCH(E17,'جدول الكميات'!$B$6:$B$105,0)),"⚠ كود غير موجود")) | L17: =IF(J17="نعم",0,N(I17))
A18: =IF(B18="","",COUNTA($B$6:B18)) | F18: =IF(E18="","",IFERROR(INDEX('جدول الكميات'!$D$6:$D$105,MATCH(E18,'جدول الكميات'!$B$6:$B$105,0)),"⚠ كود غير موجود")) | L18: =IF(J18="نعم",0,N(I18))
A19: =IF(B19="","",COUNTA($B$6:B19)) | F19: =IF(E19="","",IFERROR(INDEX('جدول الكميات'!$D$6:$D$105,MATCH(E19,'جدول الكميات'!$B$6:$B$105,0)),"⚠ كود غير موجود")) | L19: =IF(J19="نعم",0,N(I19))
A20: =IF(B20="","",COUNTA($B$6:B20)) | F20: =IF(E20="","",IFERROR(INDEX('جدول الكميات'!$D$6:$D$105,MATCH(E20,'جدول الكميات'!$B$6:$B$105,0)),"⚠ كود غير موجود")) | L20: =IF(J20="نعم",0,N(I20))
A21: =IF(B21="","",COUNTA($B$6:B21)) | F21: =IF(E21="","",IFERROR(INDEX('جدول الكميات'!$D$6:$D$105,MATCH(E21,'جدول الكميات'!$B$6:$B$105,0)),"⚠ كود غير موجود")) | L21: =IF(J21="نعم",0,N(I21))
... A105: =IF(B105="","",COUNTA($B$6:B105)) | F105: =IF(E105="","",IFERROR(INDEX('جدول الكميات'!$D$6:$D$105,MATCH(E105,'جدول الكميات'!$B$6:$B$105,0)),"⚠ كود غير موجود")) | L105: =IF(J105="نعم",0,N(I105))
A106: الإجمالي | I106: =SUM(I6:I105) | J106: =I106-L106 | L106: =SUM(L6:L105)

Sheet الموازنة والتكاليف
B1: 💰 الموازنة التقديرية والتكاليف الفعلية والربحية (Budget & Cost Control) — داخلي
B2: =IF('بيانات العقد'!$C$5="","مشروع رقم 01 — أدخل بيانات العقد",'بيانات العقد'!$C$5&" | عقد رقم: "&'بيانات العقد'!$C$6)&" | المبالغ بـ "&'بيانات العقد'!$C$14
B3: 🗂 سجل المستخلصات | C3: ⚙ بيانات العقد | D3: 📋 جدول الكميات | F3: 🔁 التغييرية | G3: ✂ الاستقطاعات | H3: 🧾 مستخلص 01
B5: إعدادات الموازنة
B6: نسبة المصروفات العمومية والإدارية (من التكلفة المباشرة) | E6: 0.06 | F6: تُحمّل على الموازنة وعلى التكلفة الفعلية لكل مستخلص
B7: نسبة احتياطي الطوارئ (من التكلفة المباشرة) | E7: 0.03 | F7: تُضاف للموازنة فقط
B8: نسبة الربح المستهدفة من الإدارة | E8: 0.12 | F8: للمقارنة مع الربح المخطط والفعلي
B9: أولاً: الموازنة التقديرية حسب أقسام الأعمال وعناصر التكلفة (إدخال)
B10: القسم | D10: القيمة التعاقدية للقسم | E10: المواد | F10: العمالة | G10: مقاولو الباطن | H10: المعدات | I10: مصروفات الموقع | J10: إجمالي التكلفة المباشرة | K10: الربح المباشر للقسم | L10: هامش القسم
B11: =IF('بيانات العقد'!F6="","",'بيانات العقد'!F6) | D11: =IF(B11="",0,SUMIF('جدول الكميات'!$C$6:$C$105,B11,'جدول الكميات'!$H$6:$H$105)) | E11: 33600 | F11: 33600 | G11: 44800 | H11: 100800 | I11: 11200 | J11: =SUM(E11:I11) | K11: =D11-J11 | L11: =IF(D11>0,K11/D11,0)
B12: =IF('بيانات العقد'!F7="","",'بيانات العقد'!F7) | D12: =IF(B12="",0,SUMIF('جدول الكميات'!$C$6:$C$105,B12,'جدول الكميات'!$H$6:$H$105)) | E12: 2153500 | F12: 783100 | G12: 391600 | H12: 391600 | I12: 195800 | J12: =SUM(E12:I12) | K12: =D12-J12 | L12: =IF(D12>0,K12/D12,0)
B13: =IF('بيانات العقد'!F8="","",'بيانات العقد'!F8) | D13: =IF(B13="",0,SUMIF('جدول الكميات'!$C$6:$C$105,B13,'جدول الكميات'!$H$6:$H$105)) | E13: 328400 | F13: 229900 | G13: 32800 | H13: 19700 | I13: 46000 | J13: =SUM(E13:I13) | K13: =D13-J13 | L13: =IF(D13>0,K13/D13,0)
B14: =IF('بيانات العقد'!F9="","",'بيانات العقد'!F9) | D14: =IF(B14="",0,SUMIF('جدول الكميات'!$C$6:$C$105,B14,'جدول الكميات'!$H$6:$H$105)) | E14: 117000 | F14: 46800 | G14: 58500 | I14: 11700 | J14: =SUM(E14:I14) | K14: =D14-J14 | L14: =IF(D14>0,K14/D14,0)
B15: =IF('بيانات العقد'!F10="","",'بيانات العقد'!F10) | D15: =IF(B15="",0,SUMIF('جدول الكميات'!$C$6:$C$105,B15,'جدول الكميات'!$H$6:$H$105)) | E15: 1664600 | F15: 832300 | G15: 599300 | H15: 66600 | I15: 166500 | J15: =SUM(E15:I15) | K15: =D15-J15 | L15: =IF(D15>0,K15/D15,0)
B16: =IF('بيانات العقد'!F11="","",'بيانات العقد'!F11) | D16: =IF(B16="",0,SUMIF('جدول الكميات'!$C$6:$C$105,B16,'جدول الكميات'!$H$6:$H$105)) | E16: 400200 | F16: 100000 | G16: 450200 | I16: 50000 | J16: =SUM(E16:I16) | K16: =D16-J16 | L16: =IF(D16>0,K16/D16,0)
B17: =IF('بيانات العقد'!F12="","",'بيانات العقد'!F12) | D17: =IF(B17="",0,SUMIF('جدول الكميات'!$C$6:$C$105,B17,'جدول الكميات'!$H$6:$H$105)) | E17: 165300 | F17: 41300 | G17: 186000 | I17: 20700 | J17: =SUM(E17:I17) | K17: =D17-J17 | L17: =IF(D17>0,K17/D17,0)
B18: =IF('بيانات العقد'!F13="","",'بيانات العقد'!F13) | D18: =IF(B18="",0,SUMIF('جدول الكميات'!$C$6:$C$105,B18,'جدول الكميات'!$H$6:$H$105)) | E18: 387400 | F18: 43000 | G18: 387400 | I18: 43000 | J18: =SUM(E18:I18) | K18: =D18-J18 | L18: =IF(D18>0,K18/D18,0)
B19: =IF('بيانات العقد'!F14="","",'بيانات العقد'!F14) | D19: =IF(B19="",0,SUMIF('جدول الكميات'!$C$6:$C$105,B19,'جدول الكميات'!$H$6:$H$105)) | E19: 113800 | F19: 56900 | G19: 56900 | H19: 42700 | I19: 14200 | J19: =SUM(E19:I19) | K19: =D19-J19 | L19: =IF(D19>0,K19/D19,0)
B20: =IF('بيانات العقد'!F15="","",'بيانات العقد'!F15) | D20: =IF(B20="",0,SUMIF('جدول الكميات'!$C$6:$C$105,B20,'جدول الكميات'!$H$6:$H$105)) | J20: =SUM(E20:I20) | K20: =D20-J20 | L20: =IF(D20>0,K20/D20,0)
B21: =IF('بيانات العقد'!F16="","",'بيانات العقد'!F16) | D21: =IF(B21="",0,SUMIF('جدول الكميات'!$C$6:$C$105,B21,'جدول الكميات'!$H$6:$H$105)) | J21: =SUM(E21:I21) | K21: =D21-J21 | L21: =IF(D21>0,K21/D21,0)
B22: =IF('بيانات العقد'!F17="","",'بيانات العقد'!F17) | D22: =IF(B22="",0,SUMIF('جدول الكميات'!$C$6:$C$105,B22,'جدول الكميات'!$H$6:$H$105)) | J22: =SUM(E22:I22) | K22: =D22-J22 | L22: =IF(D22>0,K22/D22,0)
B23: إجمالي التكلفة المباشرة | D23: =SUM(D11:D22) | E23: =SUM(E11:E22) | F23: =SUM(F11:F22) | G23: =SUM(G11:G22) | H23: =SUM(H11:H22) | I23: =SUM(I11:I22) | J23: =SUM(J11:J22)
B24: يُضاف: المصروفات العمومية والإدارية | J24: =ROUND(J23*GAPct,2)
B25: يُضاف: احتياطي الطوارئ | J25: =ROUND(J23*ContPct,2)
B26: إجمالي الموازنة عند الإنجاز (BAC) | J26: =SUM(J23:J25)
B27: الربح المخطط (قيمة العقد الأصلية − الموازنة) | J27: =D23-J26 | K27: =IF(D23>0,J27/D23,0) | L27: =IF(J26=0,"",IF(K27>=$E$8,"✔ يحقق المستهدف","⚠ أقل من المستهدف"))
B29: ثانياً: التكاليف الفعلية لكل فترة مستخلص (إدخال التكاليف المباشرة) والربحية والقيمة المكتسبة
B30: رقم المستخلص | C30: الفترة إلى | D30: المواد | E30: العمالة | F30: مقاولو الباطن | G30: المعدات | H30: مصروفات الموقع | I30: مصروفات عمومية (محسوبة) | J30: إجمالي تكلفة الفترة | K30: التكلفة التراكمية | L30: الإيراد التراكمي (إجمالي قيمة الأعمال) | M30: الربح التراكمي | N30: هامش الربح | O30: القيمة المكتسبة بالتكلفة (EV) | P30: مؤشر أداء التكلفة CPI | Q30: التكلفة المتوقعة عند الإنجاز EAC | R30: الربح المتوقع عند الإنجاز | S30: الموقف النقدي (محصل + مقدمة − تكلفة)
B31: 1 | C31: =IF('سجل المستخلصات'!C6="","",'سجل المستخلصات'!C6) | D31: 65629.71 | E31: 26499.01 | F31: 27000.76 | G31: 7632.7 | H31: 6837.14 | I31: =ROUND(SUM(D31:H31)*GAPct,2) | J31: =SUM(D31:I31) | K31: =IF(AND(C31="",J31=0),"",SUM($J$31:J31)) | L31: =IF(C31="","",N('سجل المستخلصات'!K6)) | M31: =IF(OR(L31="",K31=""),"",L31-K31) | N31: =IF(OR(M31="",N(L31)=0),"",M31/L31) | O31: =IF(C31="","",BAC*N('سجل المستخلصات'!L6)) | P31: =IF(OR(O31="",N(K31)=0),"",O31/K31) | Q31: =IF(P31="","",IF(P31>0,BAC/P31,BAC)) | R31: =IF(Q31="","",RevisedContract-Q31) | S31: =IF(C31="","",SUMIF('سجل المستخلصات'!$A$6:$A$25,"<="&B31,'سجل المستخلصات'!$AA$6:$AA$25)+IF(AND(AdvDate<>"",N(AdvDate)<=N(C31)),AdvAmount,0)-N(K31))
B32: 2 | C32: =IF('سجل المستخلصات'!C7="","",'سجل المستخلصات'!C7) | D32: 305101.85 | E32: 123189.6 | F32: 125522.17 | G32: 35483.17 | H32: 31784.77 | I32: =ROUND(SUM(D32:H32)*GAPct,2) | J32: =SUM(D32:I32) | K32: =IF(AND(C32="",J32=0),"",SUM($J$31:J32)) | L32: =IF(C32="","",N('سجل المستخلصات'!K7)) | M32: =IF(OR(L32="",K32=""),"",L32-K32) | N32: =IF(OR(M32="",N(L32)=0),"",M32/L32) | O32: =IF(C32="","",BAC*N('سجل المستخلصات'!L7)) | P32: =IF(OR(O32="",N(K32)=0),"",O32/K32) | Q32: =IF(P32="","",IF(P32>0,BAC/P32,BAC)) | R32: =IF(Q32="","",RevisedContract-Q32) | S32: =IF(C32="","",SUMIF('سجل المستخلصات'!$A$6:$A$25,"<="&B32,'سجل المستخلصات'!$AA$6:$AA$25)+IF(AND(AdvDate<>"",N(AdvDate)<=N(C32)),AdvAmount,0)-N(K32))
B33: 3 | C33: =IF('سجل المستخلصات'!C8="","",'سجل المستخلصات'!C8) | D33: 308771.43 | E33: 124671.25 | F33: 127031.87 | G33: 35909.95 | H33: 32167.06 | I33: =ROUND(SUM(D33:H33)*GAPct,2) | J33: =SUM(D33:I33) | K33: =IF(AND(C33="",J33=0),"",SUM($J$31:J33)) | L33: =IF(C33="","",N('سجل المستخلصات'!K8)) | M33: =IF(OR(L33="",K33=""),"",L33-K33) | N33: =IF(OR(M33="",N(L33)=0),"",M33/L33) | O33: =IF(C33="","",BAC*N('سجل المستخلصات'!L8)) | P33: =IF(OR(O33="",N(K33)=0),"",O33/K33) | Q33: =IF(P33="","",IF(P33>0,BAC/P33,BAC)) | R33: =IF(Q33="","",RevisedContract-Q33) | S33: =IF(C33="","",SUMIF('سجل المستخلصات'!$A$6:$A$25,"<="&B33,'سجل المستخلصات'!$AA$6:$AA$25)+IF(AND(AdvDate<>"",N(AdvDate)<=N(C33)),AdvAmount,0)-N(K33))
B34: 4 | C34: =IF('سجل المستخلصات'!C9="","",'سجل المستخلصات'!C9) | D34: 278313.98 | E34: 112373.58 | F34: 114501.35 | G34: 32367.76 | H34: 28994.08 | I34: =ROUND(SUM(D34:H34)*GAPct,2) | J34: =SUM(D34:I34) | K34: =IF(AND(C34="",J34=0),"",SUM($J$31:J34)) | L34: =IF(C34="","",N('سجل المستخلصات'!K9)) | M34: =IF(OR(L34="",K34=""),"",L34-K34) | N34: =IF(OR(M34="",N(L34)=0),"",M34/L34) | O34: =IF(C34="","",BAC*N('سجل المستخلصات'!L9)) | P34: =IF(OR(O34="",N(K34)=0),"",O34/K34) | Q34: =IF(P34="","",IF(P34>0,BAC/P34,BAC)) | R34: =IF(Q34="","",RevisedContract-Q34) | S34: =IF(C34="","",SUMIF('سجل المستخلصات'!$A$6:$A$25,"<="&B34,'سجل المستخلصات'!$AA$6:$AA$25)+IF(AND(AdvDate<>"",N(AdvDate)<=N(C34)),AdvAmount,0)-N(K34))
B35: 5 | C35: =IF('سجل المستخلصات'!C10="","",'سجل المستخلصات'!C10) | D35: 278313.91 | E35: 112373.55 | F35: 114501.32 | G35: 32367.75 | H35: 28994.07 | I35: =ROUND(SUM(D35:H35)*GAPct,2) | J35: =SUM(D35:I35) | K35: =IF(AND(C35="",J35=0),"",SUM($J$31:J35)) | L35: =IF(C35="","",N('سجل المستخلصات'!K10)) | M35: =IF(OR(L35="",K35=""),"",L35-K35) | N35: =IF(OR(M35="",N(L35)=0),"",M35/L35) | O35: =IF(C35="","",BAC*N('سجل المستخلصات'!L10)) | P35: =IF(OR(O35="",N(K35)=0),"",O35/K35) | Q35: =IF(P35="","",IF(P35>0,BAC/P35,BAC)) | R35: =IF(Q35="","",RevisedContract-Q35) | S35: =IF(C35="","",SUMIF('سجل المستخلصات'!$A$6:$A$25,"<="&B35,'سجل المستخلصات'!$AA$6:$AA$25)+IF(AND(AdvDate<>"",N(AdvDate)<=N(C35)),AdvAmount,0)-N(K35))
B36: 6 | C36: =IF('سجل المستخلصات'!C11="","",'سجل المستخلصات'!C11) | D36: 311906.57 | E36: 125937.11 | F36: 128321.7 | G36: 36274.56 | H36: 32493.67 | I36: =ROUND(SUM(D36:H36)*GAPct,2) | J36: =SUM(D36:I36) | K36: =IF(AND(C36="",J36=0),"",SUM($J$31:J36)) | L36: =IF(C36="","",N('سجل المستخلصات'!K11)) | M36: =IF(OR(L36="",K36=""),"",L36-K36) | N36: =IF(OR(M36="",N(L36)=0),"",M36/L36) | O36: =IF(C36="","",BAC*N('سجل المستخلصات'!L11)) | P36: =IF(OR(O36="",N(K36)=0),"",O36/K36) | Q36: =IF(P36="","",IF(P36>0,BAC/P36,BAC)) | R36: =IF(Q36="","",RevisedContract-Q36) | S36: =IF(C36="","",SUMIF('سجل المستخلصات'!$A$6:$A$25,"<="&B36,'سجل المستخلصات'!$AA$6:$AA$25)+IF(AND(AdvDate<>"",N(AdvDate)<=N(C36)),AdvAmount,0)-N(K36))
B37: 7 | C37: =IF('سجل المستخلصات'!C12="","",'سجل المستخلصات'!C12) | I37: =ROUND(SUM(D37:H37)*GAPct,2) | J37: =SUM(D37:I37) | K37: =IF(AND(C37="",J37=0),"",SUM($J$31:J37)) | L37: =IF(C37="","",N('سجل المستخلصات'!K12)) | M37: =IF(OR(L37="",K37=""),"",L37-K37) | N37: =IF(OR(M37="",N(L37)=0),"",M37/L37) | O37: =IF(C37="","",BAC*N('سجل المستخلصات'!L12)) | P37: =IF(OR(O37="",N(K37)=0),"",O37/K37) | Q37: =IF(P37="","",IF(P37>0,BAC/P37,BAC)) | R37: =IF(Q37="","",RevisedContract-Q37) | S37: =IF(C37="","",SUMIF('سجل المستخلصات'!$A$6:$A$25,"<="&B37,'سجل المستخلصات'!$AA$6:$AA$25)+IF(AND(AdvDate<>"",N(AdvDate)<=N(C37)),AdvAmount,0)-N(K37))
B38: 8 | C38: =IF('سجل المستخلصات'!C13="","",'سجل المستخلصات'!C13) | I38: =ROUND(SUM(D38:H38)*GAPct,2) | J38: =SUM(D38:I38) | K38: =IF(AND(C38="",J38=0),"",SUM($J$31:J38)) | L38: =IF(C38="","",N('سجل المستخلصات'!K13)) | M38: =IF(OR(L38="",K38=""),"",L38-K38) | N38: =IF(OR(M38="",N(L38)=0),"",M38/L38) | O38: =IF(C38="","",BAC*N('سجل المستخلصات'!L13)) | P38: =IF(OR(O38="",N(K38)=0),"",O38/K38) | Q38: =IF(P38="","",IF(P38>0,BAC/P38,BAC)) | R38: =IF(Q38="","",RevisedContract-Q38) | S38: =IF(C38="","",SUMIF('سجل المستخلصات'!$A$6:$A$25,"<="&B38,'سجل المستخلصات'!$AA$6:$AA$25)+IF(AND(AdvDate<>"",N(AdvDate)<=N(C38)),AdvAmount,0)-N(K38))
B39: 9 | C39: =IF('سجل المستخلصات'!C14="","",'سجل المستخلصات'!C14) | I39: =ROUND(SUM(D39:H39)*GAPct,2) | J39: =SUM(D39:I39) | K39: =IF(AND(C39="",J39=0),"",SUM($J$31:J39)) | L39: =IF(C39="","",N('سجل المستخلصات'!K14)) | M39: =IF(OR(L39="",K39=""),"",L39-K39) | N39: =IF(OR(M39="",N(L39)=0),"",M39/L39) | O39: =IF(C39="","",BAC*N('سجل المستخلصات'!L14)) | P39: =IF(OR(O39="",N(K39)=0),"",O39/K39) | Q39: =IF(P39="","",IF(P39>0,BAC/P39,BAC)) | R39: =IF(Q39="","",RevisedContract-Q39) | S39: =IF(C39="","",SUMIF('سجل المستخلصات'!$A$6:$A$25,"<="&B39,'سجل المستخلصات'!$AA$6:$AA$25)+IF(AND(AdvDate<>"",N(AdvDate)<=N(C39)),AdvAmount,0)-N(K39))
B40: 10 | C40: =IF('سجل المستخلصات'!C15="","",'سجل المستخلصات'!C15) | I40: =ROUND(SUM(D40:H40)*GAPct,2) | J40: =SUM(D40:I40) | K40: =IF(AND(C40="",J40=0),"",SUM($J$31:J40)) | L40: =IF(C40="","",N('سجل المستخلصات'!K15)) | M40: =IF(OR(L40="",K40=""),"",L40-K40) | N40: =IF(OR(M40="",N(L40)=0),"",M40/L40) | O40: =IF(C40="","",BAC*N('سجل المستخلصات'!L15)) | P40: =IF(OR(O40="",N(K40)=0),"",O40/K40) | Q40: =IF(P40="","",IF(P40>0,BAC/P40,BAC)) | R40: =IF(Q40="","",RevisedContract-Q40) | S40: =IF(C40="","",SUMIF('سجل المستخلصات'!$A$6:$A$25,"<="&B40,'سجل المستخلصات'!$AA$6:$AA$25)+IF(AND(AdvDate<>"",N(AdvDate)<=N(C40)),AdvAmount,0)-N(K40))
B41: 11 | C41: =IF('سجل المستخلصات'!C16="","",'سجل المستخلصات'!C16) | I41: =ROUND(SUM(D41:H41)*GAPct,2) | J41: =SUM(D41:I41) | K41: =IF(AND(C41="",J41=0),"",SUM($J$31:J41)) | L41: =IF(C41="","",N('سجل المستخلصات'!K16)) | M41: =IF(OR(L41="",K41=""),"",L41-K41) | N41: =IF(OR(M41="",N(L41)=0),"",M41/L41) | O41: =IF(C41="","",BAC*N('سجل المستخلصات'!L16)) | P41: =IF(OR(O41="",N(K41)=0),"",O41/K41) | Q41: =IF(P41="","",IF(P41>0,BAC/P41,BAC)) | R41: =IF(Q41="","",RevisedContract-Q41) | S41: =IF(C41="","",SUMIF('سجل المستخلصات'!$A$6:$A$25,"<="&B41,'سجل المستخلصات'!$AA$6:$AA$25)+IF(AND(AdvDate<>"",N(AdvDate)<=N(C41)),AdvAmount,0)-N(K41))
B42: 12 | C42: =IF('سجل المستخلصات'!C17="","",'سجل المستخلصات'!C17) | I42: =ROUND(SUM(D42:H42)*GAPct,2) | J42: =SUM(D42:I42) | K42: =IF(AND(C42="",J42=0),"",SUM($J$31:J42)) | L42: =IF(C42="","",N('سجل المستخلصات'!K17)) | M42: =IF(OR(L42="",K42=""),"",L42-K42) | N42: =IF(OR(M42="",N(L42)=0),"",M42/L42) | O42: =IF(C42="","",BAC*N('سجل المستخلصات'!L17)) | P42: =IF(OR(O42="",N(K42)=0),"",O42/K42) | Q42: =IF(P42="","",IF(P42>0,BAC/P42,BAC)) | R42: =IF(Q42="","",RevisedContract-Q42) | S42: =IF(C42="","",SUMIF('سجل المستخلصات'!$A$6:$A$25,"<="&B42,'سجل المستخلصات'!$AA$6:$AA$25)+IF(AND(AdvDate<>"",N(AdvDate)<=N(C42)),AdvAmount,0)-N(K42))
B43: 13 | C43: =IF('سجل المستخلصات'!C18="","",'سجل المستخلصات'!C18) | I43: =ROUND(SUM(D43:H43)*GAPct,2) | J43: =SUM(D43:I43) | K43: =IF(AND(C43="",J43=0),"",SUM($J$31:J43)) | L43: =IF(C43="","",N('سجل المستخلصات'!K18)) | M43: =IF(OR(L43="",K43=""),"",L43-K43) | N43: =IF(OR(M43="",N(L43)=0),"",M43/L43) | O43: =IF(C43="","",BAC*N('سجل المستخلصات'!L18)) | P43: =IF(OR(O43="",N(K43)=0),"",O43/K43) | Q43: =IF(P43="","",IF(P43>0,BAC/P43,BAC)) | R43: =IF(Q43="","",RevisedContract-Q43) | S43: =IF(C43="","",SUMIF('سجل المستخلصات'!$A$6:$A$25,"<="&B43,'سجل المستخلصات'!$AA$6:$AA$25)+IF(AND(AdvDate<>"",N(AdvDate)<=N(C43)),AdvAmount,0)-N(K43))
B44: 14 | C44: =IF('سجل المستخلصات'!C19="","",'سجل المستخلصات'!C19) | I44: =ROUND(SUM(D44:H44)*GAPct,2) | J44: =SUM(D44:I44) | K44: =IF(AND(C44="",J44=0),"",SUM($J$31:J44)) | L44: =IF(C44="","",N('سجل المستخلصات'!K19)) | M44: =IF(OR(L44="",K44=""),"",L44-K44) | N44: =IF(OR(M44="",N(L44)=0),"",M44/L44) | O44: =IF(C44="","",BAC*N('سجل المستخلصات'!L19)) | P44: =IF(OR(O44="",N(K44)=0),"",O44/K44) | Q44: =IF(P44="","",IF(P44>0,BAC/P44,BAC)) | R44: =IF(Q44="","",RevisedContract-Q44) | S44: =IF(C44="","",SUMIF('سجل المستخلصات'!$A$6:$A$25,"<="&B44,'سجل المستخلصات'!$AA$6:$AA$25)+IF(AND(AdvDate<>"",N(AdvDate)<=N(C44)),AdvAmount,0)-N(K44))
B45: 15 | C45: =IF('سجل المستخلصات'!C20="","",'سجل المستخلصات'!C20) | I45: =ROUND(SUM(D45:H45)*GAPct,2) | J45: =SUM(D45:I45) | K45: =IF(AND(C45="",J45=0),"",SUM($J$31:J45)) | L45: =IF(C45="","",N('سجل المستخلصات'!K20)) | M45: =IF(OR(L45="",K45=""),"",L45-K45) | N45: =IF(OR(M45="",N(L45)=0),"",M45/L45) | O45: =IF(C45="","",BAC*N('سجل المستخلصات'!L20)) | P45: =IF(OR(O45="",N(K45)=0),"",O45/K45) | Q45: =IF(P45="","",IF(P45>0,BAC/P45,BAC)) | R45: =IF(Q45="","",RevisedContract-Q45) | S45: =IF(C45="","",SUMIF('سجل المستخلصات'!$A$6:$A$25,"<="&B45,'سجل المستخلصات'!$AA$6:$AA$25)+IF(AND(AdvDate<>"",N(AdvDate)<=N(C45)),AdvAmount,0)-N(K45))
B46: 16 | C46: =IF('سجل المستخلصات'!C21="","",'سجل المستخلصات'!C21) | I46: =ROUND(SUM(D46:H46)*GAPct,2) | J46: =SUM(D46:I46) | K46: =IF(AND(C46="",J46=0),"",SUM($J$31:J46)) | L46: =IF(C46="","",N('سجل المستخلصات'!K21)) | M46: =IF(OR(L46="",K46=""),"",L46-K46) | N46: =IF(OR(M46="",N(L46)=0),"",M46/L46) | O46: =IF(C46="","",BAC*N('سجل المستخلصات'!L21)) | P46: =IF(OR(O46="",N(K46)=0),"",O46/K46) | Q46: =IF(P46="","",IF(P46>0,BAC/P46,BAC)) | R46: =IF(Q46="","",RevisedContract-Q46) | S46: =IF(C46="","",SUMIF('سجل المستخلصات'!$A$6:$A$25,"<="&B46,'سجل المستخلصات'!$AA$6:$AA$25)+IF(AND(AdvDate<>"",N(AdvDate)<=N(C46)),AdvAmount,0)-N(K46))
B47: 17 | C47: =IF('سجل المستخلصات'!C22="","",'سجل المستخلصات'!C22) | I47: =ROUND(SUM(D47:H47)*GAPct,2) | J47: =SUM(D47:I47) | K47: =IF(AND(C47="",J47=0),"",SUM($J$31:J47)) | L47: =IF(C47="","",N('سجل المستخلصات'!K22)) | M47: =IF(OR(L47="",K47=""),"",L47-K47) | N47: =IF(OR(M47="",N(L47)=0),"",M47/L47) | O47: =IF(C47="","",BAC*N('سجل المستخلصات'!L22)) | P47: =IF(OR(O47="",N(K47)=0),"",O47/K47) | Q47: =IF(P47="","",IF(P47>0,BAC/P47,BAC)) | R47: =IF(Q47="","",RevisedContract-Q47) | S47: =IF(C47="","",SUMIF('سجل المستخلصات'!$A$6:$A$25,"<="&B47,'سجل المستخلصات'!$AA$6:$AA$25)+IF(AND(AdvDate<>"",N(AdvDate)<=N(C47)),AdvAmount,0)-N(K47))
B48: 18 | C48: =IF('سجل المستخلصات'!C23="","",'سجل المستخلصات'!C23) | I48: =ROUND(SUM(D48:H48)*GAPct,2) | J48: =SUM(D48:I48) | K48: =IF(AND(C48="",J48=0),"",SUM($J$31:J48)) | L48: =IF(C48="","",N('سجل المستخلصات'!K23)) | M48: =IF(OR(L48="",K48=""),"",L48-K48) | N48: =IF(OR(M48="",N(L48)=0),"",M48/L48) | O48: =IF(C48="","",BAC*N('سجل المستخلصات'!L23)) | P48: =IF(OR(O48="",N(K48)=0),"",O48/K48) | Q48: =IF(P48="","",IF(P48>0,BAC/P48,BAC)) | R48: =IF(Q48="","",RevisedContract-Q48) | S48: =IF(C48="","",SUMIF('سجل المستخلصات'!$A$6:$A$25,"<="&B48,'سجل المستخلصات'!$AA$6:$AA$25)+IF(AND(AdvDate<>"",N(AdvDate)<=N(C48)),AdvAmount,0)-N(K48))
... B50: 20 | C50: =IF('سجل المستخلصات'!C25="","",'سجل المستخلصات'!C25) | I50: =ROUND(SUM(D50:H50)*GAPct,2) | J50: =SUM(D50:I50) | K50: =IF(AND(C50="",J50=0),"",SUM($J$31:J50)) | L50: =IF(C50="","",N('سجل المستخلصات'!K25)) | M50: =IF(OR(L50="",K50=""),"",L50-K50) | N50: =IF(OR(M50="",N(L50)=0),"",M50/L50) | O50: =IF(C50="","",BAC*N('سجل المستخلصات'!L25)) | P50: =IF(OR(O50="",N(K50)=0),"",O50/K50) | Q50: =IF(P50="","",IF(P50>0,BAC/P50,BAC)) | R50: =IF(Q50="","",RevisedContract-Q50) | S50: =IF(C50="","",SUMIF('سجل المستخلصات'!$A$6:$A$25,"<="&B50,'سجل المستخلصات'!$AA$6:$AA$25)+IF(AND(AdvDate<>"",N(AdvDate)<=N(C50)),AdvAmount,0)-N(K50))
B51: الإجمالي | D51: =SUM(D31:D50) | E51: =SUM(E31:E50) | F51: =SUM(F31:F50) | G51: =SUM(G31:G50) | H51: =SUM(H31:H50) | I51: =SUM(I31:I50) | J51: =SUM(J31:J50)
B53: ثالثاً: مقارنة الموازنة بالفعلي حسب عنصر التكلفة
B54: عنصر التكلفة | D54: الموازنة | E54: الفعلي التراكمي | F54: المتبقي من الموازنة | G54: نسبة الاستهلاك | H54: مقارنة بنسبة الإنجاز
B55: المواد | D55: =E23 | E55: =D51 | F55: =D55-E55 | G55: =IF(D55>0,E55/D55,0) | H55: =IF(D55=0,"",IF(G55>N('سجل المستخلصات'!L26)+0.05,"⚠ استهلاك أعلى من الإنجاز","✔ ضمن المعدل"))
B56: العمالة | D56: =F23 | E56: =E51 | F56: =D56-E56 | G56: =IF(D56>0,E56/D56,0) | H56: =IF(D56=0,"",IF(G56>N('سجل المستخلصات'!L26)+0.05,"⚠ استهلاك أعلى من الإنجاز","✔ ضمن المعدل"))
B57: مقاولو الباطن | D57: =G23 | E57: =F51 | F57: =D57-E57 | G57: =IF(D57>0,E57/D57,0) | H57: =IF(D57=0,"",IF(G57>N('سجل المستخلصات'!L26)+0.05,"⚠ استهلاك أعلى من الإنجاز","✔ ضمن المعدل"))
B58: المعدات | D58: =H23 | E58: =G51 | F58: =D58-E58 | G58: =IF(D58>0,E58/D58,0) | H58: =IF(D58=0,"",IF(G58>N('سجل المستخلصات'!L26)+0.05,"⚠ استهلاك أعلى من الإنجاز","✔ ضمن المعدل"))
B59: مصروفات الموقع | D59: =I23 | E59: =H51 | F59: =D59-E59 | G59: =IF(D59>0,E59/D59,0) | H59: =IF(D59=0,"",IF(G59>N('سجل المستخلصات'!L26)+0.05,"⚠ استهلاك أعلى من الإنجاز","✔ ضمن المعدل"))
B60: المصروفات العمومية والإدارية | D60: =J24 | E60: =I51 | F60: =D60-E60 | G60: =IF(D60>0,E60/D60,0) | H60: =IF(D60=0,"",IF(G60>N('سجل المستخلصات'!L26)+0.05,"⚠ استهلاك أعلى من الإنجاز","✔ ضمن المعدل"))
B61: احتياطي الطوارئ | D61: =J25 | E61: =0 | F61: =D61-E61 | G61: =IF(D61>0,E61/D61,0) | H61: =IF(D61=0,"",IF(G61>N('سجل المستخلصات'!L26)+0.05,"⚠ استهلاك أعلى من الإنجاز","✔ ضمن المعدل"))
B62: الإجمالي | D62: =SUM(D55:D61) | E62: =SUM(E55:E61) | F62: =D62-E62 | G62: =IF(D62>0,E62/D62,0)
B65: رابعاً: ملخص الربحية ومؤشرات التكلفة
B66: إجمالي الموازنة عند الإنجاز (BAC) | D66: =BAC
B67: قيمة العقد المعدلة | D67: =RevisedContract
B68: الربح المخطط (على العقد المعدل) | D68: =D67-D66
B69: هامش الربح المخطط | D69: =IF(D67>0,D68/D67,0)
B70: التكلفة الفعلية التراكمية | D70: =J51
B71: الإيراد التراكمي (إجمالي قيمة الأعمال) | D71: =N('سجل المستخلصات'!K26)
B72: الربح الفعلي التراكمي | D72: =D71-D70
B73: هامش الربح الفعلي | D73: =IF(D71>0,D72/D71,0)
B74: مؤشر أداء التكلفة (CPI) | D74: =IF(D70>0,BAC*N('سجل المستخلصات'!L26)/D70,0)
B75: التكلفة المتوقعة عند الإنجاز (EAC) | D75: =IF(D74>0,BAC/D74,BAC)
B76: الربح المتوقع عند الإنجاز | D76: =D67-D75
B77: هامش الربح المتوقع | D77: =IF(D67>0,D76/D67,0)
B78: الموقف النقدي الحالي | D78: =SUM('سجل المستخلصات'!AA6:AA25)+IF(AdvDate<>"",AdvAmount,0)-D70
B79: حالة التكلفة | D79: =IF(D70=0,"لا توجد تكاليف مسجلة",IF(D74<0.95,"⚠ تجاوز في التكاليف",IF(D74<1,"متابعة — قريب من الموازنة","✔ ضمن الموازنة")))

Sheet سجل المستخلصات
A1: 🗂 سجل المستخلصات — مشروع رقم 01 (يُحدَّث آلياً من شيتات المستخلصات ويغذي ملف التقارير)
A2: =IF('بيانات العقد'!$C$5="","مشروع رقم 01 — أدخل بيانات العقد",'بيانات العقد'!$C$5&" | عقد رقم: "&'بيانات العقد'!$C$6)&" | المبالغ بـ "&'بيانات العقد'!$C$14
B3: ⚙ بيانات العقد | D3: 📋 جدول الكميات | F3: 🔁 التغييرية | H3: ✂ الاستقطاعات | J3: 💰 الموازنة | AI3: آخر مستخلص: | AJ3: =SUMPRODUCT(MAX((C6:C25<>"")*A6:A25))
A4: بيانات المستخلص | G4: قيمة الأعمال ونسب الإنجاز | O4: الاستقطاعات (تراكمي) | U4: صافي المستحق والضرائب | AA4: التحصيل | AF4: الفوترة والمستندات
A5: رقم المستخلص | B5: الفترة من | C5: الفترة إلى | D5: تاريخ التقديم | E5: تاريخ الاعتماد | F5: حالة المستخلص | G5: قيمة الأعمال المنفذة التراكمية | H5: أعمال الفترة | I5: الأوامر التغييرية التراكمية | J5: رصيد المواد بالموقع | K5: إجمالي القيمة التراكمية | L5: نسبة الإنجاز الفعلية | M5: نسبة الإنجاز المخططة | N5: الانحراف عن المخطط | O5: استرداد الدفعة المقدمة التراكمي | P5: ضمان الأعمال المحتسب | Q5: المفرج عنه من الضمان | R5: صافي الضمان المحتجز | S5: الاستقطاعات الفنية المحتجزة | T5: الغرامات والخصومات التراكمية | U5: الصافي التراكمي قبل الضرائب | V5: ضريبة القيمة المضافة | W5: ضريبة الاستقطاع (غير المقيم) | X5: صافي المستحق التراكمي | Y5: المعتمد في المستخلصات السابقة | Z5: صافي المستحق للمستخلص الحالي | AA5: المبلغ المحصل | AB5: تاريخ التحصيل | AC5: المتبقي غير المحصل | AD5: مدة التحصيل (يوم) | AE5: حالة التحصيل | AF5: رقم الفاتورة الضريبية | AG5: حالة المستندات النظامية
A6: 1 | B6: =IF(OR('مستخلص 01'!$J$7="",'مستخلص 01'!$J$6=""),"",'مستخلص 01'!$J$6) | C6: =IF('مستخلص 01'!$J$7="","",'مستخلص 01'!$J$7) | D6: =IF(OR('مستخلص 01'!$J$7="",'مستخلص 01'!$J$8=""),"",'مستخلص 01'!$J$8) | E6: =IF(OR('مستخلص 01'!$J$7="",'مستخلص 01'!$J$9=""),"",'مستخلص 01'!$J$9) | F6: =IF(OR('مستخلص 01'!$J$7="",'مستخلص 01'!$J$5=""),"",'مستخلص 01'!$J$5) | G6: =IF('مستخلص 01'!$J$7="","",'مستخلص 01'!$L$19) | H6: =IF('مستخلص 01'!$J$7="","",'مستخلص 01'!$J$19) | I6: =IF('مستخلص 01'!$J$7="","",'مستخلص 01'!$L$20) | J6: =IF('مستخلص 01'!$J$7="","",'مستخلص 01'!$L$21) | K6: =IF('مستخلص 01'!$J$7="","",'مستخلص 01'!$L$22) | L6: =IF('مستخلص 01'!$J$7="","",'مستخلص 01'!$L$6) | M6: =IF(OR('مستخلص 01'!$J$7="",'مستخلص 01'!$L$8=""),"",'مستخلص 01'!$L$8) | N6: =IF(OR('مستخلص 01'!$J$7="",M6=""),"",L6-M6) | O6: =IF('مستخلص 01'!$J$7="","",-'مستخلص 01'!$L$23) | P6: =IF('مستخلص 01'!$J$7="","",-'مستخلص 01'!$L$24) | Q6: =IF('مستخلص 01'!$J$7="","",'مستخلص 01'!$L$25) | R6: =IF('مستخلص 01'!$J$7="","",P6-Q6) | S6: =IF('مستخلص 01'!$J$7="","",-'مستخلص 01'!$L$26) | T6: =IF('مستخلص 01'!$J$7="","",-'مستخلص 01'!$L$27) | U6: =IF('مستخلص 01'!$J$7="","",'مستخلص 01'!$L$28) | V6: =IF('مستخلص 01'!$J$7="","",'مستخلص 01'!$L$29) | W6: =IF('مستخلص 01'!$J$7="","",-'مستخلص 01'!$L$30) | X6: =IF('مستخلص 01'!$J$7="","",'مستخلص 01'!$L$31) | Y6: =IF('مستخلص 01'!$J$7="","",'مستخلص 01'!$H$31) | Z6: =IF('مستخلص 01'!$J$7="","",'مستخلص 01'!$J$31) | AA6: =IF('مستخلص 01'!$J$7="","",N('مستخلص 01'!$E$15)) | AB6: =IF(OR('مستخلص 01'!$J$7="",'مستخلص 01'!$K$15=""),"",'مستخلص 01'!$K$15) | AC6: =IF('مستخلص 01'!$J$7="","",Z6-AA6) | AD6: =IF(OR(AB6="",E6=""),"",AB6-E6) | AE6: =IF('مستخلص 01'!$J$7="","",IF(N(AA6)=0,IF(E6="","⏳ بانتظار الاعتماد","✖ غير محصل"),IF(AC6<=1,"✔ محصل بالكامل","⚠ محصل جزئياً"))) | AF6: =IF(OR('مستخلص 01'!$J$7="",'مستخلص 01'!$E$16=""),"",'مستخلص 01'!$E$16) | AG6: =IF('مستخلص 01'!$J$7="","",'مستخلص 01'!$E$43)
A7: 2 | B7: =IF(OR('مستخلص 02'!$J$7="",'مستخلص 02'!$J$6=""),"",'مستخلص 02'!$J$6) | C7: =IF('مستخلص 02'!$J$7="","",'مستخلص 02'!$J$7) | D7: =IF(OR('مستخلص 02'!$J$7="",'مستخلص 02'!$J$8=""),"",'مستخلص 02'!$J$8) | E7: =IF(OR('مستخلص 02'!$J$7="",'مستخلص 02'!$J$9=""),"",'مستخلص 02'!$J$9) | F7: =IF(OR('مستخلص 02'!$J$7="",'مستخلص 02'!$J$5=""),"",'مستخلص 02'!$J$5) | G7: =IF('مستخلص 02'!$J$7="","",'مستخلص 02'!$L$19) | H7: =IF('مستخلص 02'!$J$7="","",'مستخلص 02'!$J$19) | I7: =IF('مستخلص 02'!$J$7="","",'مستخلص 02'!$L$20) | J7: =IF('مستخلص 02'!$J$7="","",'مستخلص 02'!$L$21) | K7: =IF('مستخلص 02'!$J$7="","",'مستخلص 02'!$L$22) | L7: =IF('مستخلص 02'!$J$7="","",'مستخلص 02'!$L$6) | M7: =IF(OR('مستخلص 02'!$J$7="",'مستخلص 02'!$L$8=""),"",'مستخلص 02'!$L$8) | N7: =IF(OR('مستخلص 02'!$J$7="",M7=""),"",L7-M7) | O7: =IF('مستخلص 02'!$J$7="","",-'مستخلص 02'!$L$23) | P7: =IF('مستخلص 02'!$J$7="","",-'مستخلص 02'!$L$24) | Q7: =IF('مستخلص 02'!$J$7="","",'مستخلص 02'!$L$25) | R7: =IF('مستخلص 02'!$J$7="","",P7-Q7) | S7: =IF('مستخلص 02'!$J$7="","",-'مستخلص 02'!$L$26) | T7: =IF('مستخلص 02'!$J$7="","",-'مستخلص 02'!$L$27) | U7: =IF('مستخلص 02'!$J$7="","",'مستخلص 02'!$L$28) | V7: =IF('مستخلص 02'!$J$7="","",'مستخلص 02'!$L$29) | W7: =IF('مستخلص 02'!$J$7="","",-'مستخلص 02'!$L$30) | X7: =IF('مستخلص 02'!$J$7="","",'مستخلص 02'!$L$31) | Y7: =IF('مستخلص 02'!$J$7="","",'مستخلص 02'!$H$31) | Z7: =IF('مستخلص 02'!$J$7="","",'مستخلص 02'!$J$31) | AA7: =IF('مستخلص 02'!$J$7="","",N('مستخلص 02'!$E$15)) | AB7: =IF(OR('مستخلص 02'!$J$7="",'مستخلص 02'!$K$15=""),"",'مستخلص 02'!$K$15) | AC7: =IF('مستخلص 02'!$J$7="","",Z7-AA7) | AD7: =IF(OR(AB7="",E7=""),"",AB7-E7) | AE7: =IF('مستخلص 02'!$J$7="","",IF(N(AA7)=0,IF(E7="","⏳ بانتظار الاعتماد","✖ غير محصل"),IF(AC7<=1,"✔ محصل بالكامل","⚠ محصل جزئياً"))) | AF7: =IF(OR('مستخلص 02'!$J$7="",'مستخلص 02'!$E$16=""),"",'مستخلص 02'!$E$16) | AG7: =IF('مستخلص 02'!$J$7="","",'مستخلص 02'!$E$43)
A8: 3 | B8: =IF(OR('مستخلص 03'!$J$7="",'مستخلص 03'!$J$6=""),"",'مستخلص 03'!$J$6) | C8: =IF('مستخلص 03'!$J$7="","",'مستخلص 03'!$J$7) | D8: =IF(OR('مستخلص 03'!$J$7="",'مستخلص 03'!$J$8=""),"",'مستخلص 03'!$J$8) | E8: =IF(OR('مستخلص 03'!$J$7="",'مستخلص 03'!$J$9=""),"",'مستخلص 03'!$J$9) | F8: =IF(OR('مستخلص 03'!$J$7="",'مستخلص 03'!$J$5=""),"",'مستخلص 03'!$J$5) | G8: =IF('مستخلص 03'!$J$7="","",'مستخلص 03'!$L$19) | H8: =IF('مستخلص 03'!$J$7="","",'مستخلص 03'!$J$19) | I8: =IF('مستخلص 03'!$J$7="","",'مستخلص 03'!$L$20) | J8: =IF('مستخلص 03'!$J$7="","",'مستخلص 03'!$L$21) | K8: =IF('مستخلص 03'!$J$7="","",'مستخلص 03'!$L$22) | L8: =IF('مستخلص 03'!$J$7="","",'مستخلص 03'!$L$6) | M8: =IF(OR('مستخلص 03'!$J$7="",'مستخلص 03'!$L$8=""),"",'مستخلص 03'!$L$8) | N8: =IF(OR('مستخلص 03'!$J$7="",M8=""),"",L8-M8) | O8: =IF('مستخلص 03'!$J$7="","",-'مستخلص 03'!$L$23) | P8: =IF('مستخلص 03'!$J$7="","",-'مستخلص 03'!$L$24) | Q8: =IF('مستخلص 03'!$J$7="","",'مستخلص 03'!$L$25) | R8: =IF('مستخلص 03'!$J$7="","",P8-Q8) | S8: =IF('مستخلص 03'!$J$7="","",-'مستخلص 03'!$L$26) | T8: =IF('مستخلص 03'!$J$7="","",-'مستخلص 03'!$L$27) | U8: =IF('مستخلص 03'!$J$7="","",'مستخلص 03'!$L$28) | V8: =IF('مستخلص 03'!$J$7="","",'مستخلص 03'!$L$29) | W8: =IF('مستخلص 03'!$J$7="","",-'مستخلص 03'!$L$30) | X8: =IF('مستخلص 03'!$J$7="","",'مستخلص 03'!$L$31) | Y8: =IF('مستخلص 03'!$J$7="","",'مستخلص 03'!$H$31) | Z8: =IF('مستخلص 03'!$J$7="","",'مستخلص 03'!$J$31) | AA8: =IF('مستخلص 03'!$J$7="","",N('مستخلص 03'!$E$15)) | AB8: =IF(OR('مستخلص 03'!$J$7="",'مستخلص 03'!$K$15=""),"",'مستخلص 03'!$K$15) | AC8: =IF('مستخلص 03'!$J$7="","",Z8-AA8) | AD8: =IF(OR(AB8="",E8=""),"",AB8-E8) | AE8: =IF('مستخلص 03'!$J$7="","",IF(N(AA8)=0,IF(E8="","⏳ بانتظار الاعتماد","✖ غير محصل"),IF(AC8<=1,"✔ محصل بالكامل","⚠ محصل جزئياً"))) | AF8: =IF(OR('مستخلص 03'!$J$7="",'مستخلص 03'!$E$16=""),"",'مستخلص 03'!$E$16) | AG8: =IF('مستخلص 03'!$J$7="","",'مستخلص 03'!$E$43)
A9: 4 | B9: =IF(OR('مستخلص 04'!$J$7="",'مستخلص 04'!$J$6=""),"",'مستخلص 04'!$J$6) | C9: =IF('مستخلص 04'!$J$7="","",'مستخلص 04'!$J$7) | D9: =IF(OR('مستخلص 04'!$J$7="",'مستخلص 04'!$J$8=""),"",'مستخلص 04'!$J$8) | E9: =IF(OR('مستخلص 04'!$J$7="",'مستخلص 04'!$J$9=""),"",'مستخلص 04'!$J$9) | F9: =IF(OR('مستخلص 04'!$J$7="",'مستخلص 04'!$J$5=""),"",'مستخلص 04'!$J$5) | G9: =IF('مستخلص 04'!$J$7="","",'مستخلص 04'!$L$19) | H9: =IF('مستخلص 04'!$J$7="","",'مستخلص 04'!$J$19) | I9: =IF('مستخلص 04'!$J$7="","",'مستخلص 04'!$L$20) | J9: =IF('مستخلص 04'!$J$7="","",'مستخلص 04'!$L$21) | K9: =IF('مستخلص 04'!$J$7="","",'مستخلص 04'!$L$22) | L9: =IF('مستخلص 04'!$J$7="","",'مستخلص 04'!$L$6) | M9: =IF(OR('مستخلص 04'!$J$7="",'مستخلص 04'!$L$8=""),"",'مستخلص 04'!$L$8) | N9: =IF(OR('مستخلص 04'!$J$7="",M9=""),"",L9-M9) | O9: =IF('مستخلص 04'!$J$7="","",-'مستخلص 04'!$L$23) | P9: =IF('مستخلص 04'!$J$7="","",-'مستخلص 04'!$L$24) | Q9: =IF('مستخلص 04'!$J$7="","",'مستخلص 04'!$L$25) | R9: =IF('مستخلص 04'!$J$7="","",P9-Q9) | S9: =IF('مستخلص 04'!$J$7="","",-'مستخلص 04'!$L$26) | T9: =IF('مستخلص 04'!$J$7="","",-'مستخلص 04'!$L$27) | U9: =IF('مستخلص 04'!$J$7="","",'مستخلص 04'!$L$28) | V9: =IF('مستخلص 04'!$J$7="","",'مستخلص 04'!$L$29) | W9: =IF('مستخلص 04'!$J$7="","",-'مستخلص 04'!$L$30) | X9: =IF('مستخلص 04'!$J$7="","",'مستخلص 04'!$L$31) | Y9: =IF('مستخلص 04'!$J$7="","",'مستخلص 04'!$H$31) | Z9: =IF('مستخلص 04'!$J$7="","",'مستخلص 04'!$J$31) | AA9: =IF('مستخلص 04'!$J$7="","",N('مستخلص 04'!$E$15)) | AB9: =IF(OR('مستخلص 04'!$J$7="",'مستخلص 04'!$K$15=""),"",'مستخلص 04'!$K$15) | AC9: =IF('مستخلص 04'!$J$7="","",Z9-AA9) | AD9: =IF(OR(AB9="",E9=""),"",AB9-E9) | AE9: =IF('مستخلص 04'!$J$7="","",IF(N(AA9)=0,IF(E9="","⏳ بانتظار الاعتماد","✖ غير محصل"),IF(AC9<=1,"✔ محصل بالكامل","⚠ محصل جزئياً"))) | AF9: =IF(OR('مستخلص 04'!$J$7="",'مستخلص 04'!$E$16=""),"",'مستخلص 04'!$E$16) | AG9: =IF('مستخلص 04'!$J$7="","",'مستخلص 04'!$E$43)
A10: 5 | B10: =IF(OR('مستخلص 05'!$J$7="",'مستخلص 05'!$J$6=""),"",'مستخلص 05'!$J$6) | C10: =IF('مستخلص 05'!$J$7="","",'مستخلص 05'!$J$7) | D10: =IF(OR('مستخلص 05'!$J$7="",'مستخلص 05'!$J$8=""),"",'مستخلص 05'!$J$8) | E10: =IF(OR('مستخلص 05'!$J$7="",'مستخلص 05'!$J$9=""),"",'مستخلص 05'!$J$9) | F10: =IF(OR('مستخلص 05'!$J$7="",'مستخلص 05'!$J$5=""),"",'مستخلص 05'!$J$5) | G10: =IF('مستخلص 05'!$J$7="","",'مستخلص 05'!$L$19) | H10: =IF('مستخلص 05'!$J$7="","",'مستخلص 05'!$J$19) | I10: =IF('مستخلص 05'!$J$7="","",'مستخلص 05'!$L$20) | J10: =IF('مستخلص 05'!$J$7="","",'مستخلص 05'!$L$21) | K10: =IF('مستخلص 05'!$J$7="","",'مستخلص 05'!$L$22) | L10: =IF('مستخلص 05'!$J$7="","",'مستخلص 05'!$L$6) | M10: =IF(OR('مستخلص 05'!$J$7="",'مستخلص 05'!$L$8=""),"",'مستخلص 05'!$L$8) | N10: =IF(OR('مستخلص 05'!$J$7="",M10=""),"",L10-M10) | O10: =IF('مستخلص 05'!$J$7="","",-'مستخلص 05'!$L$23) | P10: =IF('مستخلص 05'!$J$7="","",-'مستخلص 05'!$L$24) | Q10: =IF('مستخلص 05'!$J$7="","",'مستخلص 05'!$L$25) | R10: =IF('مستخلص 05'!$J$7="","",P10-Q10) | S10: =IF('مستخلص 05'!$J$7="","",-'مستخلص 05'!$L$26) | T10: =IF('مستخلص 05'!$J$7="","",-'مستخلص 05'!$L$27) | U10: =IF('مستخلص 05'!$J$7="","",'مستخلص 05'!$L$28) | V10: =IF('مستخلص 05'!$J$7="","",'مستخلص 05'!$L$29) | W10: =IF('مستخلص 05'!$J$7="","",-'مستخلص 05'!$L$30) | X10: =IF('مستخلص 05'!$J$7="","",'مستخلص 05'!$L$31) | Y10: =IF('مستخلص 05'!$J$7="","",'مستخلص 05'!$H$31) | Z10: =IF('مستخلص 05'!$J$7="","",'مستخلص 05'!$J$31) | AA10: =IF('مستخلص 05'!$J$7="","",N('مستخلص 05'!$E$15)) | AB10: =IF(OR('مستخلص 05'!$J$7="",'مستخلص 05'!$K$15=""),"",'مستخلص 05'!$K$15) | AC10: =IF('مستخلص 05'!$J$7="","",Z10-AA10) | AD10: =IF(OR(AB10="",E10=""),"",AB10-E10) | AE10: =IF('مستخلص 05'!$J$7="","",IF(N(AA10)=0,IF(E10="","⏳ بانتظار الاعتماد","✖ غير محصل"),IF(AC10<=1,"✔ محصل بالكامل","⚠ محصل جزئياً"))) | AF10: =IF(OR('مستخلص 05'!$J$7="",'مستخلص 05'!$E$16=""),"",'مستخلص 05'!$E$16) | AG10: =IF('مستخلص 05'!$J$7="","",'مستخلص 05'!$E$43)
A11: 6 | B11: =IF(OR('مستخلص 06'!$J$7="",'مستخلص 06'!$J$6=""),"",'مستخلص 06'!$J$6) | C11: =IF('مستخلص 06'!$J$7="","",'مستخلص 06'!$J$7) | D11: =IF(OR('مستخلص 06'!$J$7="",'مستخلص 06'!$J$8=""),"",'مستخلص 06'!$J$8) | E11: =IF(OR('مستخلص 06'!$J$7="",'مستخلص 06'!$J$9=""),"",'مستخلص 06'!$J$9) | F11: =IF(OR('مستخلص 06'!$J$7="",'مستخلص 06'!$J$5=""),"",'مستخلص 06'!$J$5) | G11: =IF('مستخلص 06'!$J$7="","",'مستخلص 06'!$L$19) | H11: =IF('مستخلص 06'!$J$7="","",'مستخلص 06'!$J$19) | I11: =IF('مستخلص 06'!$J$7="","",'مستخلص 06'!$L$20) | J11: =IF('مستخلص 06'!$J$7="","",'مستخلص 06'!$L$21) | K11: =IF('مستخلص 06'!$J$7="","",'مستخلص 06'!$L$22) | L11: =IF('مستخلص 06'!$J$7="","",'مستخلص 06'!$L$6) | M11: =IF(OR('مستخلص 06'!$J$7="",'مستخلص 06'!$L$8=""),"",'مستخلص 06'!$L$8) | N11: =IF(OR('مستخلص 06'!$J$7="",M11=""),"",L11-M11) | O11: =IF('مستخلص 06'!$J$7="","",-'مستخلص 06'!$L$23) | P11: =IF('مستخلص 06'!$J$7="","",-'مستخلص 06'!$L$24) | Q11: =IF('مستخلص 06'!$J$7="","",'مستخلص 06'!$L$25) | R11: =IF('مستخلص 06'!$J$7="","",P11-Q11) | S11: =IF('مستخلص 06'!$J$7="","",-'مستخلص 06'!$L$26) | T11: =IF('مستخلص 06'!$J$7="","",-'مستخلص 06'!$L$27) | U11: =IF('مستخلص 06'!$J$7="","",'مستخلص 06'!$L$28) | V11: =IF('مستخلص 06'!$J$7="","",'مستخلص 06'!$L$29) | W11: =IF('مستخلص 06'!$J$7="","",-'مستخلص 06'!$L$30) | X11: =IF('مستخلص 06'!$J$7="","",'مستخلص 06'!$L$31) | Y11: =IF('مستخلص 06'!$J$7="","",'مستخلص 06'!$H$31) | Z11: =IF('مستخلص 06'!$J$7="","",'مستخلص 06'!$J$31) | AA11: =IF('مستخلص 06'!$J$7="","",N('مستخلص 06'!$E$15)) | AB11: =IF(OR('مستخلص 06'!$J$7="",'مستخلص 06'!$K$15=""),"",'مستخلص 06'!$K$15) | AC11: =IF('مستخلص 06'!$J$7="","",Z11-AA11) | AD11: =IF(OR(AB11="",E11=""),"",AB11-E11) | AE11: =IF('مستخلص 06'!$J$7="","",IF(N(AA11)=0,IF(E11="","⏳ بانتظار الاعتماد","✖ غير محصل"),IF(AC11<=1,"✔ محصل بالكامل","⚠ محصل جزئياً"))) | AF11: =IF(OR('مستخلص 06'!$J$7="",'مستخلص 06'!$E$16=""),"",'مستخلص 06'!$E$16) | AG11: =IF('مستخلص 06'!$J$7="","",'مستخلص 06'!$E$43)
A12: 7 | B12: =IF(OR('مستخلص 07'!$J$7="",'مستخلص 07'!$J$6=""),"",'مستخلص 07'!$J$6) | C12: =IF('مستخلص 07'!$J$7="","",'مستخلص 07'!$J$7) | D12: =IF(OR('مستخلص 07'!$J$7="",'مستخلص 07'!$J$8=""),"",'مستخلص 07'!$J$8) | E12: =IF(OR('مستخلص 07'!$J$7="",'مستخلص 07'!$J$9=""),"",'مستخلص 07'!$J$9) | F12: =IF(OR('مستخلص 07'!$J$7="",'مستخلص 07'!$J$5=""),"",'مستخلص 07'!$J$5) | G12: =IF('مستخلص 07'!$J$7="","",'مستخلص 07'!$L$19) | H12: =IF('مستخلص 07'!$J$7="","",'مستخلص 07'!$J$19) | I12: =IF('مستخلص 07'!$J$7="","",'مستخلص 07'!$L$20) | J12: =IF('مستخلص 07'!$J$7="","",'مستخلص 07'!$L$21) | K12: =IF('مستخلص 07'!$J$7="","",'مستخلص 07'!$L$22) | L12: =IF('مستخلص 07'!$J$7="","",'مستخلص 07'!$L$6) | M12: =IF(OR('مستخلص 07'!$J$7="",'مستخلص 07'!$L$8=""),"",'مستخلص 07'!$L$8) | N12: =IF(OR('مستخلص 07'!$J$7="",M12=""),"",L12-M12) | O12: =IF('مستخلص 07'!$J$7="","",-'مستخلص 07'!$L$23) | P12: =IF('مستخلص 07'!$J$7="","",-'مستخلص 07'!$L$24) | Q12: =IF('مستخلص 07'!$J$7="","",'مستخلص 07'!$L$25) | R12: =IF('مستخلص 07'!$J$7="","",P12-Q12) | S12: =IF('مستخلص 07'!$J$7="","",-'مستخلص 07'!$L$26) | T12: =IF('مستخلص 07'!$J$7="","",-'مستخلص 07'!$L$27) | U12: =IF('مستخلص 07'!$J$7="","",'مستخلص 07'!$L$28) | V12: =IF('مستخلص 07'!$J$7="","",'مستخلص 07'!$L$29) | W12: =IF('مستخلص 07'!$J$7="","",-'مستخلص 07'!$L$30) | X12: =IF('مستخلص 07'!$J$7="","",'مستخلص 07'!$L$31) | Y12: =IF('مستخلص 07'!$J$7="","",'مستخلص 07'!$H$31) | Z12: =IF('مستخلص 07'!$J$7="","",'مستخلص 07'!$J$31) | AA12: =IF('مستخلص 07'!$J$7="","",N('مستخلص 07'!$E$15)) | AB12: =IF(OR('مستخلص 07'!$J$7="",'مستخلص 07'!$K$15=""),"",'مستخلص 07'!$K$15) | AC12: =IF('مستخلص 07'!$J$7="","",Z12-AA12) | AD12: =IF(OR(AB12="",E12=""),"",AB12-E12) | AE12: =IF('مستخلص 07'!$J$7="","",IF(N(AA12)=0,IF(E12="","⏳ بانتظار الاعتماد","✖ غير محصل"),IF(AC12<=1,"✔ محصل بالكامل","⚠ محصل جزئياً"))) | AF12: =IF(OR('مستخلص 07'!$J$7="",'مستخلص 07'!$E$16=""),"",'مستخلص 07'!$E$16) | AG12: =IF('مستخلص 07'!$J$7="","",'مستخلص 07'!$E$43)
A13: 8 | B13: =IF(OR('مستخلص 08'!$J$7="",'مستخلص 08'!$J$6=""),"",'مستخلص 08'!$J$6) | C13: =IF('مستخلص 08'!$J$7="","",'مستخلص 08'!$J$7) | D13: =IF(OR('مستخلص 08'!$J$7="",'مستخلص 08'!$J$8=""),"",'مستخلص 08'!$J$8) | E13: =IF(OR('مستخلص 08'!$J$7="",'مستخلص 08'!$J$9=""),"",'مستخلص 08'!$J$9) | F13: =IF(OR('مستخلص 08'!$J$7="",'مستخلص 08'!$J$5=""),"",'مستخلص 08'!$J$5) | G13: =IF('مستخلص 08'!$J$7="","",'مستخلص 08'!$L$19) | H13: =IF('مستخلص 08'!$J$7="","",'مستخلص 08'!$J$19) | I13: =IF('مستخلص 08'!$J$7="","",'مستخلص 08'!$L$20) | J13: =IF('مستخلص 08'!$J$7="","",'مستخلص 08'!$L$21) | K13: =IF('مستخلص 08'!$J$7="","",'مستخلص 08'!$L$22) | L13: =IF('مستخلص 08'!$J$7="","",'مستخلص 08'!$L$6) | M13: =IF(OR('مستخلص 08'!$J$7="",'مستخلص 08'!$L$8=""),"",'مستخلص 08'!$L$8) | N13: =IF(OR('مستخلص 08'!$J$7="",M13=""),"",L13-M13) | O13: =IF('مستخلص 08'!$J$7="","",-'مستخلص 08'!$L$23) | P13: =IF('مستخلص 08'!$J$7="","",-'مستخلص 08'!$L$24) | Q13: =IF('مستخلص 08'!$J$7="","",'مستخلص 08'!$L$25) | R13: =IF('مستخلص 08'!$J$7="","",P13-Q13) | S13: =IF('مستخلص 08'!$J$7="","",-'مستخلص 08'!$L$26) | T13: =IF('مستخلص 08'!$J$7="","",-'مستخلص 08'!$L$27) | U13: =IF('مستخلص 08'!$J$7="","",'مستخلص 08'!$L$28) | V13: =IF('مستخلص 08'!$J$7="","",'مستخلص 08'!$L$29) | W13: =IF('مستخلص 08'!$J$7="","",-'مستخلص 08'!$L$30) | X13: =IF('مستخلص 08'!$J$7="","",'مستخلص 08'!$L$31) | Y13: =IF('مستخلص 08'!$J$7="","",'مستخلص 08'!$H$31) | Z13: =IF('مستخلص 08'!$J$7="","",'مستخلص 08'!$J$31) | AA13: =IF('مستخلص 08'!$J$7="","",N('مستخلص 08'!$E$15)) | AB13: =IF(OR('مستخلص 08'!$J$7="",'مستخلص 08'!$K$15=""),"",'مستخلص 08'!$K$15) | AC13: =IF('مستخلص 08'!$J$7="","",Z13-AA13) | AD13: =IF(OR(AB13="",E13=""),"",AB13-E13) | AE13: =IF('مستخلص 08'!$J$7="","",IF(N(AA13)=0,IF(E13="","⏳ بانتظار الاعتماد","✖ غير محصل"),IF(AC13<=1,"✔ محصل بالكامل","⚠ محصل جزئياً"))) | AF13: =IF(OR('مستخلص 08'!$J$7="",'مستخلص 08'!$E$16=""),"",'مستخلص 08'!$E$16) | AG13: =IF('مستخلص 08'!$J$7="","",'مستخلص 08'!$E$43)
A14: 9 | B14: =IF(OR('مستخلص 09'!$J$7="",'مستخلص 09'!$J$6=""),"",'مستخلص 09'!$J$6) | C14: =IF('مستخلص 09'!$J$7="","",'مستخلص 09'!$J$7) | D14: =IF(OR('مستخلص 09'!$J$7="",'مستخلص 09'!$J$8=""),"",'مستخلص 09'!$J$8) | E14: =IF(OR('مستخلص 09'!$J$7="",'مستخلص 09'!$J$9=""),"",'مستخلص 09'!$J$9) | F14: =IF(OR('مستخلص 09'!$J$7="",'مستخلص 09'!$J$5=""),"",'مستخلص 09'!$J$5) | G14: =IF('مستخلص 09'!$J$7="","",'مستخلص 09'!$L$19) | H14: =IF('مستخلص 09'!$J$7="","",'مستخلص 09'!$J$19) | I14: =IF('مستخلص 09'!$J$7="","",'مستخلص 09'!$L$20) | J14: =IF('مستخلص 09'!$J$7="","",'مستخلص 09'!$L$21) | K14: =IF('مستخلص 09'!$J$7="","",'مستخلص 09'!$L$22) | L14: =IF('مستخلص 09'!$J$7="","",'مستخلص 09'!$L$6) | M14: =IF(OR('مستخلص 09'!$J$7="",'مستخلص 09'!$L$8=""),"",'مستخلص 09'!$L$8) | N14: =IF(OR('مستخلص 09'!$J$7="",M14=""),"",L14-M14) | O14: =IF('مستخلص 09'!$J$7="","",-'مستخلص 09'!$L$23) | P14: =IF('مستخلص 09'!$J$7="","",-'مستخلص 09'!$L$24) | Q14: =IF('مستخلص 09'!$J$7="","",'مستخلص 09'!$L$25) | R14: =IF('مستخلص 09'!$J$7="","",P14-Q14) | S14: =IF('مستخلص 09'!$J$7="","",-'مستخلص 09'!$L$26) | T14: =IF('مستخلص 09'!$J$7="","",-'مستخلص 09'!$L$27) | U14: =IF('مستخلص 09'!$J$7="","",'مستخلص 09'!$L$28) | V14: =IF('مستخلص 09'!$J$7="","",'مستخلص 09'!$L$29) | W14: =IF('مستخلص 09'!$J$7="","",-'مستخلص 09'!$L$30) | X14: =IF('مستخلص 09'!$J$7="","",'مستخلص 09'!$L$31) | Y14: =IF('مستخلص 09'!$J$7="","",'مستخلص 09'!$H$31) | Z14: =IF('مستخلص 09'!$J$7="","",'مستخلص 09'!$J$31) | AA14: =IF('مستخلص 09'!$J$7="","",N('مستخلص 09'!$E$15)) | AB14: =IF(OR('مستخلص 09'!$J$7="",'مستخلص 09'!$K$15=""),"",'مستخلص 09'!$K$15) | AC14: =IF('مستخلص 09'!$J$7="","",Z14-AA14) | AD14: =IF(OR(AB14="",E14=""),"",AB14-E14) | AE14: =IF('مستخلص 09'!$J$7="","",IF(N(AA14)=0,IF(E14="","⏳ بانتظار الاعتماد","✖ غير محصل"),IF(AC14<=1,"✔ محصل بالكامل","⚠ محصل جزئياً"))) | AF14: =IF(OR('مستخلص 09'!$J$7="",'مستخلص 09'!$E$16=""),"",'مستخلص 09'!$E$16) | AG14: =IF('مستخلص 09'!$J$7="","",'مستخلص 09'!$E$43)
A15: 10 | B15: =IF(OR('مستخلص 10'!$J$7="",'مستخلص 10'!$J$6=""),"",'مستخلص 10'!$J$6) | C15: =IF('مستخلص 10'!$J$7="","",'مستخلص 10'!$J$7) | D15: =IF(OR('مستخلص 10'!$J$7="",'مستخلص 10'!$J$8=""),"",'مستخلص 10'!$J$8) | E15: =IF(OR('مستخلص 10'!$J$7="",'مستخلص 10'!$J$9=""),"",'مستخلص 10'!$J$9) | F15: =IF(OR('مستخلص 10'!$J$7="",'مستخلص 10'!$J$5=""),"",'مستخلص 10'!$J$5) | G15: =IF('مستخلص 10'!$J$7="","",'مستخلص 10'!$L$19) | H15: =IF('مستخلص 10'!$J$7="","",'مستخلص 10'!$J$19) | I15: =IF('مستخلص 10'!$J$7="","",'مستخلص 10'!$L$20) | J15: =IF('مستخلص 10'!$J$7="","",'مستخلص 10'!$L$21) | K15: =IF('مستخلص 10'!$J$7="","",'مستخلص 10'!$L$22) | L15: =IF('مستخلص 10'!$J$7="","",'مستخلص 10'!$L$6) | M15: =IF(OR('مستخلص 10'!$J$7="",'مستخلص 10'!$L$8=""),"",'مستخلص 10'!$L$8) | N15: =IF(OR('مستخلص 10'!$J$7="",M15=""),"",L15-M15) | O15: =IF('مستخلص 10'!$J$7="","",-'مستخلص 10'!$L$23) | P15: =IF('مستخلص 10'!$J$7="","",-'مستخلص 10'!$L$24) | Q15: =IF('مستخلص 10'!$J$7="","",'مستخلص 10'!$L$25) | R15: =IF('مستخلص 10'!$J$7="","",P15-Q15) | S15: =IF('مستخلص 10'!$J$7="","",-'مستخلص 10'!$L$26) | T15: =IF('مستخلص 10'!$J$7="","",-'مستخلص 10'!$L$27) | U15: =IF('مستخلص 10'!$J$7="","",'مستخلص 10'!$L$28) | V15: =IF('مستخلص 10'!$J$7="","",'مستخلص 10'!$L$29) | W15: =IF('مستخلص 10'!$J$7="","",-'مستخلص 10'!$L$30) | X15: =IF('مستخلص 10'!$J$7="","",'مستخلص 10'!$L$31) | Y15: =IF('مستخلص 10'!$J$7="","",'مستخلص 10'!$H$31) | Z15: =IF('مستخلص 10'!$J$7="","",'مستخلص 10'!$J$31) | AA15: =IF('مستخلص 10'!$J$7="","",N('مستخلص 10'!$E$15)) | AB15: =IF(OR('مستخلص 10'!$J$7="",'مستخلص 10'!$K$15=""),"",'مستخلص 10'!$K$15) | AC15: =IF('مستخلص 10'!$J$7="","",Z15-AA15) | AD15: =IF(OR(AB15="",E15=""),"",AB15-E15) | AE15: =IF('مستخلص 10'!$J$7="","",IF(N(AA15)=0,IF(E15="","⏳ بانتظار الاعتماد","✖ غير محصل"),IF(AC15<=1,"✔ محصل بالكامل","⚠ محصل جزئياً"))) | AF15: =IF(OR('مستخلص 10'!$J$7="",'مستخلص 10'!$E$16=""),"",'مستخلص 10'!$E$16) | AG15: =IF('مستخلص 10'!$J$7="","",'مستخلص 10'!$E$43)
A16: 11 | B16: =IF(OR('مستخلص 11'!$J$7="",'مستخلص 11'!$J$6=""),"",'مستخلص 11'!$J$6) | C16: =IF('مستخلص 11'!$J$7="","",'مستخلص 11'!$J$7) | D16: =IF(OR('مستخلص 11'!$J$7="",'مستخلص 11'!$J$8=""),"",'مستخلص 11'!$J$8) | E16: =IF(OR('مستخلص 11'!$J$7="",'مستخلص 11'!$J$9=""),"",'مستخلص 11'!$J$9) | F16: =IF(OR('مستخلص 11'!$J$7="",'مستخلص 11'!$J$5=""),"",'مستخلص 11'!$J$5) | G16: =IF('مستخلص 11'!$J$7="","",'مستخلص 11'!$L$19) | H16: =IF('مستخلص 11'!$J$7="","",'مستخلص 11'!$J$19) | I16: =IF('مستخلص 11'!$J$7="","",'مستخلص 11'!$L$20) | J16: =IF('مستخلص 11'!$J$7="","",'مستخلص 11'!$L$21) | K16: =IF('مستخلص 11'!$J$7="","",'مستخلص 11'!$L$22) | L16: =IF('مستخلص 11'!$J$7="","",'مستخلص 11'!$L$6) | M16: =IF(OR('مستخلص 11'!$J$7="",'مستخلص 11'!$L$8=""),"",'مستخلص 11'!$L$8) | N16: =IF(OR('مستخلص 11'!$J$7="",M16=""),"",L16-M16) | O16: =IF('مستخلص 11'!$J$7="","",-'مستخلص 11'!$L$23) | P16: =IF('مستخلص 11'!$J$7="","",-'مستخلص 11'!$L$24) | Q16: =IF('مستخلص 11'!$J$7="","",'مستخلص 11'!$L$25) | R16: =IF('مستخلص 11'!$J$7="","",P16-Q16) | S16: =IF('مستخلص 11'!$J$7="","",-'مستخلص 11'!$L$26) | T16: =IF('مستخلص 11'!$J$7="","",-'مستخلص 11'!$L$27) | U16: =IF('مستخلص 11'!$J$7="","",'مستخلص 11'!$L$28) | V16: =IF('مستخلص 11'!$J$7="","",'مستخلص 11'!$L$29) | W16: =IF('مستخلص 11'!$J$7="","",-'مستخلص 11'!$L$30) | X16: =IF('مستخلص 11'!$J$7="","",'مستخلص 11'!$L$31) | Y16: =IF('مستخلص 11'!$J$7="","",'مستخلص 11'!$H$31) | Z16: =IF('مستخلص 11'!$J$7="","",'مستخلص 11'!$J$31) | AA16: =IF('مستخلص 11'!$J$7="","",N('مستخلص 11'!$E$15)) | AB16: =IF(OR('مستخلص 11'!$J$7="",'مستخلص 11'!$K$15=""),"",'مستخلص 11'!$K$15) | AC16: =IF('مستخلص 11'!$J$7="","",Z16-AA16) | AD16: =IF(OR(AB16="",E16=""),"",AB16-E16) | AE16: =IF('مستخلص 11'!$J$7="","",IF(N(AA16)=0,IF(E16="","⏳ بانتظار الاعتماد","✖ غير محصل"),IF(AC16<=1,"✔ محصل بالكامل","⚠ محصل جزئياً"))) | AF16: =IF(OR('مستخلص 11'!$J$7="",'مستخلص 11'!$E$16=""),"",'مستخلص 11'!$E$16) | AG16: =IF('مستخلص 11'!$J$7="","",'مستخلص 11'!$E$43)
A17: 12 | B17: =IF(OR('مستخلص 12'!$J$7="",'مستخلص 12'!$J$6=""),"",'مستخلص 12'!$J$6) | C17: =IF('مستخلص 12'!$J$7="","",'مستخلص 12'!$J$7) | D17: =IF(OR('مستخلص 12'!$J$7="",'مستخلص 12'!$J$8=""),"",'مستخلص 12'!$J$8) | E17: =IF(OR('مستخلص 12'!$J$7="",'مستخلص 12'!$J$9=""),"",'مستخلص 12'!$J$9) | F17: =IF(OR('مستخلص 12'!$J$7="",'مستخلص 12'!$J$5=""),"",'مستخلص 12'!$J$5) | G17: =IF('مستخلص 12'!$J$7="","",'مستخلص 12'!$L$19) | H17: =IF('مستخلص 12'!$J$7="","",'مستخلص 12'!$J$19) | I17: =IF('مستخلص 12'!$J$7="","",'مستخلص 12'!$L$20) | J17: =IF('مستخلص 12'!$J$7="","",'مستخلص 12'!$L$21) | K17: =IF('مستخلص 12'!$J$7="","",'مستخلص 12'!$L$22) | L17: =IF('مستخلص 12'!$J$7="","",'مستخلص 12'!$L$6) | M17: =IF(OR('مستخلص 12'!$J$7="",'مستخلص 12'!$L$8=""),"",'مستخلص 12'!$L$8) | N17: =IF(OR('مستخلص 12'!$J$7="",M17=""),"",L17-M17) | O17: =IF('مستخلص 12'!$J$7="","",-'مستخلص 12'!$L$23) | P17: =IF('مستخلص 12'!$J$7="","",-'مستخلص 12'!$L$24) | Q17: =IF('مستخلص 12'!$J$7="","",'مستخلص 12'!$L$25) | R17: =IF('مستخلص 12'!$J$7="","",P17-Q17) | S17: =IF('مستخلص 12'!$J$7="","",-'مستخلص 12'!$L$26) | T17: =IF('مستخلص 12'!$J$7="","",-'مستخلص 12'!$L$27) | U17: =IF('مستخلص 12'!$J$7="","",'مستخلص 12'!$L$28) | V17: =IF('مستخلص 12'!$J$7="","",'مستخلص 12'!$L$29) | W17: =IF('مستخلص 12'!$J$7="","",-'مستخلص 12'!$L$30) | X17: =IF('مستخلص 12'!$J$7="","",'مستخلص 12'!$L$31) | Y17: =IF('مستخلص 12'!$J$7="","",'مستخلص 12'!$H$31) | Z17: =IF('مستخلص 12'!$J$7="","",'مستخلص 12'!$J$31) | AA17: =IF('مستخلص 12'!$J$7="","",N('مستخلص 12'!$E$15)) | AB17: =IF(OR('مستخلص 12'!$J$7="",'مستخلص 12'!$K$15=""),"",'مستخلص 12'!$K$15) | AC17: =IF('مستخلص 12'!$J$7="","",Z17-AA17) | AD17: =IF(OR(AB17="",E17=""),"",AB17-E17) | AE17: =IF('مستخلص 12'!$J$7="","",IF(N(AA17)=0,IF(E17="","⏳ بانتظار الاعتماد","✖ غير محصل"),IF(AC17<=1,"✔ محصل بالكامل","⚠ محصل جزئياً"))) | AF17: =IF(OR('مستخلص 12'!$J$7="",'مستخلص 12'!$E$16=""),"",'مستخلص 12'!$E$16) | AG17: =IF('مستخلص 12'!$J$7="","",'مستخلص 12'!$E$43)
A18: 13 | B18: =IF(OR('مستخلص 13'!$J$7="",'مستخلص 13'!$J$6=""),"",'مستخلص 13'!$J$6) | C18: =IF('مستخلص 13'!$J$7="","",'مستخلص 13'!$J$7) | D18: =IF(OR('مستخلص 13'!$J$7="",'مستخلص 13'!$J$8=""),"",'مستخلص 13'!$J$8) | E18: =IF(OR('مستخلص 13'!$J$7="",'مستخلص 13'!$J$9=""),"",'مستخلص 13'!$J$9) | F18: =IF(OR('مستخلص 13'!$J$7="",'مستخلص 13'!$J$5=""),"",'مستخلص 13'!$J$5) | G18: =IF('مستخلص 13'!$J$7="","",'مستخلص 13'!$L$19) | H18: =IF('مستخلص 13'!$J$7="","",'مستخلص 13'!$J$19) | I18: =IF('مستخلص 13'!$J$7="","",'مستخلص 13'!$L$20) | J18: =IF('مستخلص 13'!$J$7="","",'مستخلص 13'!$L$21) | K18: =IF('مستخلص 13'!$J$7="","",'مستخلص 13'!$L$22) | L18: =IF('مستخلص 13'!$J$7="","",'مستخلص 13'!$L$6) | M18: =IF(OR('مستخلص 13'!$J$7="",'مستخلص 13'!$L$8=""),"",'مستخلص 13'!$L$8) | N18: =IF(OR('مستخلص 13'!$J$7="",M18=""),"",L18-M18) | O18: =IF('مستخلص 13'!$J$7="","",-'مستخلص 13'!$L$23) | P18: =IF('مستخلص 13'!$J$7="","",-'مستخلص 13'!$L$24) | Q18: =IF('مستخلص 13'!$J$7="","",'مستخلص 13'!$L$25) | R18: =IF('مستخلص 13'!$J$7="","",P18-Q18) | S18: =IF('مستخلص 13'!$J$7="","",-'مستخلص 13'!$L$26) | T18: =IF('مستخلص 13'!$J$7="","",-'مستخلص 13'!$L$27) | U18: =IF('مستخلص 13'!$J$7="","",'مستخلص 13'!$L$28) | V18: =IF('مستخلص 13'!$J$7="","",'مستخلص 13'!$L$29) | W18: =IF('مستخلص 13'!$J$7="","",-'مستخلص 13'!$L$30) | X18: =IF('مستخلص 13'!$J$7="","",'مستخلص 13'!$L$31) | Y18: =IF('مستخلص 13'!$J$7="","",'مستخلص 13'!$H$31) | Z18: =IF('مستخلص 13'!$J$7="","",'مستخلص 13'!$J$31) | AA18: =IF('مستخلص 13'!$J$7="","",N('مستخلص 13'!$E$15)) | AB18: =IF(OR('مستخلص 13'!$J$7="",'مستخلص 13'!$K$15=""),"",'مستخلص 13'!$K$15) | AC18: =IF('مستخلص 13'!$J$7="","",Z18-AA18) | AD18: =IF(OR(AB18="",E18=""),"",AB18-E18) | AE18: =IF('مستخلص 13'!$J$7="","",IF(N(AA18)=0,IF(E18="","⏳ بانتظار الاعتماد","✖ غير محصل"),IF(AC18<=1,"✔ محصل بالكامل","⚠ محصل جزئياً"))) | AF18: =IF(OR('مستخلص 13'!$J$7="",'مستخلص 13'!$E$16=""),"",'مستخلص 13'!$E$16) | AG18: =IF('مستخلص 13'!$J$7="","",'مستخلص 13'!$E$43)
A19: 14 | B19: =IF(OR('مستخلص 14'!$J$7="",'مستخلص 14'!$J$6=""),"",'مستخلص 14'!$J$6) | C19: =IF('مستخلص 14'!$J$7="","",'مستخلص 14'!$J$7) | D19: =IF(OR('مستخلص 14'!$J$7="",'مستخلص 14'!$J$8=""),"",'مستخلص 14'!$J$8) | E19: =IF(OR('مستخلص 14'!$J$7="",'مستخلص 14'!$J$9=""),"",'مستخلص 14'!$J$9) | F19: =IF(OR('مستخلص 14'!$J$7="",'مستخلص 14'!$J$5=""),"",'مستخلص 14'!$J$5) | G19: =IF('مستخلص 14'!$J$7="","",'مستخلص 14'!$L$19) | H19: =IF('مستخلص 14'!$J$7="","",'مستخلص 14'!$J$19) | I19: =IF('مستخلص 14'!$J$7="","",'مستخلص 14'!$L$20) | J19: =IF('مستخلص 14'!$J$7="","",'مستخلص 14'!$L$21) | K19: =IF('مستخلص 14'!$J$7="","",'مستخلص 14'!$L$22) | L19: =IF('مستخلص 14'!$J$7="","",'مستخلص 14'!$L$6) | M19: =IF(OR('مستخلص 14'!$J$7="",'مستخلص 14'!$L$8=""),"",'مستخلص 14'!$L$8) | N19: =IF(OR('مستخلص 14'!$J$7="",M19=""),"",L19-M19) | O19: =IF('مستخلص 14'!$J$7="","",-'مستخلص 14'!$L$23) | P19: =IF('مستخلص 14'!$J$7="","",-'مستخلص 14'!$L$24) | Q19: =IF('مستخلص 14'!$J$7="","",'مستخلص 14'!$L$25) | R19: =IF('مستخلص 14'!$J$7="","",P19-Q19) | S19: =IF('مستخلص 14'!$J$7="","",-'مستخلص 14'!$L$26) | T19: =IF('مستخلص 14'!$J$7="","",-'مستخلص 14'!$L$27) | U19: =IF('مستخلص 14'!$J$7="","",'مستخلص 14'!$L$28) | V19: =IF('مستخلص 14'!$J$7="","",'مستخلص 14'!$L$29) | W19: =IF('مستخلص 14'!$J$7="","",-'مستخلص 14'!$L$30) | X19: =IF('مستخلص 14'!$J$7="","",'مستخلص 14'!$L$31) | Y19: =IF('مستخلص 14'!$J$7="","",'مستخلص 14'!$H$31) | Z19: =IF('مستخلص 14'!$J$7="","",'مستخلص 14'!$J$31) | AA19: =IF('مستخلص 14'!$J$7="","",N('مستخلص 14'!$E$15)) | AB19: =IF(OR('مستخلص 14'!$J$7="",'مستخلص 14'!$K$15=""),"",'مستخلص 14'!$K$15) | AC19: =IF('مستخلص 14'!$J$7="","",Z19-AA19) | AD19: =IF(OR(AB19="",E19=""),"",AB19-E19) | AE19: =IF('مستخلص 14'!$J$7="","",IF(N(AA19)=0,IF(E19="","⏳ بانتظار الاعتماد","✖ غير محصل"),IF(AC19<=1,"✔ محصل بالكامل","⚠ محصل جزئياً"))) | AF19: =IF(OR('مستخلص 14'!$J$7="",'مستخلص 14'!$E$16=""),"",'مستخلص 14'!$E$16) | AG19: =IF('مستخلص 14'!$J$7="","",'مستخلص 14'!$E$43)
A20: 15 | B20: =IF(OR('مستخلص 15'!$J$7="",'مستخلص 15'!$J$6=""),"",'مستخلص 15'!$J$6) | C20: =IF('مستخلص 15'!$J$7="","",'مستخلص 15'!$J$7) | D20: =IF(OR('مستخلص 15'!$J$7="",'مستخلص 15'!$J$8=""),"",'مستخلص 15'!$J$8) | E20: =IF(OR('مستخلص 15'!$J$7="",'مستخلص 15'!$J$9=""),"",'مستخلص 15'!$J$9) | F20: =IF(OR('مستخلص 15'!$J$7="",'مستخلص 15'!$J$5=""),"",'مستخلص 15'!$J$5) | G20: =IF('مستخلص 15'!$J$7="","",'مستخلص 15'!$L$19) | H20: =IF('مستخلص 15'!$J$7="","",'مستخلص 15'!$J$19) | I20: =IF('مستخلص 15'!$J$7="","",'مستخلص 15'!$L$20) | J20: =IF('مستخلص 15'!$J$7="","",'مستخلص 15'!$L$21) | K20: =IF('مستخلص 15'!$J$7="","",'مستخلص 15'!$L$22) | L20: =IF('مستخلص 15'!$J$7="","",'مستخلص 15'!$L$6) | M20: =IF(OR('مستخلص 15'!$J$7="",'مستخلص 15'!$L$8=""),"",'مستخلص 15'!$L$8) | N20: =IF(OR('مستخلص 15'!$J$7="",M20=""),"",L20-M20) | O20: =IF('مستخلص 15'!$J$7="","",-'مستخلص 15'!$L$23) | P20: =IF('مستخلص 15'!$J$7="","",-'مستخلص 15'!$L$24) | Q20: =IF('مستخلص 15'!$J$7="","",'مستخلص 15'!$L$25) | R20: =IF('مستخلص 15'!$J$7="","",P20-Q20) | S20: =IF('مستخلص 15'!$J$7="","",-'مستخلص 15'!$L$26) | T20: =IF('مستخلص 15'!$J$7="","",-'مستخلص 15'!$L$27) | U20: =IF('مستخلص 15'!$J$7="","",'مستخلص 15'!$L$28) | V20: =IF('مستخلص 15'!$J$7="","",'مستخلص 15'!$L$29) | W20: =IF('مستخلص 15'!$J$7="","",-'مستخلص 15'!$L$30) | X20: =IF('مستخلص 15'!$J$7="","",'مستخلص 15'!$L$31) | Y20: =IF('مستخلص 15'!$J$7="","",'مستخلص 15'!$H$31) | Z20: =IF('مستخلص 15'!$J$7="","",'مستخلص 15'!$J$31) | AA20: =IF('مستخلص 15'!$J$7="","",N('مستخلص 15'!$E$15)) | AB20: =IF(OR('مستخلص 15'!$J$7="",'مستخلص 15'!$K$15=""),"",'مستخلص 15'!$K$15) | AC20: =IF('مستخلص 15'!$J$7="","",Z20-AA20) | AD20: =IF(OR(AB20="",E20=""),"",AB20-E20) | AE20: =IF('مستخلص 15'!$J$7="","",IF(N(AA20)=0,IF(E20="","⏳ بانتظار الاعتماد","✖ غير محصل"),IF(AC20<=1,"✔ محصل بالكامل","⚠ محصل جزئياً"))) | AF20: =IF(OR('مستخلص 15'!$J$7="",'مستخلص 15'!$E$16=""),"",'مستخلص 15'!$E$16) | AG20: =IF('مستخلص 15'!$J$7="","",'مستخلص 15'!$E$43)
A21: 16 | B21: =IF(OR('مستخلص 16'!$J$7="",'مستخلص 16'!$J$6=""),"",'مستخلص 16'!$J$6) | C21: =IF('مستخلص 16'!$J$7="","",'مستخلص 16'!$J$7) | D21: =IF(OR('مستخلص 16'!$J$7="",'مستخلص 16'!$J$8=""),"",'مستخلص 16'!$J$8) | E21: =IF(OR('مستخلص 16'!$J$7="",'مستخلص 16'!$J$9=""),"",'مستخلص 16'!$J$9) | F21: =IF(OR('مستخلص 16'!$J$7="",'مستخلص 16'!$J$5=""),"",'مستخلص 16'!$J$5) | G21: =IF('مستخلص 16'!$J$7="","",'مستخلص 16'!$L$19) | H21: =IF('مستخلص 16'!$J$7="","",'مستخلص 16'!$J$19) | I21: =IF('مستخلص 16'!$J$7="","",'مستخلص 16'!$L$20) | J21: =IF('مستخلص 16'!$J$7="","",'مستخلص 16'!$L$21) | K21: =IF('مستخلص 16'!$J$7="","",'مستخلص 16'!$L$22) | L21: =IF('مستخلص 16'!$J$7="","",'مستخلص 16'!$L$6) | M21: =IF(OR('مستخلص 16'!$J$7="",'مستخلص 16'!$L$8=""),"",'مستخلص 16'!$L$8) | N21: =IF(OR('مستخلص 16'!$J$7="",M21=""),"",L21-M21) | O21: =IF('مستخلص 16'!$J$7="","",-'مستخلص 16'!$L$23) | P21: =IF('مستخلص 16'!$J$7="","",-'مستخلص 16'!$L$24) | Q21: =IF('مستخلص 16'!$J$7="","",'مستخلص 16'!$L$25) | R21: =IF('مستخلص 16'!$J$7="","",P21-Q21) | S21: =IF('مستخلص 16'!$J$7="","",-'مستخلص 16'!$L$26) | T21: =IF('مستخلص 16'!$J$7="","",-'مستخلص 16'!$L$27) | U21: =IF('مستخلص 16'!$J$7="","",'مستخلص 16'!$L$28) | V21: =IF('مستخلص 16'!$J$7="","",'مستخلص 16'!$L$29) | W21: =IF('مستخلص 16'!$J$7="","",-'مستخلص 16'!$L$30) | X21: =IF('مستخلص 16'!$J$7="","",'مستخلص 16'!$L$31) | Y21: =IF('مستخلص 16'!$J$7="","",'مستخلص 16'!$H$31) | Z21: =IF('مستخلص 16'!$J$7="","",'مستخلص 16'!$J$31) | AA21: =IF('مستخلص 16'!$J$7="","",N('مستخلص 16'!$E$15)) | AB21: =IF(OR('مستخلص 16'!$J$7="",'مستخلص 16'!$K$15=""),"",'مستخلص 16'!$K$15) | AC21: =IF('مستخلص 16'!$J$7="","",Z21-AA21) | AD21: =IF(OR(AB21="",E21=""),"",AB21-E21) | AE21: =IF('مستخلص 16'!$J$7="","",IF(N(AA21)=0,IF(E21="","⏳ بانتظار الاعتماد","✖ غير محصل"),IF(AC21<=1,"✔ محصل بالكامل","⚠ محصل جزئياً"))) | AF21: =IF(OR('مستخلص 16'!$J$7="",'مستخلص 16'!$E$16=""),"",'مستخلص 16'!$E$16) | AG21: =IF('مستخلص 16'!$J$7="","",'مستخلص 16'!$E$43)
A22: 17 | B22: =IF(OR('مستخلص 17'!$J$7="",'مستخلص 17'!$J$6=""),"",'مستخلص 17'!$J$6) | C22: =IF('مستخلص 17'!$J$7="","",'مستخلص 17'!$J$7) | D22: =IF(OR('مستخلص 17'!$J$7="",'مستخلص 17'!$J$8=""),"",'مستخلص 17'!$J$8) | E22: =IF(OR('مستخلص 17'!$J$7="",'مستخلص 17'!$J$9=""),"",'مستخلص 17'!$J$9) | F22: =IF(OR('مستخلص 17'!$J$7="",'مستخلص 17'!$J$5=""),"",'مستخلص 17'!$J$5) | G22: =IF('مستخلص 17'!$J$7="","",'مستخلص 17'!$L$19) | H22: =IF('مستخلص 17'!$J$7="","",'مستخلص 17'!$J$19) | I22: =IF('مستخلص 17'!$J$7="","",'مستخلص 17'!$L$20) | J22: =IF('مستخلص 17'!$J$7="","",'مستخلص 17'!$L$21) | K22: =IF('مستخلص 17'!$J$7="","",'مستخلص 17'!$L$22) | L22: =IF('مستخلص 17'!$J$7="","",'مستخلص 17'!$L$6) | M22: =IF(OR('مستخلص 17'!$J$7="",'مستخلص 17'!$L$8=""),"",'مستخلص 17'!$L$8) | N22: =IF(OR('مستخلص 17'!$J$7="",M22=""),"",L22-M22) | O22: =IF('مستخلص 17'!$J$7="","",-'مستخلص 17'!$L$23) | P22: =IF('مستخلص 17'!$J$7="","",-'مستخلص 17'!$L$24) | Q22: =IF('مستخلص 17'!$J$7="","",'مستخلص 17'!$L$25) | R22: =IF('مستخلص 17'!$J$7="","",P22-Q22) | S22: =IF('مستخلص 17'!$J$7="","",-'مستخلص 17'!$L$26) | T22: =IF('مستخلص 17'!$J$7="","",-'مستخلص 17'!$L$27) | U22: =IF('مستخلص 17'!$J$7="","",'مستخلص 17'!$L$28) | V22: =IF('مستخلص 17'!$J$7="","",'مستخلص 17'!$L$29) | W22: =IF('مستخلص 17'!$J$7="","",-'مستخلص 17'!$L$30) | X22: =IF('مستخلص 17'!$J$7="","",'مستخلص 17'!$L$31) | Y22: =IF('مستخلص 17'!$J$7="","",'مستخلص 17'!$H$31) | Z22: =IF('مستخلص 17'!$J$7="","",'مستخلص 17'!$J$31) | AA22: =IF('مستخلص 17'!$J$7="","",N('مستخلص 17'!$E$15)) | AB22: =IF(OR('مستخلص 17'!$J$7="",'مستخلص 17'!$K$15=""),"",'مستخلص 17'!$K$15) | AC22: =IF('مستخلص 17'!$J$7="","",Z22-AA22) | AD22: =IF(OR(AB22="",E22=""),"",AB22-E22) | AE22: =IF('مستخلص 17'!$J$7="","",IF(N(AA22)=0,IF(E22="","⏳ بانتظار الاعتماد","✖ غير محصل"),IF(AC22<=1,"✔ محصل بالكامل","⚠ محصل جزئياً"))) | AF22: =IF(OR('مستخلص 17'!$J$7="",'مستخلص 17'!$E$16=""),"",'مستخلص 17'!$E$16) | AG22: =IF('مستخلص 17'!$J$7="","",'مستخلص 17'!$E$43)
A23: 18 | B23: =IF(OR('مستخلص 18'!$J$7="",'مستخلص 18'!$J$6=""),"",'مستخلص 18'!$J$6) | C23: =IF('مستخلص 18'!$J$7="","",'مستخلص 18'!$J$7) | D23: =IF(OR('مستخلص 18'!$J$7="",'مستخلص 18'!$J$8=""),"",'مستخلص 18'!$J$8) | E23: =IF(OR('مستخلص 18'!$J$7="",'مستخلص 18'!$J$9=""),"",'مستخلص 18'!$J$9) | F23: =IF(OR('مستخلص 18'!$J$7="",'مستخلص 18'!$J$5=""),"",'مستخلص 18'!$J$5) | G23: =IF('مستخلص 18'!$J$7="","",'مستخلص 18'!$L$19) | H23: =IF('مستخلص 18'!$J$7="","",'مستخلص 18'!$J$19) | I23: =IF('مستخلص 18'!$J$7="","",'مستخلص 18'!$L$20) | J23: =IF('مستخلص 18'!$J$7="","",'مستخلص 18'!$L$21) | K23: =IF('مستخلص 18'!$J$7="","",'مستخلص 18'!$L$22) | L23: =IF('مستخلص 18'!$J$7="","",'مستخلص 18'!$L$6) | M23: =IF(OR('مستخلص 18'!$J$7="",'مستخلص 18'!$L$8=""),"",'مستخلص 18'!$L$8) | N23: =IF(OR('مستخلص 18'!$J$7="",M23=""),"",L23-M23) | O23: =IF('مستخلص 18'!$J$7="","",-'مستخلص 18'!$L$23) | P23: =IF('مستخلص 18'!$J$7="","",-'مستخلص 18'!$L$24) | Q23: =IF('مستخلص 18'!$J$7="","",'مستخلص 18'!$L$25) | R23: =IF('مستخلص 18'!$J$7="","",P23-Q23) | S23: =IF('مستخلص 18'!$J$7="","",-'مستخلص 18'!$L$26) | T23: =IF('مستخلص 18'!$J$7="","",-'مستخلص 18'!$L$27) | U23: =IF('مستخلص 18'!$J$7="","",'مستخلص 18'!$L$28) | V23: =IF('مستخلص 18'!$J$7="","",'مستخلص 18'!$L$29) | W23: =IF('مستخلص 18'!$J$7="","",-'مستخلص 18'!$L$30) | X23: =IF('مستخلص 18'!$J$7="","",'مستخلص 18'!$L$31) | Y23: =IF('مستخلص 18'!$J$7="","",'مستخلص 18'!$H$31) | Z23: =IF('مستخلص 18'!$J$7="","",'مستخلص 18'!$J$31) | AA23: =IF('مستخلص 18'!$J$7="","",N('مستخلص 18'!$E$15)) | AB23: =IF(OR('مستخلص 18'!$J$7="",'مستخلص 18'!$K$15=""),"",'مستخلص 18'!$K$15) | AC23: =IF('مستخلص 18'!$J$7="","",Z23-AA23) | AD23: =IF(OR(AB23="",E23=""),"",AB23-E23) | AE23: =IF('مستخلص 18'!$J$7="","",IF(N(AA23)=0,IF(E23="","⏳ بانتظار الاعتماد","✖ غير محصل"),IF(AC23<=1,"✔ محصل بالكامل","⚠ محصل جزئياً"))) | AF23: =IF(OR('مستخلص 18'!$J$7="",'مستخلص 18'!$E$16=""),"",'مستخلص 18'!$E$16) | AG23: =IF('مستخلص 18'!$J$7="","",'مستخلص 18'!$E$43)
A24: 19 | B24: =IF(OR('مستخلص 19'!$J$7="",'مستخلص 19'!$J$6=""),"",'مستخلص 19'!$J$6) | C24: =IF('مستخلص 19'!$J$7="","",'مستخلص 19'!$J$7) | D24: =IF(OR('مستخلص 19'!$J$7="",'مستخلص 19'!$J$8=""),"",'مستخلص 19'!$J$8) | E24: =IF(OR('مستخلص 19'!$J$7="",'مستخلص 19'!$J$9=""),"",'مستخلص 19'!$J$9) | F24: =IF(OR('مستخلص 19'!$J$7="",'مستخلص 19'!$J$5=""),"",'مستخلص 19'!$J$5) | G24: =IF('مستخلص 19'!$J$7="","",'مستخلص 19'!$L$19) | H24: =IF('مستخلص 19'!$J$7="","",'مستخلص 19'!$J$19) | I24: =IF('مستخلص 19'!$J$7="","",'مستخلص 19'!$L$20) | J24: =IF('مستخلص 19'!$J$7="","",'مستخلص 19'!$L$21) | K24: =IF('مستخلص 19'!$J$7="","",'مستخلص 19'!$L$22) | L24: =IF('مستخلص 19'!$J$7="","",'مستخلص 19'!$L$6) | M24: =IF(OR('مستخلص 19'!$J$7="",'مستخلص 19'!$L$8=""),"",'مستخلص 19'!$L$8) | N24: =IF(OR('مستخلص 19'!$J$7="",M24=""),"",L24-M24) | O24: =IF('مستخلص 19'!$J$7="","",-'مستخلص 19'!$L$23) | P24: =IF('مستخلص 19'!$J$7="","",-'مستخلص 19'!$L$24) | Q24: =IF('مستخلص 19'!$J$7="","",'مستخلص 19'!$L$25) | R24: =IF('مستخلص 19'!$J$7="","",P24-Q24) | S24: =IF('مستخلص 19'!$J$7="","",-'مستخلص 19'!$L$26) | T24: =IF('مستخلص 19'!$J$7="","",-'مستخلص 19'!$L$27) | U24: =IF('مستخلص 19'!$J$7="","",'مستخلص 19'!$L$28) | V24: =IF('مستخلص 19'!$J$7="","",'مستخلص 19'!$L$29) | W24: =IF('مستخلص 19'!$J$7="","",-'مستخلص 19'!$L$30) | X24: =IF('مستخلص 19'!$J$7="","",'مستخلص 19'!$L$31) | Y24: =IF('مستخلص 19'!$J$7="","",'مستخلص 19'!$H$31) | Z24: =IF('مستخلص 19'!$J$7="","",'مستخلص 19'!$J$31) | AA24: =IF('مستخلص 19'!$J$7="","",N('مستخلص 19'!$E$15)) | AB24: =IF(OR('مستخلص 19'!$J$7="",'مستخلص 19'!$K$15=""),"",'مستخلص 19'!$K$15) | AC24: =IF('مستخلص 19'!$J$7="","",Z24-AA24) | AD24: =IF(OR(AB24="",E24=""),"",AB24-E24) | AE24: =IF('مستخلص 19'!$J$7="","",IF(N(AA24)=0,IF(E24="","⏳ بانتظار الاعتماد","✖ غير محصل"),IF(AC24<=1,"✔ محصل بالكامل","⚠ محصل جزئياً"))) | AF24: =IF(OR('مستخلص 19'!$J$7="",'مستخلص 19'!$E$16=""),"",'مستخلص 19'!$E$16) | AG24: =IF('مستخلص 19'!$J$7="","",'مستخلص 19'!$E$43)
A25: 20 | B25: =IF(OR('مستخلص 20'!$J$7="",'مستخلص 20'!$J$6=""),"",'مستخلص 20'!$J$6) | C25: =IF('مستخلص 20'!$J$7="","",'مستخلص 20'!$J$7) | D25: =IF(OR('مستخلص 20'!$J$7="",'مستخلص 20'!$J$8=""),"",'مستخلص 20'!$J$8) | E25: =IF(OR('مستخلص 20'!$J$7="",'مستخلص 20'!$J$9=""),"",'مستخلص 20'!$J$9) | F25: =IF(OR('مستخلص 20'!$J$7="",'مستخلص 20'!$J$5=""),"",'مستخلص 20'!$J$5) | G25: =IF('مستخلص 20'!$J$7="","",'مستخلص 20'!$L$19) | H25: =IF('مستخلص 20'!$J$7="","",'مستخلص 20'!$J$19) | I25: =IF('مستخلص 20'!$J$7="","",'مستخلص 20'!$L$20) | J25: =IF('مستخلص 20'!$J$7="","",'مستخلص 20'!$L$21) | K25: =IF('مستخلص 20'!$J$7="","",'مستخلص 20'!$L$22) | L25: =IF('مستخلص 20'!$J$7="","",'مستخلص 20'!$L$6) | M25: =IF(OR('مستخلص 20'!$J$7="",'مستخلص 20'!$L$8=""),"",'مستخلص 20'!$L$8) | N25: =IF(OR('مستخلص 20'!$J$7="",M25=""),"",L25-M25) | O25: =IF('مستخلص 20'!$J$7="","",-'مستخلص 20'!$L$23) | P25: =IF('مستخلص 20'!$J$7="","",-'مستخلص 20'!$L$24) | Q25: =IF('مستخلص 20'!$J$7="","",'مستخلص 20'!$L$25) | R25: =IF('مستخلص 20'!$J$7="","",P25-Q25) | S25: =IF('مستخلص 20'!$J$7="","",-'مستخلص 20'!$L$26) | T25: =IF('مستخلص 20'!$J$7="","",-'مستخلص 20'!$L$27) | U25: =IF('مستخلص 20'!$J$7="","",'مستخلص 20'!$L$28) | V25: =IF('مستخلص 20'!$J$7="","",'مستخلص 20'!$L$29) | W25: =IF('مستخلص 20'!$J$7="","",-'مستخلص 20'!$L$30) | X25: =IF('مستخلص 20'!$J$7="","",'مستخلص 20'!$L$31) | Y25: =IF('مستخلص 20'!$J$7="","",'مستخلص 20'!$H$31) | Z25: =IF('مستخلص 20'!$J$7="","",'مستخلص 20'!$J$31) | AA25: =IF('مستخلص 20'!$J$7="","",N('مستخلص 20'!$E$15)) | AB25: =IF(OR('مستخلص 20'!$J$7="",'مستخلص 20'!$K$15=""),"",'مستخلص 20'!$K$15) | AC25: =IF('مستخلص 20'!$J$7="","",Z25-AA25) | AD25: =IF(OR(AB25="",E25=""),"",AB25-E25) | AE25: =IF('مستخلص 20'!$J$7="","",IF(N(AA25)=0,IF(E25="","⏳ بانتظار الاعتماد","✖ غير محصل"),IF(AC25<=1,"✔ محصل بالكامل","⚠ محصل جزئياً"))) | AF25: =IF(OR('مستخلص 20'!$J$7="",'مستخلص 20'!$E$16=""),"",'مستخلص 20'!$E$16) | AG25: =IF('مستخلص 20'!$J$7="","",'مستخلص 20'!$E$43)
A26: الإجمالي / آخر رصيد | G26: =IF($AJ$3=0,0,INDEX(G6:G25,$AJ$3)) | H26: =SUM(H6:H25) | I26: =IF($AJ$3=0,0,INDEX(I6:I25,$AJ$3)) | J26: =IF($AJ$3=0,0,INDEX(J6:J25,$AJ$3)) | K26: =IF($AJ$3=0,0,INDEX(K6:K25,$AJ$3)) | L26: =IF($AJ$3=0,0,INDEX(L6:L25,$AJ$3)) | O26: =IF($AJ$3=0,0,INDEX(O6:O25,$AJ$3)) | P26: =IF($AJ$3=0,0,INDEX(P6:P25,$AJ$3)) | Q26: =IF($AJ$3=0,0,INDEX(Q6:Q25,$AJ$3)) | R26: =IF($AJ$3=0,0,INDEX(R6:R25,$AJ$3)) | S26: =IF($AJ$3=0,0,INDEX(S6:S25,$AJ$3)) | T26: =IF($AJ$3=0,0,INDEX(T6:T25,$AJ$3)) | U26: =IF($AJ$3=0,0,INDEX(U6:U25,$AJ$3)) | V26: =IF($AJ$3=0,0,INDEX(V6:V25,$AJ$3)) | ... X26: =IF($AJ$3=0,0,INDEX(X6:X25,$AJ$3)) | Z26: =SUM(Z6:Z25) | AA26: =SUM(AA6:AA25) | AC26: =SUM(AC6:AC25) | AD26: =IFERROR(AVERAGE(AD6:AD25),0)
A28: هذا السجل للعرض فقط (لا يُدخل فيه شيء) — كل البيانات تُدخل في شيت كل مستخلص. يصبح المستخلص فعالاً بمجرد إدخال «الفترة إلى» في شيته. اضغط على رقم المستخلص للانتقال إليه.
B30: الإنجاز حسب أقسام الأعمال
B31: القسم | E31: القيمة التعاقدية | F31: القيمة المنفذة التراكمية | G31: نسبة الإنجاز | H31: الوزن من العقد
B32: =IF('بيانات العقد'!F6="","",'بيانات العقد'!F6) | E32: =IF(B32="",0,SUMIF('جدول الكميات'!$C$6:$C$105,B32,'جدول الكميات'!$H$6:$H$105)) | F32: =IF(B32="",0,SUMIF('جدول الكميات'!$C$6:$C$105,B32,'مستخلص 20'!$M$51:$M$150)) | G32: =IF(E32>0,F32/E32,0) | H32: =IF(ContractValue>0,E32/ContractValue,0)
B33: =IF('بيانات العقد'!F7="","",'بيانات العقد'!F7) | E33: =IF(B33="",0,SUMIF('جدول الكميات'!$C$6:$C$105,B33,'جدول الكميات'!$H$6:$H$105)) | F33: =IF(B33="",0,SUMIF('جدول الكميات'!$C$6:$C$105,B33,'مستخلص 20'!$M$51:$M$150)) | G33: =IF(E33>0,F33/E33,0) | H33: =IF(ContractValue>0,E33/ContractValue,0)
B34: =IF('بيانات العقد'!F8="","",'بيانات العقد'!F8) | E34: =IF(B34="",0,SUMIF('جدول الكميات'!$C$6:$C$105,B34,'جدول الكميات'!$H$6:$H$105)) | F34: =IF(B34="",0,SUMIF('جدول الكميات'!$C$6:$C$105,B34,'مستخلص 20'!$M$51:$M$150)) | G34: =IF(E34>0,F34/E34,0) | H34: =IF(ContractValue>0,E34/ContractValue,0)
B35: =IF('بيانات العقد'!F9="","",'بيانات العقد'!F9) | E35: =IF(B35="",0,SUMIF('جدول الكميات'!$C$6:$C$105,B35,'جدول الكميات'!$H$6:$H$105)) | F35: =IF(B35="",0,SUMIF('جدول الكميات'!$C$6:$C$105,B35,'مستخلص 20'!$M$51:$M$150)) | G35: =IF(E35>0,F35/E35,0) | H35: =IF(ContractValue>0,E35/ContractValue,0)
B36: =IF('بيانات العقد'!F10="","",'بيانات العقد'!F10) | E36: =IF(B36="",0,SUMIF('جدول الكميات'!$C$6:$C$105,B36,'جدول الكميات'!$H$6:$H$105)) | F36: =IF(B36="",0,SUMIF('جدول الكميات'!$C$6:$C$105,B36,'مستخلص 20'!$M$51:$M$150)) | G36: =IF(E36>0,F36/E36,0) | H36: =IF(ContractValue>0,E36/ContractValue,0)
B37: =IF('بيانات العقد'!F11="","",'بيانات العقد'!F11) | E37: =IF(B37="",0,SUMIF('جدول الكميات'!$C$6:$C$105,B37,'جدول الكميات'!$H$6:$H$105)) | F37: =IF(B37="",0,SUMIF('جدول الكميات'!$C$6:$C$105,B37,'مستخلص 20'!$M$51:$M$150)) | G37: =IF(E37>0,F37/E37,0) | H37: =IF(ContractValue>0,E37/ContractValue,0)
B38: =IF('بيانات العقد'!F12="","",'بيانات العقد'!F12) | E38: =IF(B38="",0,SUMIF('جدول الكميات'!$C$6:$C$105,B38,'جدول الكميات'!$H$6:$H$105)) | F38: =IF(B38="",0,SUMIF('جدول الكميات'!$C$6:$C$105,B38,'مستخلص 20'!$M$51:$M$150)) | G38: =IF(E38>0,F38/E38,0) | H38: =IF(ContractValue>0,E38/ContractValue,0)
B39: =IF('بيانات العقد'!F13="","",'بيانات العقد'!F13) | E39: =IF(B39="",0,SUMIF('جدول الكميات'!$C$6:$C$105,B39,'جدول الكميات'!$H$6:$H$105)) | F39: =IF(B39="",0,SUMIF('جدول الكميات'!$C$6:$C$105,B39,'مستخلص 20'!$M$51:$M$150)) | G39: =IF(E39>0,F39/E39,0) | H39: =IF(ContractValue>0,E39/ContractValue,0)
B40: =IF('بيانات العقد'!F14="","",'بيانات العقد'!F14) | E40: =IF(B40="",0,SUMIF('جدول الكميات'!$C$6:$C$105,B40,'جدول الكميات'!$H$6:$H$105)) | F40: =IF(B40="",0,SUMIF('جدول الكميات'!$C$6:$C$105,B40,'مستخلص 20'!$M$51:$M$150)) | G40: =IF(E40>0,F40/E40,0) | H40: =IF(ContractValue>0,E40/ContractValue,0)
B41: =IF('بيانات العقد'!F15="","",'بيانات العقد'!F15) | E41: =IF(B41="",0,SUMIF('جدول الكميات'!$C$6:$C$105,B41,'جدول الكميات'!$H$6:$H$105)) | F41: =IF(B41="",0,SUMIF('جدول الكميات'!$C$6:$C$105,B41,'مستخلص 20'!$M$51:$M$150)) | G41: =IF(E41>0,F41/E41,0) | H41: =IF(ContractValue>0,E41/ContractValue,0)
B42: =IF('بيانات العقد'!F16="","",'بيانات العقد'!F16) | E42: =IF(B42="",0,SUMIF('جدول الكميات'!$C$6:$C$105,B42,'جدول الكميات'!$H$6:$H$105)) | F42: =IF(B42="",0,SUMIF('جدول الكميات'!$C$6:$C$105,B42,'مستخلص 20'!$M$51:$M$150)) | G42: =IF(E42>0,F42/E42,0) | H42: =IF(ContractValue>0,E42/ContractValue,0)
B43: =IF('بيانات العقد'!F17="","",'بيانات العقد'!F17) | E43: =IF(B43="",0,SUMIF('جدول الكميات'!$C$6:$C$105,B43,'جدول الكميات'!$H$6:$H$105)) | F43: =IF(B43="",0,SUMIF('جدول الكميات'!$C$6:$C$105,B43,'مستخلص 20'!$M$51:$M$150)) | G43: =IF(E43>0,F43/E43,0) | H43: =IF(ContractValue>0,E43/ContractValue,0)

Sheet مستخلص 01
B1: 🧾 مستخلص أعمال رقم (1) — شهادة دفع مؤقتة (Interim Payment Certificate)
B2: =IF('بيانات العقد'!$C$5="","مشروع رقم 01 — أدخل بيانات العقد",'بيانات العقد'!$C$5&" | عقد رقم: "&'بيانات العقد'!$C$6)&" | المبالغ بـ "&'بيانات العقد'!$C$14
B3: 🗂 سجل المستخلصات | C3: ⚙ بيانات العقد | E3: 📋 جدول الكميات | G3: 🔁 التغييرية | I3: ✂ الاستقطاعات | L3: المستخلص التالي ►
B5: رقم المستخلص | C5: 1 | H5: حالة المستخلص | J5: معتمد | L5: نسبة الإنجاز الفعلية
B6: المشروع | C6: ='بيانات العقد'!C5 | H6: الفترة من | J6: 46082 | L6: =IF(ContractValue+L20>0,(L19+L20)/(ContractValue+L20),0)
B7: رقم العقد | C7: ='بيانات العقد'!C6 | H7: الفترة إلى | J7: 46112 | L7: نسبة الإنجاز المخططة (من البرنامج)
B8: صاحب العمل | C8: ='بيانات العقد'!C7 | H8: تاريخ التقديم | J8: 46117 | L8: 0.0109
B9: الاستشاري | C9: ='بيانات العقد'!C8 | H9: تاريخ الاعتماد | J9: 46133 | L9: الانحراف عن المخطط
B10: المقاول | C10: ='بيانات العقد'!C9 | H10: قيمة العقد المعدلة | J10: =RevisedContract | L10: =IF(L8="","",L6-L8)
B11: الرقم الضريبي للمقاول | C11: =IF('بيانات العقد'!C37="","",'بيانات العقد'!C37) | H11: الفترة بالتاريخ الهجري | J11: =IF(J6="","",J6) | K11: =IF(J7="","",J7)
B12: أولاً: بيانات الفترة (إدخال)
B13: رصيد المواد الموردة بالموقع (نهاية الفترة) | E13: 0 | H13: إفراج عن ضمان الأعمال خلال الفترة
B14: غرامات تأخير / خصومات أخرى خلال الفترة | H14: سبب الغرامة / الخصم
B15: المبلغ المحصل من هذا المستخلص | E15: 145872.76 | H15: تاريخ التحصيل | K15: 46165
B16: رقم الفاتورة الضريبية (من نظام الفوترة الإلكترونية) | E16: INV-2026-01001 | H16: تاريخ الفاتورة الضريبية | K16: 46133
B17: ثانياً: الملخص المالي للمستخلص
B18: م | C18: البيان | H18: السابق | J18: الحالي | L18: الإجمالي التراكمي
B19: 1 | C19: قيمة الأعمال المنفذة طبقاً لحصر البنود | H19: 0 | J19: =L19-H19 | L19: =M151
B20: 2 | C20: قيمة الأوامر التغييرية المعتمدة | H20: 0 | J20: =L20-H20 | L20: =SUMIFS('الأوامر التغييرية'!$J$6:$J$55,'الأوامر التغييرية'!$H$6:$H$55,"معتمد",'الأوامر التغييرية'!$K$6:$K$55,"<="&$C$5)
B21: 3 | C21: المواد الموردة بالموقع (رصيد) | H21: 0 | J21: =L21-H21 | L21: =N(E13)
B22: 4 | C22: إجمالي قيمة الأعمال | H22: 0 | J22: =L22-H22 | L22: =SUM(L19:L21)
B23: 5 | C23: يُخصم: استرداد الدفعة المقدمة | H23: 0 | J23: =L23-H23 | L23: =-ROUND(IF(L6>=RecFull,AdvAmount,MIN(AdvAmount,MAX(0,L19+L20-RecStart*ContractValue)*RecRate)),2)
B24: 6 | C24: يُخصم: ضمان الأعمال المحتسب | H24: 0 | J24: =L24-H24 | L24: =-ROUND(MIN(L22*RetPct,RetCap),2)
B25: 7 | C25: يُضاف: المفرج عنه من ضمان الأعمال | H25: 0 | J25: =L25-H25 | L25: =H25+N(K13)
B26: 8 | C26: يُخصم: الاستقطاعات الفنية المحتجزة | H26: 0 | J26: =L26-H26 | L26: =-(SUMIFS('الاستقطاعات الفنية'!$I$6:$I$105,'الاستقطاعات الفنية'!$D$6:$D$105,"<="&$C$5)-SUMIFS('الاستقطاعات الفنية'!$I$6:$I$105,'الاستقطاعات الفنية'!$J$6:$J$105,"نعم",'الاستقطاعات الفنية'!$K$6:$K$105,"<="&$C$5))
B27: 9 | C27: يُخصم: الغرامات والخصومات الأخرى | H27: 0 | J27: =L27-H27 | L27: =H27-N(E14)
B28: 10 | C28: صافي القيمة قبل الضرائب | H28: 0 | J28: =L28-H28 | L28: =SUM(L22:L27)
B29: 11 | C29: يُضاف: ضريبة القيمة المضافة | H29: 0 | J29: =L29-H29 | L29: =ROUND(VATPct*(L28+IF(VATBeforeRet="نعم",-(L24+L25),0)+IF(PenInVAT="لا",-L27,0)),2)
B30: 12 | C30: يُخصم: ضريبة الاستقطاع (غير المقيم) | H30: 0 | J30: =L30-H30 | L30: =-ROUND(WHTPct*(L28-(L24+L25)),2)
B31: 13 | C31: صافي المستحق | H31: 0 | J31: =L31-H31 | L31: =L28+L29+L30
B32: صافي المبلغ المستحق صرفه عن هذا المستخلص | J32: =J31
B33: المحصل من هذا المستخلص | J33: =N(E15)
B34: المتبقي غير المحصل | J34: =J32-J33
B35: فقط وقدره:
B37: ثالثاً: المستندات والمتطلبات النظامية للصرف (المملكة العربية السعودية)
B38: الفاتورة الضريبية الإلكترونية (متوافقة مع فاتورة - ZATCA) | F38: نعم | H38: شهادة الزكاة والضريبة سارية | L38: نعم
B39: شهادة التأمينات الاجتماعية (GOSI) سارية | F39: نعم | H39: شهادة نطاقات (التوطين) سارية | L39: نعم
B40: السجل التجاري وعضوية الغرفة التجارية سارية | F40: نعم | H40: محضر حصر الكميات معتمد من الاستشاري | L40: نعم
B41: ضمان الدفعة المقدمة ساري | F41: نعم | H41: الضمان النهائي ساري | L41: نعم
B42: وثيقة التأمين على الأعمال (CAR) سارية | F42: نعم | H42: تقرير الاستشاري الشهري | L42: نعم
B43: حالة المستندات: | E43: =IF(COUNTIF(F38:F42,"لا")+COUNTIF(L38:L42,"لا")+COUNTBLANK(F38:F42)+COUNTBLANK(L38:L42)=0,"✔ مكتملة — جاهز للصرف","⚠ ناقص "&(COUNTIF(F38:F42,"لا")+COUNTIF(L38:L42,"لا")+COUNTBLANK(F38:F42)+COUNTBLANK(L38:L42))&" مستند") | H43: الرقم الضريبي لصاحب العمل: | K43: =IF('بيانات العقد'!C39="","",'بيانات العقد'!C39)
B45: رابعاً: الاعتمادات
B46: إعداد: مهندس المقاول | F46: مراجعة: المهندس الاستشاري | J46: اعتماد: صاحب العمل
B47: الاسم: .................... التوقيع: .................. التاريخ: .................. | F47: الاسم: .................... التوقيع: .................. التاريخ: .................. | J47: الاسم: .................... التوقيع: .................. التاريخ: ..................
B49: خامساً: حصر الأعمال المنفذة حسب بنود جدول الكميات — أدخل «الكمية الحالية» فقط
B50: كود البند | C50: الوصف | D50: الوحدة | E50: الكمية التعاقدية | F50: سعر الوحدة | G50: الكمية السابقة | H50: الكمية الحالية | I50: الكمية التراكمية | J50: نسبة الإنجاز | K50: القيمة السابقة | L50: القيمة الحالية | M50: القيمة التراكمية
B51: =IF('جدول الكميات'!B6="","",'جدول الكميات'!B6) | C51: =IF('جدول الكميات'!D6="","",'جدول الكميات'!D6) | D51: =IF('جدول الكميات'!E6="","",'جدول الكميات'!E6) | E51: =N('جدول الكميات'!F6) | F51: =N('جدول الكميات'!G6) | G51: 0 | H51: 1500 | I51: =G51+H51 | J51: =IF(E51>0,I51/E51,0) | K51: =G51*F51 | L51: =N(H51)*F51 | M51: =I51*F51
B52: =IF('جدول الكميات'!B7="","",'جدول الكميات'!B7) | C52: =IF('جدول الكميات'!D7="","",'جدول الكميات'!D7) | D52: =IF('جدول الكميات'!E7="","",'جدول الكميات'!E7) | E52: =N('جدول الكميات'!F7) | F52: =N('جدول الكميات'!G7) | G52: 0 | H52: 733.33 | I52: =G52+H52 | J52: =IF(E52>0,I52/E52,0) | K52: =G52*F52 | L52: =N(H52)*F52 | M52: =I52*F52
B53: =IF('جدول الكميات'!B8="","",'جدول الكميات'!B8) | C53: =IF('جدول الكميات'!D8="","",'جدول الكميات'!D8) | D53: =IF('جدول الكميات'!E8="","",'جدول الكميات'!E8) | E53: =N('جدول الكميات'!F8) | F53: =N('جدول الكميات'!G8) | G53: 0 | H53: 600 | I53: =G53+H53 | J53: =IF(E53>0,I53/E53,0) | K53: =G53*F53 | L53: =N(H53)*F53 | M53: =I53*F53
B54: =IF('جدول الكميات'!B9="","",'جدول الكميات'!B9) | C54: =IF('جدول الكميات'!D9="","",'جدول الكميات'!D9) | D54: =IF('جدول الكميات'!E9="","",'جدول الكميات'!E9) | E54: =N('جدول الكميات'!F9) | F54: =N('جدول الكميات'!G9) | G54: 0 | H54: 5.07 | I54: =G54+H54 | J54: =IF(E54>0,I54/E54,0) | K54: =G54*F54 | L54: =N(H54)*F54 | M54: =I54*F54
B55: =IF('جدول الكميات'!B10="","",'جدول الكميات'!B10) | C55: =IF('جدول الكميات'!D10="","",'جدول الكميات'!D10) | D55: =IF('جدول الكميات'!E10="","",'جدول الكميات'!E10) | E55: =N('جدول الكميات'!F10) | F55: =N('جدول الكميات'!G10) | G55: 0 | H55: 12.67 | I55: =G55+H55 | J55: =IF(E55>0,I55/E55,0) | K55: =G55*F55 | L55: =N(H55)*F55 | M55: =I55*F55
B56: =IF('جدول الكميات'!B11="","",'جدول الكميات'!B11) | C56: =IF('جدول الكميات'!D11="","",'جدول الكميات'!D11) | D56: =IF('جدول الكميات'!E11="","",'جدول الكميات'!E11) | E56: =N('جدول الكميات'!F11) | F56: =N('جدول الكميات'!G11) | G56: 0 | H56: 5.6 | I56: =G56+H56 | J56: =IF(E56>0,I56/E56,0) | K56: =G56*F56 | L56: =N(H56)*F56 | M56: =I56*F56
B57: =IF('جدول الكميات'!B12="","",'جدول الكميات'!B12) | C57: =IF('جدول الكميات'!D12="","",'جدول الكميات'!D12) | D57: =IF('جدول الكميات'!E12="","",'جدول الكميات'!E12) | E57: =N('جدول الكميات'!F12) | F57: =N('جدول الكميات'!G12) | G57: 0 | H57: 22 | I57: =G57+H57 | J57: =IF(E57>0,I57/E57,0) | K57: =G57*F57 | L57: =N(H57)*F57 | M57: =I57*F57
B58: =IF('جدول الكميات'!B13="","",'جدول الكميات'!B13) | C58: =IF('جدول الكميات'!D13="","",'جدول الكميات'!D13) | D58: =IF('جدول الكميات'!E13="","",'جدول الكميات'!E13) | E58: =N('جدول الكميات'!F13) | F58: =N('جدول الكميات'!G13) | G58: 0 | H58: 6.4 | I58: =G58+H58 | J58: =IF(E58>0,I58/E58,0) | K58: =G58*F58 | L58: =N(H58)*F58 | M58: =I58*F58
B59: =IF('جدول الكميات'!B14="","",'جدول الكميات'!B14) | C59: =IF('جدول الكميات'!D14="","",'جدول الكميات'!D14) | D59: =IF('جدول الكميات'!E14="","",'جدول الكميات'!E14) | E59: =N('جدول الكميات'!F14) | F59: =N('جدول الكميات'!G14) | G59: 0 | I59: =G59+H59 | J59: =IF(E59>0,I59/E59,0) | K59: =G59*F59 | L59: =N(H59)*F59 | M59: =I59*F59
B60: =IF('جدول الكميات'!B15="","",'جدول الكميات'!B15) | C60: =IF('جدول الكميات'!D15="","",'جدول الكميات'!D15) | D60: =IF('جدول الكميات'!E15="","",'جدول الكميات'!E15) | E60: =N('جدول الكميات'!F15) | F60: =N('جدول الكميات'!G15) | G60: 0 | I60: =G60+H60 | J60: =IF(E60>0,I60/E60,0) | K60: =G60*F60 | L60: =N(H60)*F60 | M60: =I60*F60
B61: =IF('جدول الكميات'!B16="","",'جدول الكميات'!B16) | C61: =IF('جدول الكميات'!D16="","",'جدول الكميات'!D16) | D61: =IF('جدول الكميات'!E16="","",'جدول الكميات'!E16) | E61: =N('جدول الكميات'!F16) | F61: =N('جدول الكميات'!G16) | G61: 0 | I61: =G61+H61 | J61: =IF(E61>0,I61/E61,0) | K61: =G61*F61 | L61: =N(H61)*F61 | M61: =I61*F61
B62: =IF('جدول الكميات'!B17="","",'جدول الكميات'!B17) | C62: =IF('جدول الكميات'!D17="","",'جدول الكميات'!D17) | D62: =IF('جدول الكميات'!E17="","",'جدول الكميات'!E17) | E62: =N('جدول الكميات'!F17) | F62: =N('جدول الكميات'!G17) | G62: 0 | I62: =G62+H62 | J62: =IF(E62>0,I62/E62,0) | K62: =G62*F62 | L62: =N(H62)*F62 | M62: =I62*F62
B63: =IF('جدول الكميات'!B18="","",'جدول الكميات'!B18) | C63: =IF('جدول الكميات'!D18="","",'جدول الكميات'!D18) | D63: =IF('جدول الكميات'!E18="","",'جدول الكميات'!E18) | E63: =N('جدول الكميات'!F18) | F63: =N('جدول الكميات'!G18) | G63: 0 | I63: =G63+H63 | J63: =IF(E63>0,I63/E63,0) | K63: =G63*F63 | L63: =N(H63)*F63 | M63: =I63*F63
B64: =IF('جدول الكميات'!B19="","",'جدول الكميات'!B19) | C64: =IF('جدول الكميات'!D19="","",'جدول الكميات'!D19) | D64: =IF('جدول الكميات'!E19="","",'جدول الكميات'!E19) | E64: =N('جدول الكميات'!F19) | F64: =N('جدول الكميات'!G19) | G64: 0 | I64: =G64+H64 | J64: =IF(E64>0,I64/E64,0) | K64: =G64*F64 | L64: =N(H64)*F64 | M64: =I64*F64
B65: =IF('جدول الكميات'!B20="","",'جدول الكميات'!B20) | C65: =IF('جدول الكميات'!D20="","",'جدول الكميات'!D20) | D65: =IF('جدول الكميات'!E20="","",'جدول الكميات'!E20) | E65: =N('جدول الكميات'!F20) | F65: =N('جدول الكميات'!G20) | G65: 0 | I65: =G65+H65 | J65: =IF(E65>0,I65/E65,0) | K65: =G65*F65 | L65: =N(H65)*F65 | M65: =I65*F65
B66: =IF('جدول الكميات'!B21="","",'جدول الكميات'!B21) | C66: =IF('جدول الكميات'!D21="","",'جدول الكميات'!D21) | D66: =IF('جدول الكميات'!E21="","",'جدول الكميات'!E21) | E66: =N('جدول الكميات'!F21) | F66: =N('جدول الكميات'!G21) | G66: 0 | I66: =G66+H66 | J66: =IF(E66>0,I66/E66,0) | K66: =G66*F66 | L66: =N(H66)*F66 | M66: =I66*F66
B67: =IF('جدول الكميات'!B22="","",'جدول الكميات'!B22) | C67: =IF('جدول الكميات'!D22="","",'جدول الكميات'!D22) | D67: =IF('جدول الكميات'!E22="","",'جدول الكميات'!E22) | E67: =N('جدول الكميات'!F22) | F67: =N('جدول الكميات'!G22) | G67: 0 | I67: =G67+H67 | J67: =IF(E67>0,I67/E67,0) | K67: =G67*F67 | L67: =N(H67)*F67 | M67: =I67*F67
B68: =IF('جدول الكميات'!B23="","",'جدول الكميات'!B23) | C68: =IF('جدول الكميات'!D23="","",'جدول الكميات'!D23) | D68: =IF('جدول الكميات'!E23="","",'جدول الكميات'!E23) | E68: =N('جدول الكميات'!F23) | F68: =N('جدول الكميات'!G23) | G68: 0 | I68: =G68+H68 | J68: =IF(E68>0,I68/E68,0) | K68: =G68*F68 | L68: =N(H68)*F68 | M68: =I68*F68
B69: =IF('جدول الكميات'!B24="","",'جدول الكميات'!B24) | C69: =IF('جدول الكميات'!D24="","",'جدول الكميات'!D24) | D69: =IF('جدول الكميات'!E24="","",'جدول الكميات'!E24) | E69: =N('جدول الكميات'!F24) | F69: =N('جدول الكميات'!G24) | G69: 0 | I69: =G69+H69 | J69: =IF(E69>0,I69/E69,0) | K69: =G69*F69 | L69: =N(H69)*F69 | M69: =I69*F69
B70: =IF('جدول الكميات'!B25="","",'جدول الكميات'!B25) | C70: =IF('جدول الكميات'!D25="","",'جدول الكميات'!D25) | D70: =IF('جدول الكميات'!E25="","",'جدول الكميات'!E25) | E70: =N('جدول الكميات'!F25) | F70: =N('جدول الكميات'!G25) | G70: 0 | I70: =G70+H70 | J70: =IF(E70>0,I70/E70,0) | K70: =G70*F70 | L70: =N(H70)*F70 | M70: =I70*F70
... B150: =IF('جدول الكميات'!B105="","",'جدول الكميات'!B105) | C150: =IF('جدول الكميات'!D105="","",'جدول الكميات'!D105) | D150: =IF('جدول الكميات'!E105="","",'جدول الكميات'!E105) | E150: =N('جدول الكميات'!F105) | F150: =N('جدول الكميات'!G105) | G150: 0 | I150: =G150+H150 | J150: =IF(E150>0,I150/E150,0) | K150: =G150*F150 | L150: =N(H150)*F150 | M150: =I150*F150
B151: الإجمالي | K151: =SUM(K51:K150) | L151: =SUM(L51:L150) | M151: =SUM(M51:M150)

Sheet مستخلص 02
B1: 🧾 مستخلص أعمال رقم (2) — شهادة دفع مؤقتة (Interim Payment Certificate)
B2: =IF('بيانات العقد'!$C$5="","مشروع رقم 01 — أدخل بيانات العقد",'بيانات العقد'!$C$5&" | عقد رقم: "&'بيانات العقد'!$C$6)&" | المبالغ بـ "&'بيانات العقد'!$C$14
B3: 🗂 سجل المستخلصات | C3: ⚙ بيانات العقد | E3: 📋 جدول الكميات | G3: 🔁 التغييرية | I3: ✂ الاستقطاعات | K3: ◄ المستخلص السابق | L3: المستخلص التالي ►
B5: رقم المستخلص | C5: 2 | H5: حالة المستخلص | J5: معتمد | L5: نسبة الإنجاز الفعلية
B6: المشروع | C6: ='بيانات العقد'!C5 | H6: الفترة من | J6: 46113 | L6: =IF(ContractValue+L20>0,(L19+L20)/(ContractValue+L20),0)
B7: رقم العقد | C7: ='بيانات العقد'!C6 | H7: الفترة إلى | J7: 46142 | L7: نسبة الإنجاز المخططة (من البرنامج)
B8: صاحب العمل | C8: ='بيانات العقد'!C7 | H8: تاريخ التقديم | J8: 46147 | L8: 0.0618
B9: الاستشاري | C9: ='بيانات العقد'!C8 | H9: تاريخ الاعتماد | J9: 46164 | L9: الانحراف عن المخطط
B10: المقاول | C10: ='بيانات العقد'!C9 | H10: قيمة العقد المعدلة | J10: =RevisedContract | L10: =IF(L8="","",L6-L8)
B11: الرقم الضريبي للمقاول | C11: =IF('بيانات العقد'!C37="","",'بيانات العقد'!C37) | H11: الفترة بالتاريخ الهجري | J11: =IF(J6="","",J6) | K11: =IF(J7="","",J7)
B12: أولاً: بيانات الفترة (إدخال)
B13: رصيد المواد الموردة بالموقع (نهاية الفترة) | E13: 90000 | H13: إفراج عن ضمان الأعمال خلال الفترة
B14: غرامات تأخير / خصومات أخرى خلال الفترة | H14: سبب الغرامة / الخصم
B15: المبلغ المحصل من هذا المستخلص | E15: 753088.75 | H15: تاريخ التحصيل | K15: 46203
B16: رقم الفاتورة الضريبية (من نظام الفوترة الإلكترونية) | E16: INV-2026-01002 | H16: تاريخ الفاتورة الضريبية | K16: 46164
B17: ثانياً: الملخص المالي للمستخلص
B18: م | C18: البيان | H18: السابق | J18: الحالي | L18: الإجمالي التراكمي
B19: 1 | C19: قيمة الأعمال المنفذة طبقاً لحصر البنود | H19: ='مستخلص 01'!L19 | J19: =L19-H19 | L19: =M151
B20: 2 | C20: قيمة الأوامر التغييرية المعتمدة | H20: ='مستخلص 01'!L20 | J20: =L20-H20 | L20: =SUMIFS('الأوامر التغييرية'!$J$6:$J$55,'الأوامر التغييرية'!$H$6:$H$55,"معتمد",'الأوامر التغييرية'!$K$6:$K$55,"<="&$C$5)
B21: 3 | C21: المواد الموردة بالموقع (رصيد) | H21: ='مستخلص 01'!L21 | J21: =L21-H21 | L21: =N(E13)
B22: 4 | C22: إجمالي قيمة الأعمال | H22: ='مستخلص 01'!L22 | J22: =L22-H22 | L22: =SUM(L19:L21)
B23: 5 | C23: يُخصم: استرداد الدفعة المقدمة | H23: ='مستخلص 01'!L23 | J23: =L23-H23 | L23: =-ROUND(IF(L6>=RecFull,AdvAmount,MIN(AdvAmount,MAX(0,L19+L20-RecStart*ContractValue)*RecRate)),2)
B24: 6 | C24: يُخصم: ضمان الأعمال المحتسب | H24: ='مستخلص 01'!L24 | J24: =L24-H24 | L24: =-ROUND(MIN(L22*RetPct,RetCap),2)
B25: 7 | C25: يُضاف: المفرج عنه من ضمان الأعمال | H25: ='مستخلص 01'!L25 | J25: =L25-H25 | L25: =H25+N(K13)
B26: 8 | C26: يُخصم: الاستقطاعات الفنية المحتجزة | H26: ='مستخلص 01'!L26 | J26: =L26-H26 | L26: =-(SUMIFS('الاستقطاعات الفنية'!$I$6:$I$105,'الاستقطاعات الفنية'!$D$6:$D$105,"<="&$C$5)-SUMIFS('الاستقطاعات الفنية'!$I$6:$I$105,'الاستقطاعات الفنية'!$J$6:$J$105,"نعم",'الاستقطاعات الفنية'!$K$6:$K$105,"<="&$C$5))
B27: 9 | C27: يُخصم: الغرامات والخصومات الأخرى | H27: ='مستخلص 01'!L27 | J27: =L27-H27 | L27: =H27-N(E14)
B28: 10 | C28: صافي القيمة قبل الضرائب | H28: ='مستخلص 01'!L28 | J28: =L28-H28 | L28: =SUM(L22:L27)
B29: 11 | C29: يُضاف: ضريبة القيمة المضافة | H29: ='مستخلص 01'!L29 | J29: =L29-H29 | L29: =ROUND(VATPct*(L28+IF(VATBeforeRet="نعم",-(L24+L25),0)+IF(PenInVAT="لا",-L27,0)),2)
B30: 12 | C30: يُخصم: ضريبة الاستقطاع (غير المقيم) | H30: ='مستخلص 01'!L30 | J30: =L30-H30 | L30: =-ROUND(WHTPct*(L28-(L24+L25)),2)
B31: 13 | C31: صافي المستحق | H31: ='مستخلص 01'!L31 | J31: =L31-H31 | L31: =L28+L29+L30
B32: صافي المبلغ المستحق صرفه عن هذا المستخلص | J32: =J31
B33: المحصل من هذا المستخلص | J33: =N(E15)
B34: المتبقي غير المحصل | J34: =J32-J33
B35: فقط وقدره:
B37: ثالثاً: المستندات والمتطلبات النظامية للصرف (المملكة العربية السعودية)
B38: الفاتورة الضريبية الإلكترونية (متوافقة مع فاتورة - ZATCA) | F38: نعم | H38: شهادة الزكاة والضريبة سارية | L38: نعم
B39: شهادة التأمينات الاجتماعية (GOSI) سارية | F39: نعم | H39: شهادة نطاقات (التوطين) سارية | L39: نعم
B40: السجل التجاري وعضوية الغرفة التجارية سارية | F40: نعم | H40: محضر حصر الكميات معتمد من الاستشاري | L40: نعم
B41: ضمان الدفعة المقدمة ساري | F41: نعم | H41: الضمان النهائي ساري | L41: نعم
B42: وثيقة التأمين على الأعمال (CAR) سارية | F42: نعم | H42: تقرير الاستشاري الشهري | L42: نعم
B43: حالة المستندات: | E43: =IF(COUNTIF(F38:F42,"لا")+COUNTIF(L38:L42,"لا")+COUNTBLANK(F38:F42)+COUNTBLANK(L38:L42)=0,"✔ مكتملة — جاهز للصرف","⚠ ناقص "&(COUNTIF(F38:F42,"لا")+COUNTIF(L38:L42,"لا")+COUNTBLANK(F38:F42)+COUNTBLANK(L38:L42))&" مستند") | H43: الرقم الضريبي لصاحب العمل: | K43: =IF('بيانات العقد'!C39="","",'بيانات العقد'!C39)
B45: رابعاً: الاعتمادات
B46: إعداد: مهندس المقاول | F46: مراجعة: المهندس الاستشاري | J46: اعتماد: صاحب العمل
B47: الاسم: .................... التوقيع: .................. التاريخ: .................. | F47: الاسم: .................... التوقيع: .................. التاريخ: .................. | J47: الاسم: .................... التوقيع: .................. التاريخ: ..................
B49: خامساً: حصر الأعمال المنفذة حسب بنود جدول الكميات — أدخل «الكمية الحالية» فقط
B50: كود البند | C50: الوصف | D50: الوحدة | E50: الكمية التعاقدية | F50: سعر الوحدة | G50: الكمية السابقة | H50: الكمية الحالية | I50: الكمية التراكمية | J50: نسبة الإنجاز | K50: القيمة السابقة | L50: القيمة الحالية | M50: القيمة التراكمية
B51: =IF('جدول الكميات'!B6="","",'جدول الكميات'!B6) | C51: =IF('جدول الكميات'!D6="","",'جدول الكميات'!D6) | D51: =IF('جدول الكميات'!E6="","",'جدول الكميات'!E6) | E51: =N('جدول الكميات'!F6) | F51: =N('جدول الكميات'!G6) | G51: ='مستخلص 01'!I51 | H51: 1500 | I51: =G51+H51 | J51: =IF(E51>0,I51/E51,0) | K51: =G51*F51 | L51: =N(H51)*F51 | M51: =I51*F51
B52: =IF('جدول الكميات'!B7="","",'جدول الكميات'!B7) | C52: =IF('جدول الكميات'!D7="","",'جدول الكميات'!D7) | D52: =IF('جدول الكميات'!E7="","",'جدول الكميات'!E7) | E52: =N('جدول الكميات'!F7) | F52: =N('جدول الكميات'!G7) | G52: ='مستخلص 01'!I52 | H52: 733.33 | I52: =G52+H52 | J52: =IF(E52>0,I52/E52,0) | K52: =G52*F52 | L52: =N(H52)*F52 | M52: =I52*F52
B53: =IF('جدول الكميات'!B8="","",'جدول الكميات'!B8) | C53: =IF('جدول الكميات'!D8="","",'جدول الكميات'!D8) | D53: =IF('جدول الكميات'!E8="","",'جدول الكميات'!E8) | E53: =N('جدول الكميات'!F8) | F53: =N('جدول الكميات'!G8) | G53: ='مستخلص 01'!I53 | H53: 600 | I53: =G53+H53 | J53: =IF(E53>0,I53/E53,0) | K53: =G53*F53 | L53: =N(H53)*F53 | M53: =I53*F53
B54: =IF('جدول الكميات'!B9="","",'جدول الكميات'!B9) | C54: =IF('جدول الكميات'!D9="","",'جدول الكميات'!D9) | D54: =IF('جدول الكميات'!E9="","",'جدول الكميات'!E9) | E54: =N('جدول الكميات'!F9) | F54: =N('جدول الكميات'!G9) | G54: ='مستخلص 01'!I54 | H54: 50.67 | I54: =G54+H54 | J54: =IF(E54>0,I54/E54,0) | K54: =G54*F54 | L54: =N(H54)*F54 | M54: =I54*F54
B55: =IF('جدول الكميات'!B10="","",'جدول الكميات'!B10) | C55: =IF('جدول الكميات'!D10="","",'جدول الكميات'!D10) | D55: =IF('جدول الكميات'!E10="","",'جدول الكميات'!E10) | E55: =N('جدول الكميات'!F10) | F55: =N('جدول الكميات'!G10) | G55: ='مستخلص 01'!I55 | H55: 126.67 | I55: =G55+H55 | J55: =IF(E55>0,I55/E55,0) | K55: =G55*F55 | L55: =N(H55)*F55 | M55: =I55*F55
B56: =IF('جدول الكميات'!B11="","",'جدول الكميات'!B11) | C56: =IF('جدول الكميات'!D11="","",'جدول الكميات'!D11) | D56: =IF('جدول الكميات'!E11="","",'جدول الكميات'!E11) | E56: =N('جدول الكميات'!F11) | F56: =N('جدول الكميات'!G11) | G56: ='مستخلص 01'!I56 | H56: 56 | I56: =G56+H56 | J56: =IF(E56>0,I56/E56,0) | K56: =G56*F56 | L56: =N(H56)*F56 | M56: =I56*F56
B57: =IF('جدول الكميات'!B12="","",'جدول الكميات'!B12) | C57: =IF('جدول الكميات'!D12="","",'جدول الكميات'!D12) | D57: =IF('جدول الكميات'!E12="","",'جدول الكميات'!E12) | E57: =N('جدول الكميات'!F12) | F57: =N('جدول الكميات'!G12) | G57: ='مستخلص 01'!I57 | H57: 220 | I57: =G57+H57 | J57: =IF(E57>0,I57/E57,0) | K57: =G57*F57 | L57: =N(H57)*F57 | M57: =I57*F57
B58: =IF('جدول الكميات'!B13="","",'جدول الكميات'!B13) | C58: =IF('جدول الكميات'!D13="","",'جدول الكميات'!D13) | D58: =IF('جدول الكميات'!E13="","",'جدول الكميات'!E13) | E58: =N('جدول الكميات'!F13) | F58: =N('جدول الكميات'!G13) | G58: ='مستخلص 01'!I58 | H58: 64 | I58: =G58+H58 | J58: =IF(E58>0,I58/E58,0) | K58: =G58*F58 | L58: =N(H58)*F58 | M58: =I58*F58
B59: =IF('جدول الكميات'!B14="","",'جدول الكميات'!B14) | C59: =IF('جدول الكميات'!D14="","",'جدول الكميات'!D14) | D59: =IF('جدول الكميات'!E14="","",'جدول الكميات'!E14) | E59: =N('جدول الكميات'!F14) | F59: =N('جدول الكميات'!G14) | G59: ='مستخلص 01'!I59 | I59: =G59+H59 | J59: =IF(E59>0,I59/E59,0) | K59: =G59*F59 | L59: =N(H59)*F59 | M59: =I59*F59
B60: =IF('جدول الكميات'!B15="","",'جدول الكميات'!B15) | C60: =IF('جدول الكميات'!D15="","",'جدول الكميات'!D15) | D60: =IF('جدول الكميات'!E15="","",'جدول الكميات'!E15) | E60: =N('جدول الكميات'!F15) | F60: =N('جدول الكميات'!G15) | G60: ='مستخلص 01'!I60 | I60: =G60+H60 | J60: =IF(E60>0,I60/E60,0) | K60: =G60*F60 | L60: =N(H60)*F60 | M60: =I60*F60
B61: =IF('جدول الكميات'!B16="","",'جدول الكميات'!B16) | C61: =IF('جدول الكميات'!D16="","",'جدول الكميات'!D16) | D61: =IF('جدول الكميات'!E16="","",'جدول الكميات'!E16) | E61: =N('جدول الكميات'!F16) | F61: =N('جدول الكميات'!G16) | G61: ='مستخلص 01'!I61 | I61: =G61+H61 | J61: =IF(E61>0,I61/E61,0) | K61: =G61*F61 | L61: =N(H61)*F61 | M61: =I61*F61
B62: =IF('جدول الكميات'!B17="","",'جدول الكميات'!B17) | C62: =IF('جدول الكميات'!D17="","",'جدول الكميات'!D17) | D62: =IF('جدول الكميات'!E17="","",'جدول الكميات'!E17) | E62: =N('جدول الكميات'!F17) | F62: =N('جدول الكميات'!G17) | G62: ='مستخلص 01'!I62 | I62: =G62+H62 | J62: =IF(E62>0,I62/E62,0) | K62: =G62*F62 | L62: =N(H62)*F62 | M62: =I62*F62
B63: =IF('جدول الكميات'!B18="","",'جدول الكميات'!B18) | C63: =IF('جدول الكميات'!D18="","",'جدول الكميات'!D18) | D63: =IF('جدول الكميات'!E18="","",'جدول الكميات'!E18) | E63: =N('جدول الكميات'!F18) | F63: =N('جدول الكميات'!G18) | G63: ='مستخلص 01'!I63 | I63: =G63+H63 | J63: =IF(E63>0,I63/E63,0) | K63: =G63*F63 | L63: =N(H63)*F63 | M63: =I63*F63
B64: =IF('جدول الكميات'!B19="","",'جدول الكميات'!B19) | C64: =IF('جدول الكميات'!D19="","",'جدول الكميات'!D19) | D64: =IF('جدول الكميات'!E19="","",'جدول الكميات'!E19) | E64: =N('جدول الكميات'!F19) | F64: =N('جدول الكميات'!G19) | G64: ='مستخلص 01'!I64 | I64: =G64+H64 | J64: =IF(E64>0,I64/E64,0) | K64: =G64*F64 | L64: =N(H64)*F64 | M64: =I64*F64
B65: =IF('جدول الكميات'!B20="","",'جدول الكميات'!B20) | C65: =IF('جدول الكميات'!D20="","",'جدول الكميات'!D20) | D65: =IF('جدول الكميات'!E20="","",'جدول الكميات'!E20) | E65: =N('جدول الكميات'!F20) | F65: =N('جدول الكميات'!G20) | G65: ='مستخلص 01'!I65 | I65: =G65+H65 | J65: =IF(E65>0,I65/E65,0) | K65: =G65*F65 | L65: =N(H65)*F65 | M65: =I65*F65
B66: =IF('جدول الكميات'!B21="","",'جدول الكميات'!B21) | C66: =IF('جدول الكميات'!D21="","",'جدول الكميات'!D21) | D66: =IF('جدول الكميات'!E21="","",'جدول الكميات'!E21) | E66: =N('جدول الكميات'!F21) | F66: =N('جدول الكميات'!G21) | G66: ='مستخلص 01'!I66 | I66: =G66+H66 | J66: =IF(E66>0,I66/E66,0) | K66: =G66*F66 | L66: =N(H66)*F66 | M66: =I66*F66
B67: =IF('جدول الكميات'!B22="","",'جدول الكميات'!B22) | C67: =IF('جدول الكميات'!D22="","",'جدول الكميات'!D22) | D67: =IF('جدول الكميات'!E22="","",'جدول الكميات'!E22) | E67: =N('جدول الكميات'!F22) | F67: =N('جدول الكميات'!G22) | G67: ='مستخلص 01'!I67 | I67: =G67+H67 | J67: =IF(E67>0,I67/E67,0) | K67: =G67*F67 | L67: =N(H67)*F67 | M67: =I67*F67
B68: =IF('جدول الكميات'!B23="","",'جدول الكميات'!B23) | C68: =IF('جدول الكميات'!D23="","",'جدول الكميات'!D23) | D68: =IF('جدول الكميات'!E23="","",'جدول الكميات'!E23) | E68: =N('جدول الكميات'!F23) | F68: =N('جدول الكميات'!G23) | G68: ='مستخلص 01'!I68 | I68: =G68+H68 | J68: =IF(E68>0,I68/E68,0) | K68: =G68*F68 | L68: =N(H68)*F68 | M68: =I68*F68
B69: =IF('جدول الكميات'!B24="","",'جدول الكميات'!B24) | C69: =IF('جدول الكميات'!D24="","",'جدول الكميات'!D24) | D69: =IF('جدول الكميات'!E24="","",'جدول الكميات'!E24) | E69: =N('جدول الكميات'!F24) | F69: =N('جدول الكميات'!G24) | G69: ='مستخلص 01'!I69 | I69: =G69+H69 | J69: =IF(E69>0,I69/E69,0) | K69: =G69*F69 | L69: =N(H69)*F69 | M69: =I69*F69
B70: =IF('جدول الكميات'!B25="","",'جدول الكميات'!B25) | C70: =IF('جدول الكميات'!D25="","",'جدول الكميات'!D25) | D70: =IF('جدول الكميات'!E25="","",'جدول الكميات'!E25) | E70: =N('جدول الكميات'!F25) | F70: =N('جدول الكميات'!G25) | G70: ='مستخلص 01'!I70 | I70: =G70+H70 | J70: =IF(E70>0,I70/E70,0) | K70: =G70*F70 | L70: =N(H70)*F70 | M70: =I70*F70
... B150: =IF('جدول الكميات'!B105="","",'جدول الكميات'!B105) | C150: =IF('جدول الكميات'!D105="","",'جدول الكميات'!D105) | D150: =IF('جدول الكميات'!E105="","",'جدول الكميات'!E105) | E150: =N('جدول الكميات'!F105) | F150: =N('جدول الكميات'!G105) | G150: ='مستخلص 01'!I150 | I150: =G150+H150 | J150: =IF(E150>0,I150/E150,0) | K150: =G150*F150 | L150: =N(H150)*F150 | M150: =I150*F150
B151: الإجمالي | K151: =SUM(K51:K150) | L151: =SUM(L51:L150) | M151: =SUM(M51:M150)

Sheet مستخلص 03
B1: 🧾 مستخلص أعمال رقم (3) — شهادة دفع مؤقتة (Interim Payment Certificate)
B2: =IF('بيانات العقد'!$C$5="","مشروع رقم 01 — أدخل بيانات العقد",'بيانات العقد'!$C$5&" | عقد رقم: "&'بيانات العقد'!$C$6)&" | المبالغ بـ "&'بيانات العقد'!$C$14
B3: 🗂 سجل المستخلصات | C3: ⚙ بيانات العقد | E3: 📋 جدول الكميات | G3: 🔁 التغييرية | I3: ✂ الاستقطاعات | K3: ◄ المستخلص السابق | L3: المستخلص التالي ►
B5: رقم المستخلص | C5: 3 | H5: حالة المستخلص | J5: معتمد | L5: نسبة الإنجاز الفعلية
B6: المشروع | C6: ='بيانات العقد'!C5 | H6: الفترة من | J6: 46143 | L6: =IF(ContractValue+L20>0,(L19+L20)/(ContractValue+L20),0)
B7: رقم العقد | C7: ='بيانات العقد'!C6 | H7: الفترة إلى | J7: 46173 | L7: نسبة الإنجاز المخططة (من البرنامج)
B8: صاحب العمل | C8: ='بيانات العقد'!C7 | H8: تاريخ التقديم | J8: 46178 | L8: 0.1133
B9: الاستشاري | C9: ='بيانات العقد'!C8 | H9: تاريخ الاعتماد | J9: 46193 | L9: الانحراف عن المخطط
B10: المقاول | C10: ='بيانات العقد'!C9 | H10: قيمة العقد المعدلة | J10: =RevisedContract | L10: =IF(L8="","",L6-L8)
B11: الرقم الضريبي للمقاول | C11: =IF('بيانات العقد'!C37="","",'بيانات العقد'!C37) | H11: الفترة بالتاريخ الهجري | J11: =IF(J6="","",J6) | K11: =IF(J7="","",J7)
B12: أولاً: بيانات الفترة (إدخال)
B13: رصيد المواد الموردة بالموقع (نهاية الفترة) | E13: 180000 | H13: إفراج عن ضمان الأعمال خلال الفترة
B14: غرامات تأخير / خصومات أخرى خلال الفترة | H14: سبب الغرامة / الخصم
B15: المبلغ المحصل من هذا المستخلص | E15: 771595.01 | H15: تاريخ التحصيل | K15: 46223
B16: رقم الفاتورة الضريبية (من نظام الفوترة الإلكترونية) | E16: INV-2026-01003 | H16: تاريخ الفاتورة الضريبية | K16: 46193
B17: ثانياً: الملخص المالي للمستخلص
B18: م | C18: البيان | H18: السابق | J18: الحالي | L18: الإجمالي التراكمي
B19: 1 | C19: قيمة الأعمال المنفذة طبقاً لحصر البنود | H19: ='مستخلص 02'!L19 | J19: =L19-H19 | L19: =M151
B20: 2 | C20: قيمة الأوامر التغييرية المعتمدة | H20: ='مستخلص 02'!L20 | J20: =L20-H20 | L20: =SUMIFS('الأوامر التغييرية'!$J$6:$J$55,'الأوامر التغييرية'!$H$6:$H$55,"معتمد",'الأوامر التغييرية'!$K$6:$K$55,"<="&$C$5)
B21: 3 | C21: المواد الموردة بالموقع (رصيد) | H21: ='مستخلص 02'!L21 | J21: =L21-H21 | L21: =N(E13)
B22: 4 | C22: إجمالي قيمة الأعمال | H22: ='مستخلص 02'!L22 | J22: =L22-H22 | L22: =SUM(L19:L21)
B23: 5 | C23: يُخصم: استرداد الدفعة المقدمة | H23: ='مستخلص 02'!L23 | J23: =L23-H23 | L23: =-ROUND(IF(L6>=RecFull,AdvAmount,MIN(AdvAmount,MAX(0,L19+L20-RecStart*ContractValue)*RecRate)),2)
B24: 6 | C24: يُخصم: ضمان الأعمال المحتسب | H24: ='مستخلص 02'!L24 | J24: =L24-H24 | L24: =-ROUND(MIN(L22*RetPct,RetCap),2)
B25: 7 | C25: يُضاف: المفرج عنه من ضمان الأعمال | H25: ='مستخلص 02'!L25 | J25: =L25-H25 | L25: =H25+N(K13)
B26: 8 | C26: يُخصم: الاستقطاعات الفنية المحتجزة | H26: ='مستخلص 02'!L26 | J26: =L26-H26 | L26: =-(SUMIFS('الاستقطاعات الفنية'!$I$6:$I$105,'الاستقطاعات الفنية'!$D$6:$D$105,"<="&$C$5)-SUMIFS('الاستقطاعات الفنية'!$I$6:$I$105,'الاستقطاعات الفنية'!$J$6:$J$105,"نعم",'الاستقطاعات الفنية'!$K$6:$K$105,"<="&$C$5))
B27: 9 | C27: يُخصم: الغرامات والخصومات الأخرى | H27: ='مستخلص 02'!L27 | J27: =L27-H27 | L27: =H27-N(E14)
B28: 10 | C28: صافي القيمة قبل الضرائب | H28: ='مستخلص 02'!L28 | J28: =L28-H28 | L28: =SUM(L22:L27)
B29: 11 | C29: يُضاف: ضريبة القيمة المضافة | H29: ='مستخلص 02'!L29 | J29: =L29-H29 | L29: =ROUND(VATPct*(L28+IF(VATBeforeRet="نعم",-(L24+L25),0)+IF(PenInVAT="لا",-L27,0)),2)
B30: 12 | C30: يُخصم: ضريبة الاستقطاع (غير المقيم) | H30: ='مستخلص 02'!L30 | J30: =L30-H30 | L30: =-ROUND(WHTPct*(L28-(L24+L25)),2)
B31: 13 | C31: صافي المستحق | H31: ='مستخلص 02'!L31 | J31: =L31-H31 | L31: =L28+L29+L30
B32: صافي المبلغ المستحق صرفه عن هذا المستخلص | J32: =J31
B33: المحصل من هذا المستخلص | J33: =N(E15)
B34: المتبقي غير المحصل | J34: =J32-J33
B35: فقط وقدره:
B37: ثالثاً: المستندات والمتطلبات النظامية للصرف (المملكة العربية السعودية)
B38: الفاتورة الضريبية الإلكترونية (متوافقة مع فاتورة - ZATCA) | F38: نعم | H38: شهادة الزكاة والضريبة سارية | L38: نعم
B39: شهادة التأمينات الاجتماعية (GOSI) سارية | F39: نعم | H39: شهادة نطاقات (التوطين) سارية | L39: نعم
B40: السجل التجاري وعضوية الغرفة التجارية سارية | F40: نعم | H40: محضر حصر الكميات معتمد من الاستشاري | L40: نعم
B41: ضمان الدفعة المقدمة ساري | F41: نعم | H41: الضمان النهائي ساري | L41: نعم
B42: وثيقة التأمين على الأعمال (CAR) سارية | F42: نعم | H42: تقرير الاستشاري الشهري | L42: نعم
B43: حالة المستندات: | E43: =IF(COUNTIF(F38:F42,"لا")+COUNTIF(L38:L42,"لا")+COUNTBLANK(F38:F42)+COUNTBLANK(L38:L42)=0,"✔ مكتملة — جاهز للصرف","⚠ ناقص "&(COUNTIF(F38:F42,"لا")+COUNTIF(L38:L42,"لا")+COUNTBLANK(F38:F42)+COUNTBLANK(L38:L42))&" مستند") | H43: الرقم الضريبي لصاحب العمل: | K43: =IF('بيانات العقد'!C39="","",'بيانات العقد'!C39)
B45: رابعاً: الاعتمادات
B46: إعداد: مهندس المقاول | F46: مراجعة: المهندس الاستشاري | J46: اعتماد: صاحب العمل
B47: الاسم: .................... التوقيع: .................. التاريخ: .................. | F47: الاسم: .................... التوقيع: .................. التاريخ: .................. | J47: الاسم: .................... التوقيع: .................. التاريخ: ..................
B49: خامساً: حصر الأعمال المنفذة حسب بنود جدول الكميات — أدخل «الكمية الحالية» فقط
B50: كود البند | C50: الوصف | D50: الوحدة | E50: الكمية التعاقدية | F50: سعر الوحدة | G50: الكمية السابقة | H50: الكمية الحالية | I50: الكمية التراكمية | J50: نسبة الإنجاز | K50: القيمة السابقة | L50: القيمة الحالية | M50: القيمة التراكمية
B51: =IF('جدول الكميات'!B6="","",'جدول الكميات'!B6) | C51: =IF('جدول الكميات'!D6="","",'جدول الكميات'!D6) | D51: =IF('جدول الكميات'!E6="","",'جدول الكميات'!E6) | E51: =N('جدول الكميات'!F6) | F51: =N('جدول الكميات'!G6) | G51: ='مستخلص 02'!I51 | H51: 1500 | I51: =G51+H51 | J51: =IF(E51>0,I51/E51,0) | K51: =G51*F51 | L51: =N(H51)*F51 | M51: =I51*F51
B52: =IF('جدول الكميات'!B7="","",'جدول الكميات'!B7) | C52: =IF('جدول الكميات'!D7="","",'جدول الكميات'!D7) | D52: =IF('جدول الكميات'!E7="","",'جدول الكميات'!E7) | E52: =N('جدول الكميات'!F7) | F52: =N('جدول الكميات'!G7) | G52: ='مستخلص 02'!I52 | H52: 733.33 | I52: =G52+H52 | J52: =IF(E52>0,I52/E52,0) | K52: =G52*F52 | L52: =N(H52)*F52 | M52: =I52*F52
B53: =IF('جدول الكميات'!B8="","",'جدول الكميات'!B8) | C53: =IF('جدول الكميات'!D8="","",'جدول الكميات'!D8) | D53: =IF('جدول الكميات'!E8="","",'جدول الكميات'!E8) | E53: =N('جدول الكميات'!F8) | F53: =N('جدول الكميات'!G8) | G53: ='مستخلص 02'!I53 | H53: 600 | I53: =G53+H53 | J53: =IF(E53>0,I53/E53,0) | K53: =G53*F53 | L53: =N(H53)*F53 | M53: =I53*F53
B54: =IF('جدول الكميات'!B9="","",'جدول الكميات'!B9) | C54: =IF('جدول الكميات'!D9="","",'جدول الكميات'!D9) | D54: =IF('جدول الكميات'!E9="","",'جدول الكميات'!E9) | E54: =N('جدول الكميات'!F9) | F54: =N('جدول الكميات'!G9) | G54: ='مستخلص 02'!I54 | H54: 50.67 | I54: =G54+H54 | J54: =IF(E54>0,I54/E54,0) | K54: =G54*F54 | L54: =N(H54)*F54 | M54: =I54*F54
B55: =IF('جدول الكميات'!B10="","",'جدول الكميات'!B10) | C55: =IF('جدول الكميات'!D10="","",'جدول الكميات'!D10) | D55: =IF('جدول الكميات'!E10="","",'جدول الكميات'!E10) | E55: =N('جدول الكميات'!F10) | F55: =N('جدول الكميات'!G10) | G55: ='مستخلص 02'!I55 | H55: 126.67 | I55: =G55+H55 | J55: =IF(E55>0,I55/E55,0) | K55: =G55*F55 | L55: =N(H55)*F55 | M55: =I55*F55
B56: =IF('جدول الكميات'!B11="","",'جدول الكميات'!B11) | C56: =IF('جدول الكميات'!D11="","",'جدول الكميات'!D11) | D56: =IF('جدول الكميات'!E11="","",'جدول الكميات'!E11) | E56: =N('جدول الكميات'!F11) | F56: =N('جدول الكميات'!G11) | G56: ='مستخلص 02'!I56 | H56: 56 | I56: =G56+H56 | J56: =IF(E56>0,I56/E56,0) | K56: =G56*F56 | L56: =N(H56)*F56 | M56: =I56*F56
B57: =IF('جدول الكميات'!B12="","",'جدول الكميات'!B12) | C57: =IF('جدول الكميات'!D12="","",'جدول الكميات'!D12) | D57: =IF('جدول الكميات'!E12="","",'جدول الكميات'!E12) | E57: =N('جدول الكميات'!F12) | F57: =N('جدول الكميات'!G12) | G57: ='مستخلص 02'!I57 | H57: 220 | I57: =G57+H57 | J57: =IF(E57>0,I57/E57,0) | K57: =G57*F57 | L57: =N(H57)*F57 | M57: =I57*F57
B58: =IF('جدول الكميات'!B13="","",'جدول الكميات'!B13) | C58: =IF('جدول الكميات'!D13="","",'جدول الكميات'!D13) | D58: =IF('جدول الكميات'!E13="","",'جدول الكميات'!E13) | E58: =N('جدول الكميات'!F13) | F58: =N('جدول الكميات'!G13) | G58: ='مستخلص 02'!I58 | H58: 64 | I58: =G58+H58 | J58: =IF(E58>0,I58/E58,0) | K58: =G58*F58 | L58: =N(H58)*F58 | M58: =I58*F58
B59: =IF('جدول الكميات'!B14="","",'جدول الكميات'!B14) | C59: =IF('جدول الكميات'!D14="","",'جدول الكميات'!D14) | D59: =IF('جدول الكميات'!E14="","",'جدول الكميات'!E14) | E59: =N('جدول الكميات'!F14) | F59: =N('جدول الكميات'!G14) | G59: ='مستخلص 02'!I59 | I59: =G59+H59 | J59: =IF(E59>0,I59/E59,0) | K59: =G59*F59 | L59: =N(H59)*F59 | M59: =I59*F59
B60: =IF('جدول الكميات'!B15="","",'جدول الكميات'!B15) | C60: =IF('جدول الكميات'!D15="","",'جدول الكميات'!D15) | D60: =IF('جدول الكميات'!E15="","",'جدول الكميات'!E15) | E60: =N('جدول الكميات'!F15) | F60: =N('جدول الكميات'!G15) | G60: ='مستخلص 02'!I60 | I60: =G60+H60 | J60: =IF(E60>0,I60/E60,0) | K60: =G60*F60 | L60: =N(H60)*F60 | M60: =I60*F60
B61: =IF('جدول الكميات'!B16="","",'جدول الكميات'!B16) | C61: =IF('جدول الكميات'!D16="","",'جدول الكميات'!D16) | D61: =IF('جدول الكميات'!E16="","",'جدول الكميات'!E16) | E61: =N('جدول الكميات'!F16) | F61: =N('جدول الكميات'!G16) | G61: ='مستخلص 02'!I61 | H61: 72 | I61: =G61+H61 | J61: =IF(E61>0,I61/E61,0) | K61: =G61*F61 | L61: =N(H61)*F61 | M61: =I61*F61
B62: =IF('جدول الكميات'!B17="","",'جدول الكميات'!B17) | C62: =IF('جدول الكميات'!D17="","",'جدول الكميات'!D17) | D62: =IF('جدول الكميات'!E17="","",'جدول الكميات'!E17) | E62: =N('جدول الكميات'!F17) | F62: =N('جدول الكميات'!G17) | G62: ='مستخلص 02'!I62 | H62: 57 | I62: =G62+H62 | J62: =IF(E62>0,I62/E62,0) | K62: =G62*F62 | L62: =N(H62)*F62 | M62: =I62*F62
B63: =IF('جدول الكميات'!B18="","",'جدول الكميات'!B18) | C63: =IF('جدول الكميات'!D18="","",'جدول الكميات'!D18) | D63: =IF('جدول الكميات'!E18="","",'جدول الكميات'!E18) | E63: =N('جدول الكميات'!F18) | F63: =N('جدول الكميات'!G18) | G63: ='مستخلص 02'!I63 | I63: =G63+H63 | J63: =IF(E63>0,I63/E63,0) | K63: =G63*F63 | L63: =N(H63)*F63 | M63: =I63*F63
B64: =IF('جدول الكميات'!B19="","",'جدول الكميات'!B19) | C64: =IF('جدول الكميات'!D19="","",'جدول الكميات'!D19) | D64: =IF('جدول الكميات'!E19="","",'جدول الكميات'!E19) | E64: =N('جدول الكميات'!F19) | F64: =N('جدول الكميات'!G19) | G64: ='مستخلص 02'!I64 | I64: =G64+H64 | J64: =IF(E64>0,I64/E64,0) | K64: =G64*F64 | L64: =N(H64)*F64 | M64: =I64*F64
B65: =IF('جدول الكميات'!B20="","",'جدول الكميات'!B20) | C65: =IF('جدول الكميات'!D20="","",'جدول الكميات'!D20) | D65: =IF('جدول الكميات'!E20="","",'جدول الكميات'!E20) | E65: =N('جدول الكميات'!F20) | F65: =N('جدول الكميات'!G20) | G65: ='مستخلص 02'!I65 | I65: =G65+H65 | J65: =IF(E65>0,I65/E65,0) | K65: =G65*F65 | L65: =N(H65)*F65 | M65: =I65*F65
B66: =IF('جدول الكميات'!B21="","",'جدول الكميات'!B21) | C66: =IF('جدول الكميات'!D21="","",'جدول الكميات'!D21) | D66: =IF('جدول الكميات'!E21="","",'جدول الكميات'!E21) | E66: =N('جدول الكميات'!F21) | F66: =N('جدول الكميات'!G21) | G66: ='مستخلص 02'!I66 | I66: =G66+H66 | J66: =IF(E66>0,I66/E66,0) | K66: =G66*F66 | L66: =N(H66)*F66 | M66: =I66*F66
B67: =IF('جدول الكميات'!B22="","",'جدول الكميات'!B22) | C67: =IF('جدول الكميات'!D22="","",'جدول الكميات'!D22) | D67: =IF('جدول الكميات'!E22="","",'جدول الكميات'!E22) | E67: =N('جدول الكميات'!F22) | F67: =N('جدول الكميات'!G22) | G67: ='مستخلص 02'!I67 | I67: =G67+H67 | J67: =IF(E67>0,I67/E67,0) | K67: =G67*F67 | L67: =N(H67)*F67 | M67: =I67*F67
B68: =IF('جدول الكميات'!B23="","",'جدول الكميات'!B23) | C68: =IF('جدول الكميات'!D23="","",'جدول الكميات'!D23) | D68: =IF('جدول الكميات'!E23="","",'جدول الكميات'!E23) | E68: =N('جدول الكميات'!F23) | F68: =N('جدول الكميات'!G23) | G68: ='مستخلص 02'!I68 | I68: =G68+H68 | J68: =IF(E68>0,I68/E68,0) | K68: =G68*F68 | L68: =N(H68)*F68 | M68: =I68*F68
B69: =IF('جدول الكميات'!B24="","",'جدول الكميات'!B24) | C69: =IF('جدول الكميات'!D24="","",'جدول الكميات'!D24) | D69: =IF('جدول الكميات'!E24="","",'جدول الكميات'!E24) | E69: =N('جدول الكميات'!F24) | F69: =N('جدول الكميات'!G24) | G69: ='مستخلص 02'!I69 | I69: =G69+H69 | J69: =IF(E69>0,I69/E69,0) | K69: =G69*F69 | L69: =N(H69)*F69 | M69: =I69*F69
B70: =IF('جدول الكميات'!B25="","",'جدول الكميات'!B25) | C70: =IF('جدول الكميات'!D25="","",'جدول الكميات'!D25) | D70: =IF('جدول الكميات'!E25="","",'جدول الكميات'!E25) | E70: =N('جدول الكميات'!F25) | F70: =N('جدول الكميات'!G25) | G70: ='مستخلص 02'!I70 | I70: =G70+H70 | J70: =IF(E70>0,I70/E70,0) | K70: =G70*F70 | L70: =N(H70)*F70 | M70: =I70*F70
B71: =IF('جدول الكميات'!B26="","",'جدول الكميات'!B26) | C71: =IF('جدول الكميات'!D26="","",'جدول الكميات'!D26) | D71: =IF('جدول الكميات'!E26="","",'جدول الكميات'!E26) | E71: =N('جدول الكميات'!F26) | F71: =N('جدول الكميات'!G26) | G71: ='مستخلص 02'!I71 | I71: =G71+H71 | J71: =IF(E71>0,I71/E71,0) | K71: =G71*F71 | L71: =N(H71)*F71 | M71: =I71*F71
B72: =IF('جدول الكميات'!B27="","",'جدول الكميات'!B27) | C72: =IF('جدول الكميات'!D27="","",'جدول الكميات'!D27) | D72: =IF('جدول الكميات'!E27="","",'جدول الكميات'!E27) | E72: =N('جدول الكميات'!F27) | F72: =N('جدول الكميات'!G27) | G72: ='مستخلص 02'!I72 | I72: =G72+H72 | J72: =IF(E72>0,I72/E72,0) | K72: =G72*F72 | L72: =N(H72)*F72 | M72: =I72*F72
B73: =IF('جدول الكميات'!B28="","",'جدول الكميات'!B28) | C73: =IF('جدول الكميات'!D28="","",'جدول الكميات'!D28) | D73: =IF('جدول الكميات'!E28="","",'جدول الكميات'!E28) | E73: =N('جدول الكميات'!F28) | F73: =N('جدول الكميات'!G28) | G73: ='مستخلص 02'!I73 | I73: =G73+H73 | J73: =IF(E73>0,I73/E73,0) | K73: =G73*F73 | L73: =N(H73)*F73 | M73: =I73*F73
B74: =IF('جدول الكميات'!B29="","",'جدول الكميات'!B29) | C74: =IF('جدول الكميات'!D29="","",'جدول الكميات'!D29) | D74: =IF('جدول الكميات'!E29="","",'جدول الكميات'!E29) | E74: =N('جدول الكميات'!F29) | F74: =N('جدول الكميات'!G29) | G74: ='مستخلص 02'!I74 | I74: =G74+H74 | J74: =IF(E74>0,I74/E74,0) | K74: =G74*F74 | L74: =N(H74)*F74 | M74: =I74*F74
... B150: =IF('جدول الكميات'!B105="","",'جدول الكميات'!B105) | C150: =IF('جدول الكميات'!D105="","",'جدول الكميات'!D105) | D150: =IF('جدول الكميات'!E105="","",'جدول الكميات'!E105) | E150: =N('جدول الكميات'!F105) | F150: =N('جدول الكميات'!G105) | G150: ='مستخلص 02'!I150 | I150: =G150+H150 | J150: =IF(E150>0,I150/E150,0) | K150: =G150*F150 | L150: =N(H150)*F150 | M150: =I150*F150
B151: الإجمالي | K151: =SUM(K51:K150) | L151: =SUM(L51:L150) | M151: =SUM(M51:M150)

Sheet مستخلص 04
B1: 🧾 مستخلص أعمال رقم (4) — شهادة دفع مؤقتة (Interim Payment Certificate)
B2: =IF('بيانات العقد'!$C$5="","مشروع رقم 01 — أدخل بيانات العقد",'بيانات العقد'!$C$5&" | عقد رقم: "&'بيانات العقد'!$C$6)&" | المبالغ بـ "&'بيانات العقد'!$C$14
B3: 🗂 سجل المستخلصات | C3: ⚙ بيانات العقد | E3: 📋 جدول الكميات | G3: 🔁 التغييرية | I3: ✂ الاستقطاعات | K3: ◄ المستخلص السابق | L3: المستخلص التالي ►
B5: رقم المستخلص | C5: 4 | H5: حالة المستخلص | J5: معتمد | L5: نسبة الإنجاز الفعلية
B6: المشروع | C6: ='بيانات العقد'!C5 | H6: الفترة من | J6: 46174 | L6: =IF(ContractValue+L20>0,(L19+L20)/(ContractValue+L20),0)
B7: رقم العقد | C7: ='بيانات العقد'!C6 | H7: الفترة إلى | J7: 46203 | L7: نسبة الإنجاز المخططة (من البرنامج)
B8: صاحب العمل | C8: ='بيانات العقد'!C7 | H8: تاريخ التقديم | J8: 46208 | L8: 0.1613
B9: الاستشاري | C9: ='بيانات العقد'!C8 | H9: تاريخ الاعتماد | J9: 46224 | L9: الانحراف عن المخطط
B10: المقاول | C10: ='بيانات العقد'!C9 | H10: قيمة العقد المعدلة | J10: =RevisedContract | L10: =IF(L8="","",L6-L8)
B11: الرقم الضريبي للمقاول | C11: =IF('بيانات العقد'!C37="","",'بيانات العقد'!C37) | H11: الفترة بالتاريخ الهجري | J11: =IF(J6="","",J6) | K11: =IF(J7="","",J7)
B12: أولاً: بيانات الفترة (إدخال)
B13: رصيد المواد الموردة بالموقع (نهاية الفترة) | E13: 120000 | H13: إفراج عن ضمان الأعمال خلال الفترة
B14: غرامات تأخير / خصومات أخرى خلال الفترة | H14: سبب الغرامة / الخصم
B15: المبلغ المحصل من هذا المستخلص | E15: 801710.84 | H15: تاريخ التحصيل | K15: 46261
B16: رقم الفاتورة الضريبية (من نظام الفوترة الإلكترونية) | E16: INV-2026-01004 | H16: تاريخ الفاتورة الضريبية | K16: 46224
B17: ثانياً: الملخص المالي للمستخلص
B18: م | C18: البيان | H18: السابق | J18: الحالي | L18: الإجمالي التراكمي
B19: 1 | C19: قيمة الأعمال المنفذة طبقاً لحصر البنود | H19: ='مستخلص 03'!L19 | J19: =L19-H19 | L19: =M151
B20: 2 | C20: قيمة الأوامر التغييرية المعتمدة | H20: ='مستخلص 03'!L20 | J20: =L20-H20 | L20: =SUMIFS('الأوامر التغييرية'!$J$6:$J$55,'الأوامر التغييرية'!$H$6:$H$55,"معتمد",'الأوامر التغييرية'!$K$6:$K$55,"<="&$C$5)
B21: 3 | C21: المواد الموردة بالموقع (رصيد) | H21: ='مستخلص 03'!L21 | J21: =L21-H21 | L21: =N(E13)
B22: 4 | C22: إجمالي قيمة الأعمال | H22: ='مستخلص 03'!L22 | J22: =L22-H22 | L22: =SUM(L19:L21)
B23: 5 | C23: يُخصم: استرداد الدفعة المقدمة | H23: ='مستخلص 03'!L23 | J23: =L23-H23 | L23: =-ROUND(IF(L6>=RecFull,AdvAmount,MIN(AdvAmount,MAX(0,L19+L20-RecStart*ContractValue)*RecRate)),2)
B24: 6 | C24: يُخصم: ضمان الأعمال المحتسب | H24: ='مستخلص 03'!L24 | J24: =L24-H24 | L24: =-ROUND(MIN(L22*RetPct,RetCap),2)
B25: 7 | C25: يُضاف: المفرج عنه من ضمان الأعمال | H25: ='مستخلص 03'!L25 | J25: =L25-H25 | L25: =H25+N(K13)
B26: 8 | C26: يُخصم: الاستقطاعات الفنية المحتجزة | H26: ='مستخلص 03'!L26 | J26: =L26-H26 | L26: =-(SUMIFS('الاستقطاعات الفنية'!$I$6:$I$105,'الاستقطاعات الفنية'!$D$6:$D$105,"<="&$C$5)-SUMIFS('الاستقطاعات الفنية'!$I$6:$I$105,'الاستقطاعات الفنية'!$J$6:$J$105,"نعم",'الاستقطاعات الفنية'!$K$6:$K$105,"<="&$C$5))
B27: 9 | C27: يُخصم: الغرامات والخصومات الأخرى | H27: ='مستخلص 03'!L27 | J27: =L27-H27 | L27: =H27-N(E14)
B28: 10 | C28: صافي القيمة قبل الضرائب | H28: ='مستخلص 03'!L28 | J28: =L28-H28 | L28: =SUM(L22:L27)
B29: 11 | C29: يُضاف: ضريبة القيمة المضافة | H29: ='مستخلص 03'!L29 | J29: =L29-H29 | L29: =ROUND(VATPct*(L28+IF(VATBeforeRet="نعم",-(L24+L25),0)+IF(PenInVAT="لا",-L27,0)),2)
B30: 12 | C30: يُخصم: ضريبة الاستقطاع (غير المقيم) | H30: ='مستخلص 03'!L30 | J30: =L30-H30 | L30: =-ROUND(WHTPct*(L28-(L24+L25)),2)
B31: 13 | C31: صافي المستحق | H31: ='مستخلص 03'!L31 | J31: =L31-H31 | L31: =L28+L29+L30
B32: صافي المبلغ المستحق صرفه عن هذا المستخلص | J32: =J31
B33: المحصل من هذا المستخلص | J33: =N(E15)
B34: المتبقي غير المحصل | J34: =J32-J33
B35: فقط وقدره:
B37: ثالثاً: المستندات والمتطلبات النظامية للصرف (المملكة العربية السعودية)
B38: الفاتورة الضريبية الإلكترونية (متوافقة مع فاتورة - ZATCA) | F38: نعم | H38: شهادة الزكاة والضريبة سارية | L38: نعم
B39: شهادة التأمينات الاجتماعية (GOSI) سارية | F39: نعم | H39: شهادة نطاقات (التوطين) سارية | L39: نعم
B40: السجل التجاري وعضوية الغرفة التجارية سارية | F40: نعم | H40: محضر حصر الكميات معتمد من الاستشاري | L40: نعم
B41: ضمان الدفعة المقدمة ساري | F41: نعم | H41: الضمان النهائي ساري | L41: نعم
B42: وثيقة التأمين على الأعمال (CAR) سارية | F42: نعم | H42: تقرير الاستشاري الشهري | L42: نعم
B43: حالة المستندات: | E43: =IF(COUNTIF(F38:F42,"لا")+COUNTIF(L38:L42,"لا")+COUNTBLANK(F38:F42)+COUNTBLANK(L38:L42)=0,"✔ مكتملة — جاهز للصرف","⚠ ناقص "&(COUNTIF(F38:F42,"لا")+COUNTIF(L38:L42,"لا")+COUNTBLANK(F38:F42)+COUNTBLANK(L38:L42))&" مستند") | H43: الرقم الضريبي لصاحب العمل: | K43: =IF('بيانات العقد'!C39="","",'بيانات العقد'!C39)
B45: رابعاً: الاعتمادات
B46: إعداد: مهندس المقاول | F46: مراجعة: المهندس الاستشاري | J46: اعتماد: صاحب العمل
B47: الاسم: .................... التوقيع: .................. التاريخ: .................. | F47: الاسم: .................... التوقيع: .................. التاريخ: .................. | J47: الاسم: .................... التوقيع: .................. التاريخ: ..................
B49: خامساً: حصر الأعمال المنفذة حسب بنود جدول الكميات — أدخل «الكمية الحالية» فقط
B50: كود البند | C50: الوصف | D50: الوحدة | E50: الكمية التعاقدية | F50: سعر الوحدة | G50: الكمية السابقة | H50: الكمية الحالية | I50: الكمية التراكمية | J50: نسبة الإنجاز | K50: القيمة السابقة | L50: القيمة الحالية | M50: القيمة التراكمية
B51: =IF('جدول الكميات'!B6="","",'جدول الكميات'!B6) | C51: =IF('جدول الكميات'!D6="","",'جدول الكميات'!D6) | D51: =IF('جدول الكميات'!E6="","",'جدول الكميات'!E6) | E51: =N('جدول الكميات'!F6) | F51: =N('جدول الكميات'!G6) | G51: ='مستخلص 03'!I51 | I51: =G51+H51 | J51: =IF(E51>0,I51/E51,0) | K51: =G51*F51 | L51: =N(H51)*F51 | M51: =I51*F51
B52: =IF('جدول الكميات'!B7="","",'جدول الكميات'!B7) | C52: =IF('جدول الكميات'!D7="","",'جدول الكميات'!D7) | D52: =IF('جدول الكميات'!E7="","",'جدول الكميات'!E7) | E52: =N('جدول الكميات'!F7) | F52: =N('جدول الكميات'!G7) | G52: ='مستخلص 03'!I52 | H52: 0.01 | I52: =G52+H52 | J52: =IF(E52>0,I52/E52,0) | K52: =G52*F52 | L52: =N(H52)*F52 | M52: =I52*F52
B53: =IF('جدول الكميات'!B8="","",'جدول الكميات'!B8) | C53: =IF('جدول الكميات'!D8="","",'جدول الكميات'!D8) | D53: =IF('جدول الكميات'!E8="","",'جدول الكميات'!E8) | E53: =N('جدول الكميات'!F8) | F53: =N('جدول الكميات'!G8) | G53: ='مستخلص 03'!I53 | I53: =G53+H53 | J53: =IF(E53>0,I53/E53,0) | K53: =G53*F53 | L53: =N(H53)*F53 | M53: =I53*F53
B54: =IF('جدول الكميات'!B9="","",'جدول الكميات'!B9) | C54: =IF('جدول الكميات'!D9="","",'جدول الكميات'!D9) | D54: =IF('جدول الكميات'!E9="","",'جدول الكميات'!E9) | E54: =N('جدول الكميات'!F9) | F54: =N('جدول الكميات'!G9) | G54: ='مستخلص 03'!I54 | H54: 50.67 | I54: =G54+H54 | J54: =IF(E54>0,I54/E54,0) | K54: =G54*F54 | L54: =N(H54)*F54 | M54: =I54*F54
B55: =IF('جدول الكميات'!B10="","",'جدول الكميات'!B10) | C55: =IF('جدول الكميات'!D10="","",'جدول الكميات'!D10) | D55: =IF('جدول الكميات'!E10="","",'جدول الكميات'!E10) | E55: =N('جدول الكميات'!F10) | F55: =N('جدول الكميات'!G10) | G55: ='مستخلص 03'!I55 | H55: 126.67 | I55: =G55+H55 | J55: =IF(E55>0,I55/E55,0) | K55: =G55*F55 | L55: =N(H55)*F55 | M55: =I55*F55
B56: =IF('جدول الكميات'!B11="","",'جدول الكميات'!B11) | C56: =IF('جدول الكميات'!D11="","",'جدول الكميات'!D11) | D56: =IF('جدول الكميات'!E11="","",'جدول الكميات'!E11) | E56: =N('جدول الكميات'!F11) | F56: =N('جدول الكميات'!G11) | G56: ='مستخلص 03'!I56 | H56: 56 | I56: =G56+H56 | J56: =IF(E56>0,I56/E56,0) | K56: =G56*F56 | L56: =N(H56)*F56 | M56: =I56*F56
B57: =IF('جدول الكميات'!B12="","",'جدول الكميات'!B12) | C57: =IF('جدول الكميات'!D12="","",'جدول الكميات'!D12) | D57: =IF('جدول الكميات'!E12="","",'جدول الكميات'!E12) | E57: =N('جدول الكميات'!F12) | F57: =N('جدول الكميات'!G12) | G57: ='مستخلص 03'!I57 | H57: 220 | I57: =G57+H57 | J57: =IF(E57>0,I57/E57,0) | K57: =G57*F57 | L57: =N(H57)*F57 | M57: =I57*F57
B58: =IF('جدول الكميات'!B13="","",'جدول الكميات'!B13) | C58: =IF('جدول الكميات'!D13="","",'جدول الكميات'!D13) | D58: =IF('جدول الكميات'!E13="","",'جدول الكميات'!E13) | E58: =N('جدول الكميات'!F13) | F58: =N('جدول الكميات'!G13) | G58: ='مستخلص 03'!I58 | H58: 64 | I58: =G58+H58 | J58: =IF(E58>0,I58/E58,0) | K58: =G58*F58 | L58: =N(H58)*F58 | M58: =I58*F58
B59: =IF('جدول الكميات'!B14="","",'جدول الكميات'!B14) | C59: =IF('جدول الكميات'!D14="","",'جدول الكميات'!D14) | D59: =IF('جدول الكميات'!E14="","",'جدول الكميات'!E14) | E59: =N('جدول الكميات'!F14) | F59: =N('جدول الكميات'!G14) | G59: ='مستخلص 03'!I59 | I59: =G59+H59 | J59: =IF(E59>0,I59/E59,0) | K59: =G59*F59 | L59: =N(H59)*F59 | M59: =I59*F59
B60: =IF('جدول الكميات'!B15="","",'جدول الكميات'!B15) | C60: =IF('جدول الكميات'!D15="","",'جدول الكميات'!D15) | D60: =IF('جدول الكميات'!E15="","",'جدول الكميات'!E15) | E60: =N('جدول الكميات'!F15) | F60: =N('جدول الكميات'!G15) | G60: ='مستخلص 03'!I60 | I60: =G60+H60 | J60: =IF(E60>0,I60/E60,0) | K60: =G60*F60 | L60: =N(H60)*F60 | M60: =I60*F60
B61: =IF('جدول الكميات'!B16="","",'جدول الكميات'!B16) | C61: =IF('جدول الكميات'!D16="","",'جدول الكميات'!D16) | D61: =IF('جدول الكميات'!E16="","",'جدول الكميات'!E16) | E61: =N('جدول الكميات'!F16) | F61: =N('جدول الكميات'!G16) | G61: ='مستخلص 03'!I61 | H61: 240 | I61: =G61+H61 | J61: =IF(E61>0,I61/E61,0) | K61: =G61*F61 | L61: =N(H61)*F61 | M61: =I61*F61
B62: =IF('جدول الكميات'!B17="","",'جدول الكميات'!B17) | C62: =IF('جدول الكميات'!D17="","",'جدول الكميات'!D17) | D62: =IF('جدول الكميات'!E17="","",'جدول الكميات'!E17) | E62: =N('جدول الكميات'!F17) | F62: =N('جدول الكميات'!G17) | G62: ='مستخلص 03'!I62 | H62: 190 | I62: =G62+H62 | J62: =IF(E62>0,I62/E62,0) | K62: =G62*F62 | L62: =N(H62)*F62 | M62: =I62*F62
B63: =IF('جدول الكميات'!B18="","",'جدول الكميات'!B18) | C63: =IF('جدول الكميات'!D18="","",'جدول الكميات'!D18) | D63: =IF('جدول الكميات'!E18="","",'جدول الكميات'!E18) | E63: =N('جدول الكميات'!F18) | F63: =N('جدول الكميات'!G18) | G63: ='مستخلص 03'!I63 | I63: =G63+H63 | J63: =IF(E63>0,I63/E63,0) | K63: =G63*F63 | L63: =N(H63)*F63 | M63: =I63*F63
B64: =IF('جدول الكميات'!B19="","",'جدول الكميات'!B19) | C64: =IF('جدول الكميات'!D19="","",'جدول الكميات'!D19) | D64: =IF('جدول الكميات'!E19="","",'جدول الكميات'!E19) | E64: =N('جدول الكميات'!F19) | F64: =N('جدول الكميات'!G19) | G64: ='مستخلص 03'!I64 | I64: =G64+H64 | J64: =IF(E64>0,I64/E64,0) | K64: =G64*F64 | L64: =N(H64)*F64 | M64: =I64*F64
B65: =IF('جدول الكميات'!B20="","",'جدول الكميات'!B20) | C65: =IF('جدول الكميات'!D20="","",'جدول الكميات'!D20) | D65: =IF('جدول الكميات'!E20="","",'جدول الكميات'!E20) | E65: =N('جدول الكميات'!F20) | F65: =N('جدول الكميات'!G20) | G65: ='مستخلص 03'!I65 | I65: =G65+H65 | J65: =IF(E65>0,I65/E65,0) | K65: =G65*F65 | L65: =N(H65)*F65 | M65: =I65*F65
B66: =IF('جدول الكميات'!B21="","",'جدول الكميات'!B21) | C66: =IF('جدول الكميات'!D21="","",'جدول الكميات'!D21) | D66: =IF('جدول الكميات'!E21="","",'جدول الكميات'!E21) | E66: =N('جدول الكميات'!F21) | F66: =N('جدول الكميات'!G21) | G66: ='مستخلص 03'!I66 | I66: =G66+H66 | J66: =IF(E66>0,I66/E66,0) | K66: =G66*F66 | L66: =N(H66)*F66 | M66: =I66*F66
B67: =IF('جدول الكميات'!B22="","",'جدول الكميات'!B22) | C67: =IF('جدول الكميات'!D22="","",'جدول الكميات'!D22) | D67: =IF('جدول الكميات'!E22="","",'جدول الكميات'!E22) | E67: =N('جدول الكميات'!F22) | F67: =N('جدول الكميات'!G22) | G67: ='مستخلص 03'!I67 | I67: =G67+H67 | J67: =IF(E67>0,I67/E67,0) | K67: =G67*F67 | L67: =N(H67)*F67 | M67: =I67*F67
B68: =IF('جدول الكميات'!B23="","",'جدول الكميات'!B23) | C68: =IF('جدول الكميات'!D23="","",'جدول الكميات'!D23) | D68: =IF('جدول الكميات'!E23="","",'جدول الكميات'!E23) | E68: =N('جدول الكميات'!F23) | F68: =N('جدول الكميات'!G23) | G68: ='مستخلص 03'!I68 | I68: =G68+H68 | J68: =IF(E68>0,I68/E68,0) | K68: =G68*F68 | L68: =N(H68)*F68 | M68: =I68*F68
B69: =IF('جدول الكميات'!B24="","",'جدول الكميات'!B24) | C69: =IF('جدول الكميات'!D24="","",'جدول الكميات'!D24) | D69: =IF('جدول الكميات'!E24="","",'جدول الكميات'!E24) | E69: =N('جدول الكميات'!F24) | F69: =N('جدول الكميات'!G24) | G69: ='مستخلص 03'!I69 | I69: =G69+H69 | J69: =IF(E69>0,I69/E69,0) | K69: =G69*F69 | L69: =N(H69)*F69 | M69: =I69*F69
B70: =IF('جدول الكميات'!B25="","",'جدول الكميات'!B25) | C70: =IF('جدول الكميات'!D25="","",'جدول الكميات'!D25) | D70: =IF('جدول الكميات'!E25="","",'جدول الكميات'!E25) | E70: =N('جدول الكميات'!F25) | F70: =N('جدول الكميات'!G25) | G70: ='مستخلص 03'!I70 | I70: =G70+H70 | J70: =IF(E70>0,I70/E70,0) | K70: =G70*F70 | L70: =N(H70)*F70 | M70: =I70*F70
B71: =IF('جدول الكميات'!B26="","",'جدول الكميات'!B26) | C71: =IF('جدول الكميات'!D26="","",'جدول الكميات'!D26) | D71: =IF('جدول الكميات'!E26="","",'جدول الكميات'!E26) | E71: =N('جدول الكميات'!F26) | F71: =N('جدول الكميات'!G26) | G71: ='مستخلص 03'!I71 | I71: =G71+H71 | J71: =IF(E71>0,I71/E71,0) | K71: =G71*F71 | L71: =N(H71)*F71 | M71: =I71*F71
B72: =IF('جدول الكميات'!B27="","",'جدول الكميات'!B27) | C72: =IF('جدول الكميات'!D27="","",'جدول الكميات'!D27) | D72: =IF('جدول الكميات'!E27="","",'جدول الكميات'!E27) | E72: =N('جدول الكميات'!F27) | F72: =N('جدول الكميات'!G27) | G72: ='مستخلص 03'!I72 | I72: =G72+H72 | J72: =IF(E72>0,I72/E72,0) | K72: =G72*F72 | L72: =N(H72)*F72 | M72: =I72*F72
B73: =IF('جدول الكميات'!B28="","",'جدول الكميات'!B28) | C73: =IF('جدول الكميات'!D28="","",'جدول الكميات'!D28) | D73: =IF('جدول الكميات'!E28="","",'جدول الكميات'!E28) | E73: =N('جدول الكميات'!F28) | F73: =N('جدول الكميات'!G28) | G73: ='مستخلص 03'!I73 | I73: =G73+H73 | J73: =IF(E73>0,I73/E73,0) | K73: =G73*F73 | L73: =N(H73)*F73 | M73: =I73*F73
B74: =IF('جدول الكميات'!B29="","",'جدول الكميات'!B29) | C74: =IF('جدول الكميات'!D29="","",'جدول الكميات'!D29) | D74: =IF('جدول الكميات'!E29="","",'جدول الكميات'!E29) | E74: =N('جدول الكميات'!F29) | F74: =N('جدول الكميات'!G29) | G74: ='مستخلص 03'!I74 | I74: =G74+H74 | J74: =IF(E74>0,I74/E74,0) | K74: =G74*F74 | L74: =N(H74)*F74 | M74: =I74*F74
... B150: =IF('جدول الكميات'!B105="","",'جدول الكميات'!B105) | C150: =IF('جدول الكميات'!D105="","",'جدول الكميات'!D105) | D150: =IF('جدول الكميات'!E105="","",'جدول الكميات'!E105) | E150: =N('جدول الكميات'!F105) | F150: =N('جدول الكميات'!G105) | G150: ='مستخلص 03'!I150 | I150: =G150+H150 | J150: =IF(E150>0,I150/E150,0) | K150: =G150*F150 | L150: =N(H150)*F150 | M150: =I150*F150
B151: الإجمالي | K151: =SUM(K51:K150) | L151: =SUM(L51:L150) | M151: =SUM(M51:M150)

Sheet مستخلص 05
B1: 🧾 مستخلص أعمال رقم (5) — شهادة دفع مؤقتة (Interim Payment Certificate)
B2: =IF('بيانات العقد'!$C$5="","مشروع رقم 01 — أدخل بيانات العقد",'بيانات العقد'!$C$5&" | عقد رقم: "&'بيانات العقد'!$C$6)&" | المبالغ بـ "&'بيانات العقد'!$C$14
B3: 🗂 سجل المستخلصات | C3: ⚙ بيانات العقد | E3: 📋 جدول الكميات | G3: 🔁 التغييرية | I3: ✂ الاستقطاعات | K3: ◄ المستخلص السابق | L3: المستخلص التالي ►
B5: رقم المستخلص | C5: 5 | H5: حالة المستخلص | J5: معتمد | L5: نسبة الإنجاز الفعلية
B6: المشروع | C6: ='بيانات العقد'!C5 | H6: الفترة من | J6: 46204 | L6: =IF(ContractValue+L20>0,(L19+L20)/(ContractValue+L20),0)
B7: رقم العقد | C7: ='بيانات العقد'!C6 | H7: الفترة إلى | J7: 46234 | L7: نسبة الإنجاز المخططة (من البرنامج)
B8: صاحب العمل | C8: ='بيانات العقد'!C7 | H8: تاريخ التقديم | J8: 46239 | L8: 0.2077
B9: الاستشاري | C9: ='بيانات العقد'!C8 | H9: تاريخ الاعتماد | J9: 46256 | L9: الانحراف عن المخطط
B10: المقاول | C10: ='بيانات العقد'!C9 | H10: قيمة العقد المعدلة | J10: =RevisedContract | L10: =IF(L8="","",L6-L8)
B11: الرقم الضريبي للمقاول | C11: =IF('بيانات العقد'!C37="","",'بيانات العقد'!C37) | H11: الفترة بالتاريخ الهجري | J11: =IF(J6="","",J6) | K11: =IF(J7="","",J7)
B12: أولاً: بيانات الفترة (إدخال)
B13: رصيد المواد الموردة بالموقع (نهاية الفترة) | E13: 220000 | H13: إفراج عن ضمان الأعمال خلال الفترة
B14: غرامات تأخير / خصومات أخرى خلال الفترة | E14: 5000 | H14: سبب الغرامة / الخصم | K14: مخالفة اشتراطات السلامة بالموقع
B15: المبلغ المحصل من هذا المستخلص | E15: 380000 | H15: تاريخ التحصيل | K15: 46284
B16: رقم الفاتورة الضريبية (من نظام الفوترة الإلكترونية) | E16: INV-2026-01005 | H16: تاريخ الفاتورة الضريبية | K16: 46256
B17: ثانياً: الملخص المالي للمستخلص
B18: م | C18: البيان | H18: السابق | J18: الحالي | L18: الإجمالي التراكمي
B19: 1 | C19: قيمة الأعمال المنفذة طبقاً لحصر البنود | H19: ='مستخلص 04'!L19 | J19: =L19-H19 | L19: =M151
B20: 2 | C20: قيمة الأوامر التغييرية المعتمدة | H20: ='مستخلص 04'!L20 | J20: =L20-H20 | L20: =SUMIFS('الأوامر التغييرية'!$J$6:$J$55,'الأوامر التغييرية'!$H$6:$H$55,"معتمد",'الأوامر التغييرية'!$K$6:$K$55,"<="&$C$5)
B21: 3 | C21: المواد الموردة بالموقع (رصيد) | H21: ='مستخلص 04'!L21 | J21: =L21-H21 | L21: =N(E13)
B22: 4 | C22: إجمالي قيمة الأعمال | H22: ='مستخلص 04'!L22 | J22: =L22-H22 | L22: =SUM(L19:L21)
B23: 5 | C23: يُخصم: استرداد الدفعة المقدمة | H23: ='مستخلص 04'!L23 | J23: =L23-H23 | L23: =-ROUND(IF(L6>=RecFull,AdvAmount,MIN(AdvAmount,MAX(0,L19+L20-RecStart*ContractValue)*RecRate)),2)
B24: 6 | C24: يُخصم: ضمان الأعمال المحتسب | H24: ='مستخلص 04'!L24 | J24: =L24-H24 | L24: =-ROUND(MIN(L22*RetPct,RetCap),2)
B25: 7 | C25: يُضاف: المفرج عنه من ضمان الأعمال | H25: ='مستخلص 04'!L25 | J25: =L25-H25 | L25: =H25+N(K13)
B26: 8 | C26: يُخصم: الاستقطاعات الفنية المحتجزة | H26: ='مستخلص 04'!L26 | J26: =L26-H26 | L26: =-(SUMIFS('الاستقطاعات الفنية'!$I$6:$I$105,'الاستقطاعات الفنية'!$D$6:$D$105,"<="&$C$5)-SUMIFS('الاستقطاعات الفنية'!$I$6:$I$105,'الاستقطاعات الفنية'!$J$6:$J$105,"نعم",'الاستقطاعات الفنية'!$K$6:$K$105,"<="&$C$5))
B27: 9 | C27: يُخصم: الغرامات والخصومات الأخرى | H27: ='مستخلص 04'!L27 | J27: =L27-H27 | L27: =H27-N(E14)
B28: 10 | C28: صافي القيمة قبل الضرائب | H28: ='مستخلص 04'!L28 | J28: =L28-H28 | L28: =SUM(L22:L27)
B29: 11 | C29: يُضاف: ضريبة القيمة المضافة | H29: ='مستخلص 04'!L29 | J29: =L29-H29 | L29: =ROUND(VATPct*(L28+IF(VATBeforeRet="نعم",-(L24+L25),0)+IF(PenInVAT="لا",-L27,0)),2)
B30: 12 | C30: يُخصم: ضريبة الاستقطاع (غير المقيم) | H30: ='مستخلص 04'!L30 | J30: =L30-H30 | L30: =-ROUND(WHTPct*(L28-(L24+L25)),2)
B31: 13 | C31: صافي المستحق | H31: ='مستخلص 04'!L31 | J31: =L31-H31 | L31: =L28+L29+L30
B32: صافي المبلغ المستحق صرفه عن هذا المستخلص | J32: =J31
B33: المحصل من هذا المستخلص | J33: =N(E15)
B34: المتبقي غير المحصل | J34: =J32-J33
B35: فقط وقدره:
B37: ثالثاً: المستندات والمتطلبات النظامية للصرف (المملكة العربية السعودية)
B38: الفاتورة الضريبية الإلكترونية (متوافقة مع فاتورة - ZATCA) | F38: نعم | H38: شهادة الزكاة والضريبة سارية | L38: نعم
B39: شهادة التأمينات الاجتماعية (GOSI) سارية | F39: نعم | H39: شهادة نطاقات (التوطين) سارية | L39: نعم
B40: السجل التجاري وعضوية الغرفة التجارية سارية | F40: نعم | H40: محضر حصر الكميات معتمد من الاستشاري | L40: نعم
B41: ضمان الدفعة المقدمة ساري | F41: نعم | H41: الضمان النهائي ساري | L41: نعم
B42: وثيقة التأمين على الأعمال (CAR) سارية | F42: نعم | H42: تقرير الاستشاري الشهري | L42: نعم
B43: حالة المستندات: | E43: =IF(COUNTIF(F38:F42,"لا")+COUNTIF(L38:L42,"لا")+COUNTBLANK(F38:F42)+COUNTBLANK(L38:L42)=0,"✔ مكتملة — جاهز للصرف","⚠ ناقص "&(COUNTIF(F38:F42,"لا")+COUNTIF(L38:L42,"لا")+COUNTBLANK(F38:F42)+COUNTBLANK(L38:L42))&" مستند") | H43: الرقم الضريبي لصاحب العمل: | K43: =IF('بيانات العقد'!C39="","",'بيانات العقد'!C39)
B45: رابعاً: الاعتمادات
B46: إعداد: مهندس المقاول | F46: مراجعة: المهندس الاستشاري | J46: اعتماد: صاحب العمل
B47: الاسم: .................... التوقيع: .................. التاريخ: .................. | F47: الاسم: .................... التوقيع: .................. التاريخ: .................. | J47: الاسم: .................... التوقيع: .................. التاريخ: ..................
B49: خامساً: حصر الأعمال المنفذة حسب بنود جدول الكميات — أدخل «الكمية الحالية» فقط
B50: كود البند | C50: الوصف | D50: الوحدة | E50: الكمية التعاقدية | F50: سعر الوحدة | G50: الكمية السابقة | H50: الكمية الحالية | I50: الكمية التراكمية | J50: نسبة الإنجاز | K50: القيمة السابقة | L50: القيمة الحالية | M50: القيمة التراكمية
B51: =IF('جدول الكميات'!B6="","",'جدول الكميات'!B6) | C51: =IF('جدول الكميات'!D6="","",'جدول الكميات'!D6) | D51: =IF('جدول الكميات'!E6="","",'جدول الكميات'!E6) | E51: =N('جدول الكميات'!F6) | F51: =N('جدول الكميات'!G6) | G51: ='مستخلص 04'!I51 | I51: =G51+H51 | J51: =IF(E51>0,I51/E51,0) | K51: =G51*F51 | L51: =N(H51)*F51 | M51: =I51*F51
B52: =IF('جدول الكميات'!B7="","",'جدول الكميات'!B7) | C52: =IF('جدول الكميات'!D7="","",'جدول الكميات'!D7) | D52: =IF('جدول الكميات'!E7="","",'جدول الكميات'!E7) | E52: =N('جدول الكميات'!F7) | F52: =N('جدول الكميات'!G7) | G52: ='مستخلص 04'!I52 | I52: =G52+H52 | J52: =IF(E52>0,I52/E52,0) | K52: =G52*F52 | L52: =N(H52)*F52 | M52: =I52*F52
B53: =IF('جدول الكميات'!B8="","",'جدول الكميات'!B8) | C53: =IF('جدول الكميات'!D8="","",'جدول الكميات'!D8) | D53: =IF('جدول الكميات'!E8="","",'جدول الكميات'!E8) | E53: =N('جدول الكميات'!F8) | F53: =N('جدول الكميات'!G8) | G53: ='مستخلص 04'!I53 | I53: =G53+H53 | J53: =IF(E53>0,I53/E53,0) | K53: =G53*F53 | L53: =N(H53)*F53 | M53: =I53*F53
B54: =IF('جدول الكميات'!B9="","",'جدول الكميات'!B9) | C54: =IF('جدول الكميات'!D9="","",'جدول الكميات'!D9) | D54: =IF('جدول الكميات'!E9="","",'جدول الكميات'!E9) | E54: =N('جدول الكميات'!F9) | F54: =N('جدول الكميات'!G9) | G54: ='مستخلص 04'!I54 | H54: 50.67 | I54: =G54+H54 | J54: =IF(E54>0,I54/E54,0) | K54: =G54*F54 | L54: =N(H54)*F54 | M54: =I54*F54
B55: =IF('جدول الكميات'!B10="","",'جدول الكميات'!B10) | C55: =IF('جدول الكميات'!D10="","",'جدول الكميات'!D10) | D55: =IF('جدول الكميات'!E10="","",'جدول الكميات'!E10) | E55: =N('جدول الكميات'!F10) | F55: =N('جدول الكميات'!G10) | G55: ='مستخلص 04'!I55 | H55: 126.67 | I55: =G55+H55 | J55: =IF(E55>0,I55/E55,0) | K55: =G55*F55 | L55: =N(H55)*F55 | M55: =I55*F55
B56: =IF('جدول الكميات'!B11="","",'جدول الكميات'!B11) | C56: =IF('جدول الكميات'!D11="","",'جدول الكميات'!D11) | D56: =IF('جدول الكميات'!E11="","",'جدول الكميات'!E11) | E56: =N('جدول الكميات'!F11) | F56: =N('جدول الكميات'!G11) | G56: ='مستخلص 04'!I56 | H56: 56 | I56: =G56+H56 | J56: =IF(E56>0,I56/E56,0) | K56: =G56*F56 | L56: =N(H56)*F56 | M56: =I56*F56
B57: =IF('جدول الكميات'!B12="","",'جدول الكميات'!B12) | C57: =IF('جدول الكميات'!D12="","",'جدول الكميات'!D12) | D57: =IF('جدول الكميات'!E12="","",'جدول الكميات'!E12) | E57: =N('جدول الكميات'!F12) | F57: =N('جدول الكميات'!G12) | G57: ='مستخلص 04'!I57 | H57: 220 | I57: =G57+H57 | J57: =IF(E57>0,I57/E57,0) | K57: =G57*F57 | L57: =N(H57)*F57 | M57: =I57*F57
B58: =IF('جدول الكميات'!B13="","",'جدول الكميات'!B13) | C58: =IF('جدول الكميات'!D13="","",'جدول الكميات'!D13) | D58: =IF('جدول الكميات'!E13="","",'جدول الكميات'!E13) | E58: =N('جدول الكميات'!F13) | F58: =N('جدول الكميات'!G13) | G58: ='مستخلص 04'!I58 | H58: 64 | I58: =G58+H58 | J58: =IF(E58>0,I58/E58,0) | K58: =G58*F58 | L58: =N(H58)*F58 | M58: =I58*F58
B59: =IF('جدول الكميات'!B14="","",'جدول الكميات'!B14) | C59: =IF('جدول الكميات'!D14="","",'جدول الكميات'!D14) | D59: =IF('جدول الكميات'!E14="","",'جدول الكميات'!E14) | E59: =N('جدول الكميات'!F14) | F59: =N('جدول الكميات'!G14) | G59: ='مستخلص 04'!I59 | I59: =G59+H59 | J59: =IF(E59>0,I59/E59,0) | K59: =G59*F59 | L59: =N(H59)*F59 | M59: =I59*F59
B60: =IF('جدول الكميات'!B15="","",'جدول الكميات'!B15) | C60: =IF('جدول الكميات'!D15="","",'جدول الكميات'!D15) | D60: =IF('جدول الكميات'!E15="","",'جدول الكميات'!E15) | E60: =N('جدول الكميات'!F15) | F60: =N('جدول الكميات'!G15) | G60: ='مستخلص 04'!I60 | I60: =G60+H60 | J60: =IF(E60>0,I60/E60,0) | K60: =G60*F60 | L60: =N(H60)*F60 | M60: =I60*F60
B61: =IF('جدول الكميات'!B16="","",'جدول الكميات'!B16) | C61: =IF('جدول الكميات'!D16="","",'جدول الكميات'!D16) | D61: =IF('جدول الكميات'!E16="","",'جدول الكميات'!E16) | E61: =N('جدول الكميات'!F16) | F61: =N('جدول الكميات'!G16) | G61: ='مستخلص 04'!I61 | H61: 240 | I61: =G61+H61 | J61: =IF(E61>0,I61/E61,0) | K61: =G61*F61 | L61: =N(H61)*F61 | M61: =I61*F61
B62: =IF('جدول الكميات'!B17="","",'جدول الكميات'!B17) | C62: =IF('جدول الكميات'!D17="","",'جدول الكميات'!D17) | D62: =IF('جدول الكميات'!E17="","",'جدول الكميات'!E17) | E62: =N('جدول الكميات'!F17) | F62: =N('جدول الكميات'!G17) | G62: ='مستخلص 04'!I62 | H62: 190 | I62: =G62+H62 | J62: =IF(E62>0,I62/E62,0) | K62: =G62*F62 | L62: =N(H62)*F62 | M62: =I62*F62
B63: =IF('جدول الكميات'!B18="","",'جدول الكميات'!B18) | C63: =IF('جدول الكميات'!D18="","",'جدول الكميات'!D18) | D63: =IF('جدول الكميات'!E18="","",'جدول الكميات'!E18) | E63: =N('جدول الكميات'!F18) | F63: =N('جدول الكميات'!G18) | G63: ='مستخلص 04'!I63 | I63: =G63+H63 | J63: =IF(E63>0,I63/E63,0) | K63: =G63*F63 | L63: =N(H63)*F63 | M63: =I63*F63
B64: =IF('جدول الكميات'!B19="","",'جدول الكميات'!B19) | C64: =IF('جدول الكميات'!D19="","",'جدول الكميات'!D19) | D64: =IF('جدول الكميات'!E19="","",'جدول الكميات'!E19) | E64: =N('جدول الكميات'!F19) | F64: =N('جدول الكميات'!G19) | G64: ='مستخلص 04'!I64 | I64: =G64+H64 | J64: =IF(E64>0,I64/E64,0) | K64: =G64*F64 | L64: =N(H64)*F64 | M64: =I64*F64
B65: =IF('جدول الكميات'!B20="","",'جدول الكميات'!B20) | C65: =IF('جدول الكميات'!D20="","",'جدول الكميات'!D20) | D65: =IF('جدول الكميات'!E20="","",'جدول الكميات'!E20) | E65: =N('جدول الكميات'!F20) | F65: =N('جدول الكميات'!G20) | G65: ='مستخلص 04'!I65 | I65: =G65+H65 | J65: =IF(E65>0,I65/E65,0) | K65: =G65*F65 | L65: =N(H65)*F65 | M65: =I65*F65
B66: =IF('جدول الكميات'!B21="","",'جدول الكميات'!B21) | C66: =IF('جدول الكميات'!D21="","",'جدول الكميات'!D21) | D66: =IF('جدول الكميات'!E21="","",'جدول الكميات'!E21) | E66: =N('جدول الكميات'!F21) | F66: =N('جدول الكميات'!G21) | G66: ='مستخلص 04'!I66 | I66: =G66+H66 | J66: =IF(E66>0,I66/E66,0) | K66: =G66*F66 | L66: =N(H66)*F66 | M66: =I66*F66
B67: =IF('جدول الكميات'!B22="","",'جدول الكميات'!B22) | C67: =IF('جدول الكميات'!D22="","",'جدول الكميات'!D22) | D67: =IF('جدول الكميات'!E22="","",'جدول الكميات'!E22) | E67: =N('جدول الكميات'!F22) | F67: =N('جدول الكميات'!G22) | G67: ='مستخلص 04'!I67 | I67: =G67+H67 | J67: =IF(E67>0,I67/E67,0) | K67: =G67*F67 | L67: =N(H67)*F67 | M67: =I67*F67
B68: =IF('جدول الكميات'!B23="","",'جدول الكميات'!B23) | C68: =IF('جدول الكميات'!D23="","",'جدول الكميات'!D23) | D68: =IF('جدول الكميات'!E23="","",'جدول الكميات'!E23) | E68: =N('جدول الكميات'!F23) | F68: =N('جدول الكميات'!G23) | G68: ='مستخلص 04'!I68 | I68: =G68+H68 | J68: =IF(E68>0,I68/E68,0) | K68: =G68*F68 | L68: =N(H68)*F68 | M68: =I68*F68
B69: =IF('جدول الكميات'!B24="","",'جدول الكميات'!B24) | C69: =IF('جدول الكميات'!D24="","",'جدول الكميات'!D24) | D69: =IF('جدول الكميات'!E24="","",'جدول الكميات'!E24) | E69: =N('جدول الكميات'!F24) | F69: =N('جدول الكميات'!G24) | G69: ='مستخلص 04'!I69 | I69: =G69+H69 | J69: =IF(E69>0,I69/E69,0) | K69: =G69*F69 | L69: =N(H69)*F69 | M69: =I69*F69
B70: =IF('جدول الكميات'!B25="","",'جدول الكميات'!B25) | C70: =IF('جدول الكميات'!D25="","",'جدول الكميات'!D25) | D70: =IF('جدول الكميات'!E25="","",'جدول الكميات'!E25) | E70: =N('جدول الكميات'!F25) | F70: =N('جدول الكميات'!G25) | G70: ='مستخلص 04'!I70 | I70: =G70+H70 | J70: =IF(E70>0,I70/E70,0) | K70: =G70*F70 | L70: =N(H70)*F70 | M70: =I70*F70
B71: =IF('جدول الكميات'!B26="","",'جدول الكميات'!B26) | C71: =IF('جدول الكميات'!D26="","",'جدول الكميات'!D26) | D71: =IF('جدول الكميات'!E26="","",'جدول الكميات'!E26) | E71: =N('جدول الكميات'!F26) | F71: =N('جدول الكميات'!G26) | G71: ='مستخلص 04'!I71 | I71: =G71+H71 | J71: =IF(E71>0,I71/E71,0) | K71: =G71*F71 | L71: =N(H71)*F71 | M71: =I71*F71
B72: =IF('جدول الكميات'!B27="","",'جدول الكميات'!B27) | C72: =IF('جدول الكميات'!D27="","",'جدول الكميات'!D27) | D72: =IF('جدول الكميات'!E27="","",'جدول الكميات'!E27) | E72: =N('جدول الكميات'!F27) | F72: =N('جدول الكميات'!G27) | G72: ='مستخلص 04'!I72 | I72: =G72+H72 | J72: =IF(E72>0,I72/E72,0) | K72: =G72*F72 | L72: =N(H72)*F72 | M72: =I72*F72
B73: =IF('جدول الكميات'!B28="","",'جدول الكميات'!B28) | C73: =IF('جدول الكميات'!D28="","",'جدول الكميات'!D28) | D73: =IF('جدول الكميات'!E28="","",'جدول الكميات'!E28) | E73: =N('جدول الكميات'!F28) | F73: =N('جدول الكميات'!G28) | G73: ='مستخلص 04'!I73 | I73: =G73+H73 | J73: =IF(E73>0,I73/E73,0) | K73: =G73*F73 | L73: =N(H73)*F73 | M73: =I73*F73
B74: =IF('جدول الكميات'!B29="","",'جدول الكميات'!B29) | C74: =IF('جدول الكميات'!D29="","",'جدول الكميات'!D29) | D74: =IF('جدول الكميات'!E29="","",'جدول الكميات'!E29) | E74: =N('جدول الكميات'!F29) | F74: =N('جدول الكميات'!G29) | G74: ='مستخلص 04'!I74 | I74: =G74+H74 | J74: =IF(E74>0,I74/E74,0) | K74: =G74*F74 | L74: =N(H74)*F74 | M74: =I74*F74
... B150: =IF('جدول الكميات'!B105="","",'جدول الكميات'!B105) | C150: =IF('جدول الكميات'!D105="","",'جدول الكميات'!D105) | D150: =IF('جدول الكميات'!E105="","",'جدول الكميات'!E105) | E150: =N('جدول الكميات'!F105) | F150: =N('جدول الكميات'!G105) | G150: ='مستخلص 04'!I150 | I150: =G150+H150 | J150: =IF(E150>0,I150/E150,0) | K150: =G150*F150 | L150: =N(H150)*F150 | M150: =I150*F150
B151: الإجمالي | K151: =SUM(K51:K150) | L151: =SUM(L51:L150) | M151: =SUM(M51:M150)

Sheet مستخلص 06
B1: 🧾 مستخلص أعمال رقم (6) — شهادة دفع مؤقتة (Interim Payment Certificate)
B2: =IF('بيانات العقد'!$C$5="","مشروع رقم 01 — أدخل بيانات العقد",'بيانات العقد'!$C$5&" | عقد رقم: "&'بيانات العقد'!$C$6)&" | المبالغ بـ "&'بيانات العقد'!$C$14
B3: 🗂 سجل المستخلصات | C3: ⚙ بيانات العقد | E3: 📋 جدول الكميات | G3: 🔁 التغييرية | I3: ✂ الاستقطاعات | K3: ◄ المستخلص السابق | L3: المستخلص التالي ►
B5: رقم المستخلص | C5: 6 | H5: حالة المستخلص | J5: معتمد | L5: نسبة الإنجاز الفعلية
B6: المشروع | C6: ='بيانات العقد'!C5 | H6: الفترة من | J6: 46235 | L6: =IF(ContractValue+L20>0,(L19+L20)/(ContractValue+L20),0)
B7: رقم العقد | C7: ='بيانات العقد'!C6 | H7: الفترة إلى | J7: 46265 | L7: نسبة الإنجاز المخططة (من البرنامج)
B8: صاحب العمل | C8: ='بيانات العقد'!C7 | H8: تاريخ التقديم | J8: 46270 | L8: 0.2597
B9: الاستشاري | C9: ='بيانات العقد'!C8 | H9: تاريخ الاعتماد | J9: 46285 | L9: الانحراف عن المخطط
B10: المقاول | C10: ='بيانات العقد'!C9 | H10: قيمة العقد المعدلة | J10: =RevisedContract | L10: =IF(L8="","",L6-L8)
B11: الرقم الضريبي للمقاول | C11: =IF('بيانات العقد'!C37="","",'بيانات العقد'!C37) | H11: الفترة بالتاريخ الهجري | J11: =IF(J6="","",J6) | K11: =IF(J7="","",J7)
B12: أولاً: بيانات الفترة (إدخال)
B13: رصيد المواد الموردة بالموقع (نهاية الفترة) | E13: 150000 | H13: إفراج عن ضمان الأعمال خلال الفترة
B14: غرامات تأخير / خصومات أخرى خلال الفترة | H14: سبب الغرامة / الخصم
B15: المبلغ المحصل من هذا المستخلص | H15: تاريخ التحصيل
B16: رقم الفاتورة الضريبية (من نظام الفوترة الإلكترونية) | E16: INV-2026-01006 | H16: تاريخ الفاتورة الضريبية | K16: 46285
B17: ثانياً: الملخص المالي للمستخلص
B18: م | C18: البيان | H18: السابق | J18: الحالي | L18: الإجمالي التراكمي
B19: 1 | C19: قيمة الأعمال المنفذة طبقاً لحصر البنود | H19: ='مستخلص 05'!L19 | J19: =L19-H19 | L19: =M151
B20: 2 | C20: قيمة الأوامر التغييرية المعتمدة | H20: ='مستخلص 05'!L20 | J20: =L20-H20 | L20: =SUMIFS('الأوامر التغييرية'!$J$6:$J$55,'الأوامر التغييرية'!$H$6:$H$55,"معتمد",'الأوامر التغييرية'!$K$6:$K$55,"<="&$C$5)
B21: 3 | C21: المواد الموردة بالموقع (رصيد) | H21: ='مستخلص 05'!L21 | J21: =L21-H21 | L21: =N(E13)
B22: 4 | C22: إجمالي قيمة الأعمال | H22: ='مستخلص 05'!L22 | J22: =L22-H22 | L22: =SUM(L19:L21)
B23: 5 | C23: يُخصم: استرداد الدفعة المقدمة | H23: ='مستخلص 05'!L23 | J23: =L23-H23 | L23: =-ROUND(IF(L6>=RecFull,AdvAmount,MIN(AdvAmount,MAX(0,L19+L20-RecStart*ContractValue)*RecRate)),2)
B24: 6 | C24: يُخصم: ضمان الأعمال المحتسب | H24: ='مستخلص 05'!L24 | J24: =L24-H24 | L24: =-ROUND(MIN(L22*RetPct,RetCap),2)
B25: 7 | C25: يُضاف: المفرج عنه من ضمان الأعمال | H25: ='مستخلص 05'!L25 | J25: =L25-H25 | L25: =H25+N(K13)
B26: 8 | C26: يُخصم: الاستقطاعات الفنية المحتجزة | H26: ='مستخلص 05'!L26 | J26: =L26-H26 | L26: =-(SUMIFS('الاستقطاعات الفنية'!$I$6:$I$105,'الاستقطاعات الفنية'!$D$6:$D$105,"<="&$C$5)-SUMIFS('الاستقطاعات الفنية'!$I$6:$I$105,'الاستقطاعات الفنية'!$J$6:$J$105,"نعم",'الاستقطاعات الفنية'!$K$6:$K$105,"<="&$C$5))
B27: 9 | C27: يُخصم: الغرامات والخصومات الأخرى | H27: ='مستخلص 05'!L27 | J27: =L27-H27 | L27: =H27-N(E14)
B28: 10 | C28: صافي القيمة قبل الضرائب | H28: ='مستخلص 05'!L28 | J28: =L28-H28 | L28: =SUM(L22:L27)
B29: 11 | C29: يُضاف: ضريبة القيمة المضافة | H29: ='مستخلص 05'!L29 | J29: =L29-H29 | L29: =ROUND(VATPct*(L28+IF(VATBeforeRet="نعم",-(L24+L25),0)+IF(PenInVAT="لا",-L27,0)),2)
B30: 12 | C30: يُخصم: ضريبة الاستقطاع (غير المقيم) | H30: ='مستخلص 05'!L30 | J30: =L30-H30 | L30: =-ROUND(WHTPct*(L28-(L24+L25)),2)
B31: 13 | C31: صافي المستحق | H31: ='مستخلص 05'!L31 | J31: =L31-H31 | L31: =L28+L29+L30
B32: صافي المبلغ المستحق صرفه عن هذا المستخلص | J32: =J31
B33: المحصل من هذا المستخلص | J33: =N(E15)
B34: المتبقي غير المحصل | J34: =J32-J33
B35: فقط وقدره:
B37: ثالثاً: المستندات والمتطلبات النظامية للصرف (المملكة العربية السعودية)
B38: الفاتورة الضريبية الإلكترونية (متوافقة مع فاتورة - ZATCA) | F38: نعم | H38: شهادة الزكاة والضريبة سارية | L38: نعم
B39: شهادة التأمينات الاجتماعية (GOSI) سارية | F39: نعم | H39: شهادة نطاقات (التوطين) سارية | L39: نعم
B40: السجل التجاري وعضوية الغرفة التجارية سارية | F40: نعم | H40: محضر حصر الكميات معتمد من الاستشاري | L40: نعم
B41: ضمان الدفعة المقدمة ساري | F41: نعم | H41: الضمان النهائي ساري | L41: نعم
B42: وثيقة التأمين على الأعمال (CAR) سارية | F42: نعم | H42: تقرير الاستشاري الشهري | L42: نعم
B43: حالة المستندات: | E43: =IF(COUNTIF(F38:F42,"لا")+COUNTIF(L38:L42,"لا")+COUNTBLANK(F38:F42)+COUNTBLANK(L38:L42)=0,"✔ مكتملة — جاهز للصرف","⚠ ناقص "&(COUNTIF(F38:F42,"لا")+COUNTIF(L38:L42,"لا")+COUNTBLANK(F38:F42)+COUNTBLANK(L38:L42))&" مستند") | H43: الرقم الضريبي لصاحب العمل: | K43: =IF('بيانات العقد'!C39="","",'بيانات العقد'!C39)
B45: رابعاً: الاعتمادات
B46: إعداد: مهندس المقاول | F46: مراجعة: المهندس الاستشاري | J46: اعتماد: صاحب العمل
B47: الاسم: .................... التوقيع: .................. التاريخ: .................. | F47: الاسم: .................... التوقيع: .................. التاريخ: .................. | J47: الاسم: .................... التوقيع: .................. التاريخ: ..................
B49: خامساً: حصر الأعمال المنفذة حسب بنود جدول الكميات — أدخل «الكمية الحالية» فقط
B50: كود البند | C50: الوصف | D50: الوحدة | E50: الكمية التعاقدية | F50: سعر الوحدة | G50: الكمية السابقة | H50: الكمية الحالية | I50: الكمية التراكمية | J50: نسبة الإنجاز | K50: القيمة السابقة | L50: القيمة الحالية | M50: القيمة التراكمية
B51: =IF('جدول الكميات'!B6="","",'جدول الكميات'!B6) | C51: =IF('جدول الكميات'!D6="","",'جدول الكميات'!D6) | D51: =IF('جدول الكميات'!E6="","",'جدول الكميات'!E6) | E51: =N('جدول الكميات'!F6) | F51: =N('جدول الكميات'!G6) | G51: ='مستخلص 05'!I51 | I51: =G51+H51 | J51: =IF(E51>0,I51/E51,0) | K51: =G51*F51 | L51: =N(H51)*F51 | M51: =I51*F51
B52: =IF('جدول الكميات'!B7="","",'جدول الكميات'!B7) | C52: =IF('جدول الكميات'!D7="","",'جدول الكميات'!D7) | D52: =IF('جدول الكميات'!E7="","",'جدول الكميات'!E7) | E52: =N('جدول الكميات'!F7) | F52: =N('جدول الكميات'!G7) | G52: ='مستخلص 05'!I52 | I52: =G52+H52 | J52: =IF(E52>0,I52/E52,0) | K52: =G52*F52 | L52: =N(H52)*F52 | M52: =I52*F52
B53: =IF('جدول الكميات'!B8="","",'جدول الكميات'!B8) | C53: =IF('جدول الكميات'!D8="","",'جدول الكميات'!D8) | D53: =IF('جدول الكميات'!E8="","",'جدول الكميات'!E8) | E53: =N('جدول الكميات'!F8) | F53: =N('جدول الكميات'!G8) | G53: ='مستخلص 05'!I53 | I53: =G53+H53 | J53: =IF(E53>0,I53/E53,0) | K53: =G53*F53 | L53: =N(H53)*F53 | M53: =I53*F53
B54: =IF('جدول الكميات'!B9="","",'جدول الكميات'!B9) | C54: =IF('جدول الكميات'!D9="","",'جدول الكميات'!D9) | D54: =IF('جدول الكميات'!E9="","",'جدول الكميات'!E9) | E54: =N('جدول الكميات'!F9) | F54: =N('جدول الكميات'!G9) | G54: ='مستخلص 05'!I54 | H54: 50.67 | I54: =G54+H54 | J54: =IF(E54>0,I54/E54,0) | K54: =G54*F54 | L54: =N(H54)*F54 | M54: =I54*F54
B55: =IF('جدول الكميات'!B10="","",'جدول الكميات'!B10) | C55: =IF('جدول الكميات'!D10="","",'جدول الكميات'!D10) | D55: =IF('جدول الكميات'!E10="","",'جدول الكميات'!E10) | E55: =N('جدول الكميات'!F10) | F55: =N('جدول الكميات'!G10) | G55: ='مستخلص 05'!I55 | H55: 126.67 | I55: =G55+H55 | J55: =IF(E55>0,I55/E55,0) | K55: =G55*F55 | L55: =N(H55)*F55 | M55: =I55*F55
B56: =IF('جدول الكميات'!B11="","",'جدول الكميات'!B11) | C56: =IF('جدول الكميات'!D11="","",'جدول الكميات'!D11) | D56: =IF('جدول الكميات'!E11="","",'جدول الكميات'!E11) | E56: =N('جدول الكميات'!F11) | F56: =N('جدول الكميات'!G11) | G56: ='مستخلص 05'!I56 | H56: 56 | I56: =G56+H56 | J56: =IF(E56>0,I56/E56,0) | K56: =G56*F56 | L56: =N(H56)*F56 | M56: =I56*F56
B57: =IF('جدول الكميات'!B12="","",'جدول الكميات'!B12) | C57: =IF('جدول الكميات'!D12="","",'جدول الكميات'!D12) | D57: =IF('جدول الكميات'!E12="","",'جدول الكميات'!E12) | E57: =N('جدول الكميات'!F12) | F57: =N('جدول الكميات'!G12) | G57: ='مستخلص 05'!I57 | H57: 220 | I57: =G57+H57 | J57: =IF(E57>0,I57/E57,0) | K57: =G57*F57 | L57: =N(H57)*F57 | M57: =I57*F57
B58: =IF('جدول الكميات'!B13="","",'جدول الكميات'!B13) | C58: =IF('جدول الكميات'!D13="","",'جدول الكميات'!D13) | D58: =IF('جدول الكميات'!E13="","",'جدول الكميات'!E13) | E58: =N('جدول الكميات'!F13) | F58: =N('جدول الكميات'!G13) | G58: ='مستخلص 05'!I58 | H58: 64 | I58: =G58+H58 | J58: =IF(E58>0,I58/E58,0) | K58: =G58*F58 | L58: =N(H58)*F58 | M58: =I58*F58
B59: =IF('جدول الكميات'!B14="","",'جدول الكميات'!B14) | C59: =IF('جدول الكميات'!D14="","",'جدول الكميات'!D14) | D59: =IF('جدول الكميات'!E14="","",'جدول الكميات'!E14) | E59: =N('جدول الكميات'!F14) | F59: =N('جدول الكميات'!G14) | G59: ='مستخلص 05'!I59 | H59: 802.29 | I59: =G59+H59 | J59: =IF(E59>0,I59/E59,0) | K59: =G59*F59 | L59: =N(H59)*F59 | M59: =I59*F59
B60: =IF('جدول الكميات'!B15="","",'جدول الكميات'!B15) | C60: =IF('جدول الكميات'!D15="","",'جدول الكميات'!D15) | D60: =IF('جدول الكميات'!E15="","",'جدول الكميات'!E15) | E60: =N('جدول الكميات'!F15) | F60: =N('جدول الكميات'!G15) | G60: ='مستخلص 05'!I60 | H60: 370.29 | I60: =G60+H60 | J60: =IF(E60>0,I60/E60,0) | K60: =G60*F60 | L60: =N(H60)*F60 | M60: =I60*F60
B61: =IF('جدول الكميات'!B16="","",'جدول الكميات'!B16) | C61: =IF('جدول الكميات'!D16="","",'جدول الكميات'!D16) | D61: =IF('جدول الكميات'!E16="","",'جدول الكميات'!E16) | E61: =N('جدول الكميات'!F16) | F61: =N('جدول الكميات'!G16) | G61: ='مستخلص 05'!I61 | H61: 240 | I61: =G61+H61 | J61: =IF(E61>0,I61/E61,0) | K61: =G61*F61 | L61: =N(H61)*F61 | M61: =I61*F61
B62: =IF('جدول الكميات'!B17="","",'جدول الكميات'!B17) | C62: =IF('جدول الكميات'!D17="","",'جدول الكميات'!D17) | D62: =IF('جدول الكميات'!E17="","",'جدول الكميات'!E17) | E62: =N('جدول الكميات'!F17) | F62: =N('جدول الكميات'!G17) | G62: ='مستخلص 05'!I62 | H62: 190 | I62: =G62+H62 | J62: =IF(E62>0,I62/E62,0) | K62: =G62*F62 | L62: =N(H62)*F62 | M62: =I62*F62
B63: =IF('جدول الكميات'!B18="","",'جدول الكميات'!B18) | C63: =IF('جدول الكميات'!D18="","",'جدول الكميات'!D18) | D63: =IF('جدول الكميات'!E18="","",'جدول الكميات'!E18) | E63: =N('جدول الكميات'!F18) | F63: =N('جدول الكميات'!G18) | G63: ='مستخلص 05'!I63 | I63: =G63+H63 | J63: =IF(E63>0,I63/E63,0) | K63: =G63*F63 | L63: =N(H63)*F63 | M63: =I63*F63
B64: =IF('جدول الكميات'!B19="","",'جدول الكميات'!B19) | C64: =IF('جدول الكميات'!D19="","",'جدول الكميات'!D19) | D64: =IF('جدول الكميات'!E19="","",'جدول الكميات'!E19) | E64: =N('جدول الكميات'!F19) | F64: =N('جدول الكميات'!G19) | G64: ='مستخلص 05'!I64 | I64: =G64+H64 | J64: =IF(E64>0,I64/E64,0) | K64: =G64*F64 | L64: =N(H64)*F64 | M64: =I64*F64
B65: =IF('جدول الكميات'!B20="","",'جدول الكميات'!B20) | C65: =IF('جدول الكميات'!D20="","",'جدول الكميات'!D20) | D65: =IF('جدول الكميات'!E20="","",'جدول الكميات'!E20) | E65: =N('جدول الكميات'!F20) | F65: =N('جدول الكميات'!G20) | G65: ='مستخلص 05'!I65 | I65: =G65+H65 | J65: =IF(E65>0,I65/E65,0) | K65: =G65*F65 | L65: =N(H65)*F65 | M65: =I65*F65
B66: =IF('جدول الكميات'!B21="","",'جدول الكميات'!B21) | C66: =IF('جدول الكميات'!D21="","",'جدول الكميات'!D21) | D66: =IF('جدول الكميات'!E21="","",'جدول الكميات'!E21) | E66: =N('جدول الكميات'!F21) | F66: =N('جدول الكميات'!G21) | G66: ='مستخلص 05'!I66 | I66: =G66+H66 | J66: =IF(E66>0,I66/E66,0) | K66: =G66*F66 | L66: =N(H66)*F66 | M66: =I66*F66
B67: =IF('جدول الكميات'!B22="","",'جدول الكميات'!B22) | C67: =IF('جدول الكميات'!D22="","",'جدول الكميات'!D22) | D67: =IF('جدول الكميات'!E22="","",'جدول الكميات'!E22) | E67: =N('جدول الكميات'!F22) | F67: =N('جدول الكميات'!G22) | G67: ='مستخلص 05'!I67 | I67: =G67+H67 | J67: =IF(E67>0,I67/E67,0) | K67: =G67*F67 | L67: =N(H67)*F67 | M67: =I67*F67
B68: =IF('جدول الكميات'!B23="","",'جدول الكميات'!B23) | C68: =IF('جدول الكميات'!D23="","",'جدول الكميات'!D23) | D68: =IF('جدول الكميات'!E23="","",'جدول الكميات'!E23) | E68: =N('جدول الكميات'!F23) | F68: =N('جدول الكميات'!G23) | G68: ='مستخلص 05'!I68 | I68: =G68+H68 | J68: =IF(E68>0,I68/E68,0) | K68: =G68*F68 | L68: =N(H68)*F68 | M68: =I68*F68
B69: =IF('جدول الكميات'!B24="","",'جدول الكميات'!B24) | C69: =IF('جدول الكميات'!D24="","",'جدول الكميات'!D24) | D69: =IF('جدول الكميات'!E24="","",'جدول الكميات'!E24) | E69: =N('جدول الكميات'!F24) | F69: =N('جدول الكميات'!G24) | G69: ='مستخلص 05'!I69 | I69: =G69+H69 | J69: =IF(E69>0,I69/E69,0) | K69: =G69*F69 | L69: =N(H69)*F69 | M69: =I69*F69
B70: =IF('جدول الكميات'!B25="","",'جدول الكميات'!B25) | C70: =IF('جدول الكميات'!D25="","",'جدول الكميات'!D25) | D70: =IF('جدول الكميات'!E25="","",'جدول الكميات'!E25) | E70: =N('جدول الكميات'!F25) | F70: =N('جدول الكميات'!G25) | G70: ='مستخلص 05'!I70 | I70: =G70+H70 | J70: =IF(E70>0,I70/E70,0) | K70: =G70*F70 | L70: =N(H70)*F70 | M70: =I70*F70
B71: =IF('جدول الكميات'!B26="","",'جدول الكميات'!B26) | C71: =IF('جدول الكميات'!D26="","",'جدول الكميات'!D26) | D71: =IF('جدول الكميات'!E26="","",'جدول الكميات'!E26) | E71: =N('جدول الكميات'!F26) | F71: =N('جدول الكميات'!G26) | G71: ='مستخلص 05'!I71 | I71: =G71+H71 | J71: =IF(E71>0,I71/E71,0) | K71: =G71*F71 | L71: =N(H71)*F71 | M71: =I71*F71
B72: =IF('جدول الكميات'!B27="","",'جدول الكميات'!B27) | C72: =IF('جدول الكميات'!D27="","",'جدول الكميات'!D27) | D72: =IF('جدول الكميات'!E27="","",'جدول الكميات'!E27) | E72: =N('جدول الكميات'!F27) | F72: =N('جدول الكميات'!G27) | G72: ='مستخلص 05'!I72 | I72: =G72+H72 | J72: =IF(E72>0,I72/E72,0) | K72: =G72*F72 | L72: =N(H72)*F72 | M72: =I72*F72
B73: =IF('جدول الكميات'!B28="","",'جدول الكميات'!B28) | C73: =IF('جدول الكميات'!D28="","",'جدول الكميات'!D28) | D73: =IF('جدول الكميات'!E28="","",'جدول الكميات'!E28) | E73: =N('جدول الكميات'!F28) | F73: =N('جدول الكميات'!G28) | G73: ='مستخلص 05'!I73 | I73: =G73+H73 | J73: =IF(E73>0,I73/E73,0) | K73: =G73*F73 | L73: =N(H73)*F73 | M73: =I73*F73
B74: =IF('جدول الكميات'!B29="","",'جدول الكميات'!B29) | C74: =IF('جدول الكميات'!D29="","",'جدول الكميات'!D29) | D74: =IF('جدول الكميات'!E29="","",'جدول الكميات'!E29) | E74: =N('جدول الكميات'!F29) | F74: =N('جدول الكميات'!G29) | G74: ='مستخلص 05'!I74 | I74: =G74+H74 | J74: =IF(E74>0,I74/E74,0) | K74: =G74*F74 | L74: =N(H74)*F74 | M74: =I74*F74
... B150: =IF('جدول الكميات'!B105="","",'جدول الكميات'!B105) | C150: =IF('جدول الكميات'!D105="","",'جدول الكميات'!D105) | D150: =IF('جدول الكميات'!E105="","",'جدول الكميات'!E105) | E150: =N('جدول الكميات'!F105) | F150: =N('جدول الكميات'!G105) | G150: ='مستخلص 05'!I150 | I150: =G150+H150 | J150: =IF(E150>0,I150/E150,0) | K150: =G150*F150 | L150: =N(H150)*F150 | M150: =I150*F150
B151: الإجمالي | K151: =SUM(K51:K150) | L151: =SUM(L51:L150) | M151: =SUM(M51:M150)

Sheet مستخلص 07
B1: 🧾 مستخلص أعمال رقم (7) — شهادة دفع مؤقتة (Interim Payment Certificate)
B2: =IF('بيانات العقد'!$C$5="","مشروع رقم 01 — أدخل بيانات العقد",'بيانات العقد'!$C$5&" | عقد رقم: "&'بيانات العقد'!$C$6)&" | المبالغ بـ "&'بيانات العقد'!$C$14
B3: 🗂 سجل المستخلصات | C3: ⚙ بيانات العقد | E3: 📋 جدول الكميات | G3: 🔁 التغييرية | I3: ✂ الاستقطاعات | K3: ◄ المستخلص السابق | L3: المستخلص التالي ►
B5: رقم المستخلص | C5: 7 | H5: حالة المستخلص | L5: نسبة الإنجاز الفعلية
B6: المشروع | C6: ='بيانات العقد'!C5 | H6: الفترة من | L6: =IF(ContractValue+L20>0,(L19+L20)/(ContractValue+L20),0)
B7: رقم العقد | C7: ='بيانات العقد'!C6 | H7: الفترة إلى | L7: نسبة الإنجاز المخططة (من البرنامج)
B8: صاحب العمل | C8: ='بيانات العقد'!C7 | H8: تاريخ التقديم | L8: 0.3238
B9: الاستشاري | C9: ='بيانات العقد'!C8 | H9: تاريخ الاعتماد | L9: الانحراف عن المخطط
B10: المقاول | C10: ='بيانات العقد'!C9 | H10: قيمة العقد المعدلة | J10: =RevisedContract | L10: =IF(L8="","",L6-L8)
B11: الرقم الضريبي للمقاول | C11: =IF('بيانات العقد'!C37="","",'بيانات العقد'!C37) | H11: الفترة بالتاريخ الهجري | J11: =IF(J6="","",J6) | K11: =IF(J7="","",J7)
B12: أولاً: بيانات الفترة (إدخال)
B13: رصيد المواد الموردة بالموقع (نهاية الفترة) | H13: إفراج عن ضمان الأعمال خلال الفترة
B14: غرامات تأخير / خصومات أخرى خلال الفترة | H14: سبب الغرامة / الخصم
B15: المبلغ المحصل من هذا المستخلص | H15: تاريخ التحصيل
B16: رقم الفاتورة الضريبية (من نظام الفوترة الإلكترونية) | H16: تاريخ الفاتورة الضريبية
B17: ثانياً: الملخص المالي للمستخلص
B18: م | C18: البيان | H18: السابق | J18: الحالي | L18: الإجمالي التراكمي
B19: 1 | C19: قيمة الأعمال المنفذة طبقاً لحصر البنود | H19: ='مستخلص 06'!L19 | J19: =L19-H19 | L19: =M151
B20: 2 | C20: قيمة الأوامر التغييرية المعتمدة | H20: ='مستخلص 06'!L20 | J20: =L20-H20 | L20: =SUMIFS('الأوامر التغييرية'!$J$6:$J$55,'الأوامر التغييرية'!$H$6:$H$55,"معتمد",'الأوامر التغييرية'!$K$6:$K$55,"<="&$C$5)
B21: 3 | C21: المواد الموردة بالموقع (رصيد) | H21: ='مستخلص 06'!L21 | J21: =L21-H21 | L21: =N(E13)
B22: 4 | C22: إجمالي قيمة الأعمال | H22: ='مستخلص 06'!L22 | J22: =L22-H22 | L22: =SUM(L19:L21)
B23: 5 | C23: يُخصم: استرداد الدفعة المقدمة | H23: ='مستخلص 06'!L23 | J23: =L23-H23 | L23: =-ROUND(IF(L6>=RecFull,AdvAmount,MIN(AdvAmount,MAX(0,L19+L20-RecStart*ContractValue)*RecRate)),2)
B24: 6 | C24: يُخصم: ضمان الأعمال المحتسب | H24: ='مستخلص 06'!L24 | J24: =L24-H24 | L24: =-ROUND(MIN(L22*RetPct,RetCap),2)
B25: 7 | C25: يُضاف: المفرج عنه من ضمان الأعمال | H25: ='مستخلص 06'!L25 | J25: =L25-H25 | L25: =H25+N(K13)
B26: 8 | C26: يُخصم: الاستقطاعات الفنية المحتجزة | H26: ='مستخلص 06'!L26 | J26: =L26-H26 | L26: =-(SUMIFS('الاستقطاعات الفنية'!$I$6:$I$105,'الاستقطاعات الفنية'!$D$6:$D$105,"<="&$C$5)-SUMIFS('الاستقطاعات الفنية'!$I$6:$I$105,'الاستقطاعات الفنية'!$J$6:$J$105,"نعم",'الاستقطاعات الفنية'!$K$6:$K$105,"<="&$C$5))
B27: 9 | C27: يُخصم: الغرامات والخصومات الأخرى | H27: ='مستخلص 06'!L27 | J27: =L27-H27 | L27: =H27-N(E14)
B28: 10 | C28: صافي القيمة قبل الضرائب | H28: ='مستخلص 06'!L28 | J28: =L28-H28 | L28: =SUM(L22:L27)
B29: 11 | C29: يُضاف: ضريبة القيمة المضافة | H29: ='مستخلص 06'!L29 | J29: =L29-H29 | L29: =ROUND(VATPct*(L28+IF(VATBeforeRet="نعم",-(L24+L25),0)+IF(PenInVAT="لا",-L27,0)),2)
B30: 12 | C30: يُخصم: ضريبة الاستقطاع (غير المقيم) | H30: ='مستخلص 06'!L30 | J30: =L30-H30 | L30: =-ROUND(WHTPct*(L28-(L24+L25)),2)
B31: 13 | C31: صافي المستحق | H31: ='مستخلص 06'!L31 | J31: =L31-H31 | L31: =L28+L29+L30
B32: صافي المبلغ المستحق صرفه عن هذا المستخلص | J32: =J31
B33: المحصل من هذا المستخلص | J33: =N(E15)
B34: المتبقي غير المحصل | J34: =J32-J33
B35: فقط وقدره:
B37: ثالثاً: المستندات والمتطلبات النظامية للصرف (المملكة العربية السعودية)
B38: الفاتورة الضريبية الإلكترونية (متوافقة مع فاتورة - ZATCA) | H38: شهادة الزكاة والضريبة سارية
B39: شهادة التأمينات الاجتماعية (GOSI) سارية | H39: شهادة نطاقات (التوطين) سارية
B40: السجل التجاري وعضوية الغرفة التجارية سارية | H40: محضر حصر الكميات معتمد من الاستشاري
B41: ضمان الدفعة المقدمة ساري | H41: الضمان النهائي ساري
B42: وثيقة التأمين على الأعمال (CAR) سارية | H42: تقرير الاستشاري الشهري
B43: حالة المستندات: | E43: =IF(COUNTIF(F38:F42,"لا")+COUNTIF(L38:L42,"لا")+COUNTBLANK(F38:F42)+COUNTBLANK(L38:L42)=0,"✔ مكتملة — جاهز للصرف","⚠ ناقص "&(COUNTIF(F38:F42,"لا")+COUNTIF(L38:L42,"لا")+COUNTBLANK(F38:F42)+COUNTBLANK(L38:L42))&" مستند") | H43: الرقم الضريبي لصاحب العمل: | K43: =IF('بيانات العقد'!C39="","",'بيانات العقد'!C39)
B45: رابعاً: الاعتمادات
B46: إعداد: مهندس المقاول | F46: مراجعة: المهندس الاستشاري | J46: اعتماد: صاحب العمل
B47: الاسم: .................... التوقيع: .................. التاريخ: .................. | F47: الاسم: .................... التوقيع: .................. التاريخ: .................. | J47: الاسم: .................... التوقيع: .................. التاريخ: ..................
B49: خامساً: حصر الأعمال المنفذة حسب بنود جدول الكميات — أدخل «الكمية الحالية» فقط
B50: كود البند | C50: الوصف | D50: الوحدة | E50: الكمية التعاقدية | F50: سعر الوحدة | G50: الكمية السابقة | H50: الكمية الحالية | I50: الكمية التراكمية | J50: نسبة الإنجاز | K50: القيمة السابقة | L50: القيمة الحالية | M50: القيمة التراكمية
B51: =IF('جدول الكميات'!B6="","",'جدول الكميات'!B6) | C51: =IF('جدول الكميات'!D6="","",'جدول الكميات'!D6) | D51: =IF('جدول الكميات'!E6="","",'جدول الكميات'!E6) | E51: =N('جدول الكميات'!F6) | F51: =N('جدول الكميات'!G6) | G51: ='مستخلص 06'!I51 | I51: =G51+H51 | J51: =IF(E51>0,I51/E51,0) | K51: =G51*F51 | L51: =N(H51)*F51 | M51: =I51*F51
B52: =IF('جدول الكميات'!B7="","",'جدول الكميات'!B7) | C52: =IF('جدول الكميات'!D7="","",'جدول الكميات'!D7) | D52: =IF('جدول الكميات'!E7="","",'جدول الكميات'!E7) | E52: =N('جدول الكميات'!F7) | F52: =N('جدول الكميات'!G7) | G52: ='مستخلص 06'!I52 | I52: =G52+H52 | J52: =IF(E52>0,I52/E52,0) | K52: =G52*F52 | L52: =N(H52)*F52 | M52: =I52*F52
B53: =IF('جدول الكميات'!B8="","",'جدول الكميات'!B8) | C53: =IF('جدول الكميات'!D8="","",'جدول الكميات'!D8) | D53: =IF('جدول الكميات'!E8="","",'جدول الكميات'!E8) | E53: =N('جدول الكميات'!F8) | F53: =N('جدول الكميات'!G8) | G53: ='مستخلص 06'!I53 | I53: =G53+H53 | J53: =IF(E53>0,I53/E53,0) | K53: =G53*F53 | L53: =N(H53)*F53 | M53: =I53*F53
B54: =IF('جدول الكميات'!B9="","",'جدول الكميات'!B9) | C54: =IF('جدول الكميات'!D9="","",'جدول الكميات'!D9) | D54: =IF('جدول الكميات'!E9="","",'جدول الكميات'!E9) | E54: =N('جدول الكميات'!F9) | F54: =N('جدول الكميات'!G9) | G54: ='مستخلص 06'!I54 | I54: =G54+H54 | J54: =IF(E54>0,I54/E54,0) | K54: =G54*F54 | L54: =N(H54)*F54 | M54: =I54*F54
B55: =IF('جدول الكميات'!B10="","",'جدول الكميات'!B10) | C55: =IF('جدول الكميات'!D10="","",'جدول الكميات'!D10) | D55: =IF('جدول الكميات'!E10="","",'جدول الكميات'!E10) | E55: =N('جدول الكميات'!F10) | F55: =N('جدول الكميات'!G10) | G55: ='مستخلص 06'!I55 | I55: =G55+H55 | J55: =IF(E55>0,I55/E55,0) | K55: =G55*F55 | L55: =N(H55)*F55 | M55: =I55*F55
B56: =IF('جدول الكميات'!B11="","",'جدول الكميات'!B11) | C56: =IF('جدول الكميات'!D11="","",'جدول الكميات'!D11) | D56: =IF('جدول الكميات'!E11="","",'جدول الكميات'!E11) | E56: =N('جدول الكميات'!F11) | F56: =N('جدول الكميات'!G11) | G56: ='مستخلص 06'!I56 | I56: =G56+H56 | J56: =IF(E56>0,I56/E56,0) | K56: =G56*F56 | L56: =N(H56)*F56 | M56: =I56*F56
B57: =IF('جدول الكميات'!B12="","",'جدول الكميات'!B12) | C57: =IF('جدول الكميات'!D12="","",'جدول الكميات'!D12) | D57: =IF('جدول الكميات'!E12="","",'جدول الكميات'!E12) | E57: =N('جدول الكميات'!F12) | F57: =N('جدول الكميات'!G12) | G57: ='مستخلص 06'!I57 | I57: =G57+H57 | J57: =IF(E57>0,I57/E57,0) | K57: =G57*F57 | L57: =N(H57)*F57 | M57: =I57*F57
B58: =IF('جدول الكميات'!B13="","",'جدول الكميات'!B13) | C58: =IF('جدول الكميات'!D13="","",'جدول الكميات'!D13) | D58: =IF('جدول الكميات'!E13="","",'جدول الكميات'!E13) | E58: =N('جدول الكميات'!F13) | F58: =N('جدول الكميات'!G13) | G58: ='مستخلص 06'!I58 | I58: =G58+H58 | J58: =IF(E58>0,I58/E58,0) | K58: =G58*F58 | L58: =N(H58)*F58 | M58: =I58*F58
B59: =IF('جدول الكميات'!B14="","",'جدول الكميات'!B14) | C59: =IF('جدول الكميات'!D14="","",'جدول الكميات'!D14) | D59: =IF('جدول الكميات'!E14="","",'جدول الكميات'!E14) | E59: =N('جدول الكميات'!F14) | F59: =N('جدول الكميات'!G14) | G59: ='مستخلص 06'!I59 | I59: =G59+H59 | J59: =IF(E59>0,I59/E59,0) | K59: =G59*F59 | L59: =N(H59)*F59 | M59: =I59*F59
B60: =IF('جدول الكميات'!B15="","",'جدول الكميات'!B15) | C60: =IF('جدول الكميات'!D15="","",'جدول الكميات'!D15) | D60: =IF('جدول الكميات'!E15="","",'جدول الكميات'!E15) | E60: =N('جدول الكميات'!F15) | F60: =N('جدول الكميات'!G15) | G60: ='مستخلص 06'!I60 | I60: =G60+H60 | J60: =IF(E60>0,I60/E60,0) | K60: =G60*F60 | L60: =N(H60)*F60 | M60: =I60*F60
B61: =IF('جدول الكميات'!B16="","",'جدول الكميات'!B16) | C61: =IF('جدول الكميات'!D16="","",'جدول الكميات'!D16) | D61: =IF('جدول الكميات'!E16="","",'جدول الكميات'!E16) | E61: =N('جدول الكميات'!F16) | F61: =N('جدول الكميات'!G16) | G61: ='مستخلص 06'!I61 | I61: =G61+H61 | J61: =IF(E61>0,I61/E61,0) | K61: =G61*F61 | L61: =N(H61)*F61 | M61: =I61*F61
B62: =IF('جدول الكميات'!B17="","",'جدول الكميات'!B17) | C62: =IF('جدول الكميات'!D17="","",'جدول الكميات'!D17) | D62: =IF('جدول الكميات'!E17="","",'جدول الكميات'!E17) | E62: =N('جدول الكميات'!F17) | F62: =N('جدول الكميات'!G17) | G62: ='مستخلص 06'!I62 | I62: =G62+H62 | J62: =IF(E62>0,I62/E62,0) | K62: =G62*F62 | L62: =N(H62)*F62 | M62: =I62*F62
... B150: =IF('جدول الكميات'!B105="","",'جدول الكميات'!B105) | C150: =IF('جدول الكميات'!D105="","",'جدول الكميات'!D105) | D150: =IF('جدول الكميات'!E105="","",'جدول الكميات'!E105) | E150: =N('جدول الكميات'!F105) | F150: =N('جدول الكميات'!G105) | G150: ='مستخلص 06'!I150 | I150: =G150+H150 | J150: =IF(E150>0,I150/E150,0) | K150: =G150*F150 | L150: =N(H150)*F150 | M150: =I150*F150
B151: الإجمالي | K151: =SUM(K51:K150) | L151: =SUM(L51:L150) | M151: =SUM(M51:M150)

Sheet مستخلص 08
B1: 🧾 مستخلص أعمال رقم (8) — شهادة دفع مؤقتة (Interim Payment Certificate)
B2: =IF('بيانات العقد'!$C$5="","مشروع رقم 01 — أدخل بيانات العقد",'بيانات العقد'!$C$5&" | عقد رقم: "&'بيانات العقد'!$C$6)&" | المبالغ بـ "&'بيانات العقد'!$C$14
B3: 🗂 سجل المستخلصات | C3: ⚙ بيانات العقد | E3: 📋 جدول الكميات | G3: 🔁 التغييرية | I3: ✂ الاستقطاعات | K3: ◄ المستخلص السابق | L3: المستخلص التالي ►
B5: رقم المستخلص | C5: 8 | H5: حالة المستخلص | L5: نسبة الإنجاز الفعلية
B6: المشروع | C6: ='بيانات العقد'!C5 | H6: الفترة من | L6: =IF(ContractValue+L20>0,(L19+L20)/(ContractValue+L20),0)
B7: رقم العقد | C7: ='بيانات العقد'!C6 | H7: الفترة إلى | L7: نسبة الإنجاز المخططة (من البرنامج)
B8: صاحب العمل | C8: ='بيانات العقد'!C7 | H8: تاريخ التقديم | L8: 0.3915
B9: الاستشاري | C9: ='بيانات العقد'!C8 | H9: تاريخ الاعتماد | L9: الانحراف عن المخطط
B10: المقاول | C10: ='بيانات العقد'!C9 | H10: قيمة العقد المعدلة | J10: =RevisedContract | L10: =IF(L8="","",L6-L8)
B11: الرقم الضريبي للمقاول | C11: =IF('بيانات العقد'!C37="","",'بيانات العقد'!C37) | H11: الفترة بالتاريخ الهجري | J11: =IF(J6="","",J6) | K11: =IF(J7="","",J7)
B12: أولاً: بيانات الفترة (إدخال)
B13: رصيد المواد الموردة بالموقع (نهاية الفترة) | H13: إفراج عن ضمان الأعمال خلال الفترة
B14: غرامات تأخير / خصومات أخرى خلال الفترة | H14: سبب الغرامة / الخصم
B15: المبلغ المحصل من هذا المستخلص | H15: تاريخ التحصيل
B16: رقم الفاتورة الضريبية (من نظام الفوترة الإلكترونية) | H16: تاريخ الفاتورة الضريبية
B17: ثانياً: الملخص المالي للمستخلص
B18: م | C18: البيان | H18: السابق | J18: الحالي | L18: الإجمالي التراكمي
B19: 1 | C19: قيمة الأعمال المنفذة طبقاً لحصر البنود | H19: ='مستخلص 07'!L19 | J19: =L19-H19 | L19: =M151
B20: 2 | C20: قيمة الأوامر التغييرية المعتمدة | H20: ='مستخلص 07'!L20 | J20: =L20-H20 | L20: =SUMIFS('الأوامر التغييرية'!$J$6:$J$55,'الأوامر التغييرية'!$H$6:$H$55,"معتمد",'الأوامر التغييرية'!$K$6:$K$55,"<="&$C$5)
B21: 3 | C21: المواد الموردة بالموقع (رصيد) | H21: ='مستخلص 07'!L21 | J21: =L21-H21 | L21: =N(E13)
B22: 4 | C22: إجمالي قيمة الأعمال | H22: ='مستخلص 07'!L22 | J22: =L22-H22 | L22: =SUM(L19:L21)
B23: 5 | C23: يُخصم: استرداد الدفعة المقدمة | H23: ='مستخلص 07'!L23 | J23: =L23-H23 | L23: =-ROUND(IF(L6>=RecFull,AdvAmount,MIN(AdvAmount,MAX(0,L19+L20-RecStart*ContractValue)*RecRate)),2)
B24: 6 | C24: يُخصم: ضمان الأعمال المحتسب | H24: ='مستخلص 07'!L24 | J24: =L24-H24 | L24: =-ROUND(MIN(L22*RetPct,RetCap),2)
B25: 7 | C25: يُضاف: المفرج عنه من ضمان الأعمال | H25: ='مستخلص 07'!L25 | J25: =L25-H25 | L25: =H25+N(K13)
B26: 8 | C26: يُخصم: الاستقطاعات الفنية المحتجزة | H26: ='مستخلص 07'!L26 | J26: =L26-H26 | L26: =-(SUMIFS('الاستقطاعات الفنية'!$I$6:$I$105,'الاستقطاعات الفنية'!$D$6:$D$105,"<="&$C$5)-SUMIFS('الاستقطاعات الفنية'!$I$6:$I$105,'الاستقطاعات الفنية'!$J$6:$J$105,"نعم",'الاستقطاعات الفنية'!$K$6:$K$105,"<="&$C$5))
B27: 9 | C27: يُخصم: الغرامات والخصومات الأخرى | H27: ='مستخلص 07'!L27 | J27: =L27-H27 | L27: =H27-N(E14)
B28: 10 | C28: صافي القيمة قبل الضرائب | H28: ='مستخلص 07'!L28 | J28: =L28-H28 | L28: =SUM(L22:L27)
B29: 11 | C29: يُضاف: ضريبة القيمة المضافة | H29: ='مستخلص 07'!L29 | J29: =L29-H29 | L29: =ROUND(VATPct*(L28+IF(VATBeforeRet="نعم",-(L24+L25),0)+IF(PenInVAT="لا",-L27,0)),2)
B30: 12 | C30: يُخصم: ضريبة الاستقطاع (غير المقيم) | H30: ='مستخلص 07'!L30 | J30: =L30-H30 | L30: =-ROUND(WHTPct*(L28-(L24+L25)),2)
B31: 13 | C31: صافي المستحق | H31: ='مستخلص 07'!L31 | J31: =L31-H31 | L31: =L28+L29+L30
B32: صافي المبلغ المستحق صرفه عن هذا المستخلص | J32: =J31
B33: المحصل من هذا المستخلص | J33: =N(E15)
B34: المتبقي غير المحصل | J34: =J32-J33
B35: فقط وقدره:
B37: ثالثاً: المستندات والمتطلبات النظامية للصرف (المملكة العربية السعودية)
B38: الفاتورة الضريبية الإلكترونية (متوافقة مع فاتورة - ZATCA) | H38: شهادة الزكاة والضريبة سارية
B39: شهادة التأمينات الاجتماعية (GOSI) سارية | H39: شهادة نطاقات (التوطين) سارية
B40: السجل التجاري وعضوية الغرفة التجارية سارية | H40: محضر حصر الكميات معتمد من الاستشاري
B41: ضمان الدفعة المقدمة ساري | H41: الضمان النهائي ساري
B42: وثيقة التأمين على الأعمال (CAR) سارية | H42: تقرير الاستشاري الشهري
B43: حالة المستندات: | E43: =IF(COUNTIF(F38:F42,"لا")+COUNTIF(L38:L42,"لا")+COUNTBLANK(F38:F42)+COUNTBLANK(L38:L42)=0,"✔ مكتملة — جاهز للصرف","⚠ ناقص "&(COUNTIF(F38:F42,"لا")+COUNTIF(L38:L42,"لا")+COUNTBLANK(F38:F42)+COUNTBLANK(L38:L42))&" مستند") | H43: الرقم الضريبي لصاحب العمل: | K43: =IF('بيانات العقد'!C39="","",'بيانات العقد'!C39)
B45: رابعاً: الاعتمادات
B46: إعداد: مهندس المقاول | F46: مراجعة: المهندس الاستشاري | J46: اعتماد: صاحب العمل
B47: الاسم: .................... التوقيع: .................. التاريخ: .................. | F47: الاسم: .................... التوقيع: .................. التاريخ: .................. | J47: الاسم: .................... التوقيع: .................. التاريخ: ..................
B49: خامساً: حصر الأعمال المنفذة حسب بنود جدول الكميات — أدخل «الكمية الحالية» فقط
B50: كود البند | C50: الوصف | D50: الوحدة | E50: الكمية التعاقدية | F50: سعر الوحدة | G50: الكمية السابقة | H50: الكمية الحالية | I50: الكمية التراكمية | J50: نسبة الإنجاز | K50: القيمة السابقة | L50: القيمة الحالية | M50: القيمة التراكمية
B51: =IF('جدول الكميات'!B6="","",'جدول الكميات'!B6) | C51: =IF('جدول الكميات'!D6="","",'جدول الكميات'!D6) | D51: =IF('جدول الكميات'!E6="","",'جدول الكميات'!E6) | E51: =N('جدول الكميات'!F6) | F51: =N('جدول الكميات'!G6) | G51: ='مستخلص 07'!I51 | I51: =G51+H51 | J51: =IF(E51>0,I51/E51,0) | K51: =G51*F51 | L51: =N(H51)*F51 | M51: =I51*F51
B52: =IF('جدول الكميات'!B7="","",'جدول الكميات'!B7) | C52: =IF('جدول الكميات'!D7="","",'جدول الكميات'!D7) | D52: =IF('جدول الكميات'!E7="","",'جدول الكميات'!E7) | E52: =N('جدول الكميات'!F7) | F52: =N('جدول الكميات'!G7) | G52: ='مستخلص 07'!I52 | I52: =G52+H52 | J52: =IF(E52>0,I52/E52,0) | K52: =G52*F52 | L52: =N(H52)*F52 | M52: =I52*F52
B53: =IF('جدول الكميات'!B8="","",'جدول الكميات'!B8) | C53: =IF('جدول الكميات'!D8="","",'جدول الكميات'!D8) | D53: =IF('جدول الكميات'!E8="","",'جدول الكميات'!E8) | E53: =N('جدول الكميات'!F8) | F53: =N('جدول الكميات'!G8) | G53: ='مستخلص 07'!I53 | I53: =G53+H53 | J53: =IF(E53>0,I53/E53,0) | K53: =G53*F53 | L53: =N(H53)*F53 | M53: =I53*F53
B54: =IF('جدول الكميات'!B9="","",'جدول الكميات'!B9) | C54: =IF('جدول الكميات'!D9="","",'جدول الكميات'!D9) | D54: =IF('جدول الكميات'!E9="","",'جدول الكميات'!E9) | E54: =N('جدول الكميات'!F9) | F54: =N('جدول الكميات'!G9) | G54: ='مستخلص 07'!I54 | I54: =G54+H54 | J54: =IF(E54>0,I54/E54,0) | K54: =G54*F54 | L54: =N(H54)*F54 | M54: =I54*F54
B55: =IF('جدول الكميات'!B10="","",'جدول الكميات'!B10) | C55: =IF('جدول الكميات'!D10="","",'جدول الكميات'!D10) | D55: =IF('جدول الكميات'!E10="","",'جدول الكميات'!E10) | E55: =N('جدول الكميات'!F10) | F55: =N('جدول الكميات'!G10) | G55: ='مستخلص 07'!I55 | I55: =G55+H55 | J55: =IF(E55>0,I55/E55,0) | K55: =G55*F55 | L55: =N(H55)*F55 | M55: =I55*F55
B56: =IF('جدول الكميات'!B11="","",'جدول الكميات'!B11) | C56: =IF('جدول الكميات'!D11="","",'جدول الكميات'!D11) | D56: =IF('جدول الكميات'!E11="","",'جدول الكميات'!E11) | E56: =N('جدول الكميات'!F11) | F56: =N('جدول الكميات'!G11) | G56: ='مستخلص 07'!I56 | I56: =G56+H56 | J56: =IF(E56>0,I56/E56,0) | K56: =G56*F56 | L56: =N(H56)*F56 | M56: =I56*F56
B57: =IF('جدول الكميات'!B12="","",'جدول الكميات'!B12) | C57: =IF('جدول الكميات'!D12="","",'جدول الكميات'!D12) | D57: =IF('جدول الكميات'!E12="","",'جدول الكميات'!E12) | E57: =N('جدول الكميات'!F12) | F57: =N('جدول الكميات'!G12) | G57: ='مستخلص 07'!I57 | I57: =G57+H57 | J57: =IF(E57>0,I57/E57,0) | K57: =G57*F57 | L57: =N(H57)*F57 | M57: =I57*F57
B58: =IF('جدول الكميات'!B13="","",'جدول الكميات'!B13) | C58: =IF('جدول الكميات'!D13="","",'جدول الكميات'!D13) | D58: =IF('جدول الكميات'!E13="","",'جدول الكميات'!E13) | E58: =N('جدول الكميات'!F13) | F58: =N('جدول الكميات'!G13) | G58: ='مستخلص 07'!I58 | I58: =G58+H58 | J58: =IF(E58>0,I58/E58,0) | K58: =G58*F58 | L58: =N(H58)*F58 | M58: =I58*F58
B59: =IF('جدول الكميات'!B14="","",'جدول الكميات'!B14) | C59: =IF('جدول الكميات'!D14="","",'جدول الكميات'!D14) | D59: =IF('جدول الكميات'!E14="","",'جدول الكميات'!E14) | E59: =N('جدول الكميات'!F14) | F59: =N('جدول الكميات'!G14) | G59: ='مستخلص 07'!I59 | I59: =G59+H59 | J59: =IF(E59>0,I59/E59,0) | K59: =G59*F59 | L59: =N(H59)*F59 | M59: =I59*F59
B60: =IF('جدول الكميات'!B15="","",'جدول الكميات'!B15) | C60: =IF('جدول الكميات'!D15="","",'جدول الكميات'!D15) | D60: =IF('جدول الكميات'!E15="","",'جدول الكميات'!E15) | E60: =N('جدول الكميات'!F15) | F60: =N('جدول الكميات'!G15) | G60: ='مستخلص 07'!I60 | I60: =G60+H60 | J60: =IF(E60>0,I60/E60,0) | K60: =G60*F60 | L60: =N(H60)*F60 | M60: =I60*F60
B61: =IF('جدول الكميات'!B16="","",'جدول الكميات'!B16) | C61: =IF('جدول الكميات'!D16="","",'جدول الكميات'!D16) | D61: =IF('جدول الكميات'!E16="","",'جدول الكميات'!E16) | E61: =N('جدول الكميات'!F16) | F61: =N('جدول الكميات'!G16) | G61: ='مستخلص 07'!I61 | I61: =G61+H61 | J61: =IF(E61>0,I61/E61,0) | K61: =G61*F61 | L61: =N(H61)*F61 | M61: =I61*F61
B62: =IF('جدول الكميات'!B17="","",'جدول الكميات'!B17) | C62: =IF('جدول الكميات'!D17="","",'جدول الكميات'!D17) | D62: =IF('جدول الكميات'!E17="","",'جدول الكميات'!E17) | E62: =N('جدول الكميات'!F17) | F62: =N('جدول الكميات'!G17) | G62: ='مستخلص 07'!I62 | I62: =G62+H62 | J62: =IF(E62>0,I62/E62,0) | K62: =G62*F62 | L62: =N(H62)*F62 | M62: =I62*F62
... B150: =IF('جدول الكميات'!B105="","",'جدول الكميات'!B105) | C150: =IF('جدول الكميات'!D105="","",'جدول الكميات'!D105) | D150: =IF('جدول الكميات'!E105="","",'جدول الكميات'!E105) | E150: =N('جدول الكميات'!F105) | F150: =N('جدول الكميات'!G105) | G150: ='مستخلص 07'!I150 | I150: =G150+H150 | J150: =IF(E150>0,I150/E150,0) | K150: =G150*F150 | L150: =N(H150)*F150 | M150: =I150*F150
B151: الإجمالي | K151: =SUM(K51:K150) | L151: =SUM(L51:L150) | M151: =SUM(M51:M150)

Sheet مستخلص 09
B1: 🧾 مستخلص أعمال رقم (9) — شهادة دفع مؤقتة (Interim Payment Certificate)
B2: =IF('بيانات العقد'!$C$5="","مشروع رقم 01 — أدخل بيانات العقد",'بيانات العقد'!$C$5&" | عقد رقم: "&'بيانات العقد'!$C$6)&" | المبالغ بـ "&'بيانات العقد'!$C$14
B3: 🗂 سجل المستخلصات | C3: ⚙ بيانات العقد | E3: 📋 جدول الكميات | G3: 🔁 التغييرية | I3: ✂ الاستقطاعات | K3: ◄ المستخلص السابق | L3: المستخلص التالي ►
B5: رقم المستخلص | C5: 9 | H5: حالة المستخلص | L5: نسبة الإنجاز الفعلية
B6: المشروع | C6: ='بيانات العقد'!C5 | H6: الفترة من | L6: =IF(ContractValue+L20>0,(L19+L20)/(ContractValue+L20),0)
B7: رقم العقد | C7: ='بيانات العقد'!C6 | H7: الفترة إلى | L7: نسبة الإنجاز المخططة (من البرنامج)
B8: صاحب العمل | C8: ='بيانات العقد'!C7 | H8: تاريخ التقديم | L8: 0.4897
B9: الاستشاري | C9: ='بيانات العقد'!C8 | H9: تاريخ الاعتماد | L9: الانحراف عن المخطط
B10: المقاول | C10: ='بيانات العقد'!C9 | H10: قيمة العقد المعدلة | J10: =RevisedContract | L10: =IF(L8="","",L6-L8)
B11: الرقم الضريبي للمقاول | C11: =IF('بيانات العقد'!C37="","",'بيانات العقد'!C37) | H11: الفترة بالتاريخ الهجري | J11: =IF(J6="","",J6) | K11: =IF(J7="","",J7)
B12: أولاً: بيانات الفترة (إدخال)
B13: رصيد المواد الموردة بالموقع (نهاية الفترة) | H13: إفراج عن ضمان الأعمال خلال الفترة
B14: غرامات تأخير / خصومات أخرى خلال الفترة | H14: سبب الغرامة / الخصم
B15: المبلغ المحصل من هذا المستخلص | H15: تاريخ التحصيل
B16: رقم الفاتورة الضريبية (من نظام الفوترة الإلكترونية) | H16: تاريخ الفاتورة الضريبية
B17: ثانياً: الملخص المالي للمستخلص
B18: م | C18: البيان | H18: السابق | J18: الحالي | L18: الإجمالي التراكمي
B19: 1 | C19: قيمة الأعمال المنفذة طبقاً لحصر البنود | H19: ='مستخلص 08'!L19 | J19: =L19-H19 | L19: =M151
B20: 2 | C20: قيمة الأوامر التغييرية المعتمدة | H20: ='مستخلص 08'!L20 | J20: =L20-H20 | L20: =SUMIFS('الأوامر التغييرية'!$J$6:$J$55,'الأوامر التغييرية'!$H$6:$H$55,"معتمد",'الأوامر التغييرية'!$K$6:$K$55,"<="&$C$5)
B21: 3 | C21: المواد الموردة بالموقع (رصيد) | H21: ='مستخلص 08'!L21 | J21: =L21-H21 | L21: =N(E13)
B22: 4 | C22: إجمالي قيمة الأعمال | H22: ='مستخلص 08'!L22 | J22: =L22-H22 | L22: =SUM(L19:L21)
B23: 5 | C23: يُخصم: استرداد الدفعة المقدمة | H23: ='مستخلص 08'!L23 | J23: =L23-H23 | L23: =-ROUND(IF(L6>=RecFull,AdvAmount,MIN(AdvAmount,MAX(0,L19+L20-RecStart*ContractValue)*RecRate)),2)
B24: 6 | C24: يُخصم: ضمان الأعمال المحتسب | H24: ='مستخلص 08'!L24 | J24: =L24-H24 | L24: =-ROUND(MIN(L22*RetPct,RetCap),2)
B25: 7 | C25: يُضاف: المفرج عنه من ضمان الأعمال | H25: ='مستخلص 08'!L25 | J25: =L25-H25 | L25: =H25+N(K13)
B26: 8 | C26: يُخصم: الاستقطاعات الفنية المحتجزة | H26: ='مستخلص 08'!L26 | J26: =L26-H26 | L26: =-(SUMIFS('الاستقطاعات الفنية'!$I$6:$I$105,'الاستقطاعات الفنية'!$D$6:$D$105,"<="&$C$5)-SUMIFS('الاستقطاعات الفنية'!$I$6:$I$105,'الاستقطاعات الفنية'!$J$6:$J$105,"نعم",'الاستقطاعات الفنية'!$K$6:$K$105,"<="&$C$5))
B27: 9 | C27: يُخصم: الغرامات والخصومات الأخرى | H27: ='مستخلص 08'!L27 | J27: =L27-H27 | L27: =H27-N(E14)
B28: 10 | C28: صافي القيمة قبل الضرائب | H28: ='مستخلص 08'!L28 | J28: =L28-H28 | L28: =SUM(L22:L27)
B29: 11 | C29: يُضاف: ضريبة القيمة المضافة | H29: ='مستخلص 08'!L29 | J29: =L29-H29 | L29: =ROUND(VATPct*(L28+IF(VATBeforeRet="نعم",-(L24+L25),0)+IF(PenInVAT="لا",-L27,0)),2)
B30: 12 | C30: يُخصم: ضريبة الاستقطاع (غير المقيم) | H30: ='مستخلص 08'!L30 | J30: =L30-H30 | L30: =-ROUND(WHTPct*(L28-(L24+L25)),2)
B31: 13 | C31: صافي المستحق | H31: ='مستخلص 08'!L31 | J31: =L31-H31 | L31: =L28+L29+L30
B32: صافي المبلغ المستحق صرفه عن هذا المستخلص | J32: =J31
B33: المحصل من هذا المستخلص | J33: =N(E15)
B34: المتبقي غير المحصل | J34: =J32-J33
B35: فقط وقدره:
B37: ثالثاً: المستندات والمتطلبات النظامية للصرف (المملكة العربية السعودية)
B38: الفاتورة الضريبية الإلكترونية (متوافقة مع فاتورة - ZATCA) | H38: شهادة الزكاة والضريبة سارية
B39: شهادة التأمينات الاجتماعية (GOSI) سارية | H39: شهادة نطاقات (التوطين) سارية
B40: السجل التجاري وعضوية الغرفة التجارية سارية | H40: محضر حصر الكميات معتمد من الاستشاري
B41: ضمان الدفعة المقدمة ساري | H41: الضمان النهائي ساري
B42: وثيقة التأمين على الأعمال (CAR) سارية | H42: تقرير الاستشاري الشهري
B43: حالة المستندات: | E43: =IF(COUNTIF(F38:F42,"لا")+COUNTIF(L38:L42,"لا")+COUNTBLANK(F38:F42)+COUNTBLANK(L38:L42)=0,"✔ مكتملة — جاهز للصرف","⚠ ناقص "&(COUNTIF(F38:F42,"لا")+COUNTIF(L38:L42,"لا")+COUNTBLANK(F38:F42)+COUNTBLANK(L38:L42))&" مستند") | H43: الرقم الضريبي لصاحب العمل: | K43: =IF('بيانات العقد'!C39="","",'بيانات العقد'!C39)
B45: رابعاً: الاعتمادات
B46: إعداد: مهندس المقاول | F46: مراجعة: المهندس الاستشاري | J46: اعتماد: صاحب العمل
B47: الاسم: .................... التوقيع: .................. التاريخ: .................. | F47: الاسم: .................... التوقيع: .................. التاريخ: .................. | J47: الاسم: .................... التوقيع: .................. التاريخ: ..................
B49: خامساً: حصر الأعمال المنفذة حسب بنود جدول الكميات — أدخل «الكمية الحالية» فقط
B50: كود البند | C50: الوصف | D50: الوحدة | E50: الكمية التعاقدية | F50: سعر الوحدة | G50: الكمية السابقة | H50: الكمية الحالية | I50: الكمية التراكمية | J50: نسبة الإنجاز | K50: القيمة السابقة | L50: القيمة الحالية | M50: القيمة التراكمية
B51: =IF('جدول الكميات'!B6="","",'جدول الكميات'!B6) | C51: =IF('جدول الكميات'!D6="","",'جدول الكميات'!D6) | D51: =IF('جدول الكميات'!E6="","",'جدول الكميات'!E6) | E51: =N('جدول الكميات'!F6) | F51: =N('جدول الكميات'!G6) | G51: ='مستخلص 08'!I51 | I51: =G51+H51 | J51: =IF(E51>0,I51/E51,0) | K51: =G51*F51 | L51: =N(H51)*F51 | M51: =I51*F51
B52: =IF('جدول الكميات'!B7="","",'جدول الكميات'!B7) | C52: =IF('جدول الكميات'!D7="","",'جدول الكميات'!D7) | D52: =IF('جدول الكميات'!E7="","",'جدول الكميات'!E7) | E52: =N('جدول الكميات'!F7) | F52: =N('جدول الكميات'!G7) | G52: ='مستخلص 08'!I52 | I52: =G52+H52 | J52: =IF(E52>0,I52/E52,0) | K52: =G52*F52 | L52: =N(H52)*F52 | M52: =I52*F52
B53: =IF('جدول الكميات'!B8="","",'جدول الكميات'!B8) | C53: =IF('جدول الكميات'!D8="","",'جدول الكميات'!D8) | D53: =IF('جدول الكميات'!E8="","",'جدول الكميات'!E8) | E53: =N('جدول الكميات'!F8) | F53: =N('جدول الكميات'!G8) | G53: ='مستخلص 08'!I53 | I53: =G53+H53 | J53: =IF(E53>0,I53/E53,0) | K53: =G53*F53 | L53: =N(H53)*F53 | M53: =I53*F53
B54: =IF('جدول الكميات'!B9="","",'جدول الكميات'!B9) | C54: =IF('جدول الكميات'!D9="","",'جدول الكميات'!D9) | D54: =IF('جدول الكميات'!E9="","",'جدول الكميات'!E9) | E54: =N('جدول الكميات'!F9) | F54: =N('جدول الكميات'!G9) | G54: ='مستخلص 08'!I54 | I54: =G54+H54 | J54: =IF(E54>0,I54/E54,0) | K54: =G54*F54 | L54: =N(H54)*F54 | M54: =I54*F54
B55: =IF('جدول الكميات'!B10="","",'جدول الكميات'!B10) | C55: =IF('جدول الكميات'!D10="","",'جدول الكميات'!D10) | D55: =IF('جدول الكميات'!E10="","",'جدول الكميات'!E10) | E55: =N('جدول الكميات'!F10) | F55: =N('جدول الكميات'!G10) | G55: ='مستخلص 08'!I55 | I55: =G55+H55 | J55: =IF(E55>0,I55/E55,0) | K55: =G55*F55 | L55: =N(H55)*F55 | M55: =I55*F55
B56: =IF('جدول الكميات'!B11="","",'جدول الكميات'!B11) | C56: =IF('جدول الكميات'!D11="","",'جدول الكميات'!D11) | D56: =IF('جدول الكميات'!E11="","",'جدول الكميات'!E11) | E56: =N('جدول الكميات'!F11) | F56: =N('جدول الكميات'!G11) | G56: ='مستخلص 08'!I56 | I56: =G56+H56 | J56: =IF(E56>0,I56/E56,0) | K56: =G56*F56 | L56: =N(H56)*F56 | M56: =I56*F56
B57: =IF('جدول الكميات'!B12="","",'جدول الكميات'!B12) | C57: =IF('جدول الكميات'!D12="","",'جدول الكميات'!D12) | D57: =IF('جدول الكميات'!E12="","",'جدول الكميات'!E12) | E57: =N('جدول الكميات'!F12) | F57: =N('جدول الكميات'!G12) | G57: ='مستخلص 08'!I57 | I57: =G57+H57 | J57: =IF(E57>0,I57/E57,0) | K57: =G57*F57 | L57: =N(H57)*F57 | M57: =I57*F57
B58: =IF('جدول الكميات'!B13="","",'جدول الكميات'!B13) | C58: =IF('جدول الكميات'!D13="","",'جدول الكميات'!D13) | D58: =IF('جدول الكميات'!E13="","",'جدول الكميات'!E13) | E58: =N('جدول الكميات'!F13) | F58: =N('جدول الكميات'!G13) | G58: ='مستخلص 08'!I58 | I58: =G58+H58 | J58: =IF(E58>0,I58/E58,0) | K58: =G58*F58 | L58: =N(H58)*F58 | M58: =I58*F58
B59: =IF('جدول الكميات'!B14="","",'جدول الكميات'!B14) | C59: =IF('جدول الكميات'!D14="","",'جدول الكميات'!D14) | D59: =IF('جدول الكميات'!E14="","",'جدول الكميات'!E14) | E59: =N('جدول الكميات'!F14) | F59: =N('جدول الكميات'!G14) | G59: ='مستخلص 08'!I59 | I59: =G59+H59 | J59: =IF(E59>0,I59/E59,0) | K59: =G59*F59 | L59: =N(H59)*F59 | M59: =I59*F59
B60: =IF('جدول الكميات'!B15="","",'جدول الكميات'!B15) | C60: =IF('جدول الكميات'!D15="","",'جدول الكميات'!D15) | D60: =IF('جدول الكميات'!E15="","",'جدول الكميات'!E15) | E60: =N('جدول الكميات'!F15) | F60: =N('جدول الكميات'!G15) | G60: ='مستخلص 08'!I60 | I60: =G60+H60 | J60: =IF(E60>0,I60/E60,0) | K60: =G60*F60 | L60: =N(H60)*F60 | M60: =I60*F60
B61: =IF('جدول الكميات'!B16="","",'جدول الكميات'!B16) | C61: =IF('جدول الكميات'!D16="","",'جدول الكميات'!D16) | D61: =IF('جدول الكميات'!E16="","",'جدول الكميات'!E16) | E61: =N('جدول الكميات'!F16) | F61: =N('جدول الكميات'!G16) | G61: ='مستخلص 08'!I61 | I61: =G61+H61 | J61: =IF(E61>0,I61/E61,0) | K61: =G61*F61 | L61: =N(H61)*F61 | M61: =I61*F61
B62: =IF('جدول الكميات'!B17="","",'جدول الكميات'!B17) | C62: =IF('جدول الكميات'!D17="","",'جدول الكميات'!D17) | D62: =IF('جدول الكميات'!E17="","",'جدول الكميات'!E17) | E62: =N('جدول الكميات'!F17) | F62: =N('جدول الكميات'!G17) | G62: ='مستخلص 08'!I62 | I62: =G62+H62 | J62: =IF(E62>0,I62/E62,0) | K62: =G62*F62 | L62: =N(H62)*F62 | M62: =I62*F62
... B150: =IF('جدول الكميات'!B105="","",'جدول الكميات'!B105) | C150: =IF('جدول الكميات'!D105="","",'جدول الكميات'!D105) | D150: =IF('جدول الكميات'!E105="","",'جدول الكميات'!E105) | E150: =N('جدول الكميات'!F105) | F150: =N('جدول الكميات'!G105) | G150: ='مستخلص 08'!I150 | I150: =G150+H150 | J150: =IF(E150>0,I150/E150,0) | K150: =G150*F150 | L150: =N(H150)*F150 | M150: =I150*F150
B151: الإجمالي | K151: =SUM(K51:K150) | L151: =SUM(L51:L150) | M151: =SUM(M51:M150)

Sheet مستخلص 10
B1: 🧾 مستخلص أعمال رقم (10) — شهادة دفع مؤقتة (Interim Payment Certificate)
B2: =IF('بيانات العقد'!$C$5="","مشروع رقم 01 — أدخل بيانات العقد",'بيانات العقد'!$C$5&" | عقد رقم: "&'بيانات العقد'!$C$6)&" | المبالغ بـ "&'بيانات العقد'!$C$14
B3: 🗂 سجل المستخلصات | C3: ⚙ بيانات العقد | E3: 📋 جدول الكميات | G3: 🔁 التغييرية | I3: ✂ الاستقطاعات | K3: ◄ المستخلص السابق | L3: المستخلص التالي ►
B5: رقم المستخلص | C5: 10 | H5: حالة المستخلص | L5: نسبة الإنجاز الفعلية
B6: المشروع | C6: ='بيانات العقد'!C5 | H6: الفترة من | L6: =IF(ContractValue+L20>0,(L19+L20)/(ContractValue+L20),0)
B7: رقم العقد | C7: ='بيانات العقد'!C6 | H7: الفترة إلى | L7: نسبة الإنجاز المخططة (من البرنامج)
B8: صاحب العمل | C8: ='بيانات العقد'!C7 | H8: تاريخ التقديم | L8: 0.5469
B9: الاستشاري | C9: ='بيانات العقد'!C8 | H9: تاريخ الاعتماد | L9: الانحراف عن المخطط
B10: المقاول | C10: ='بيانات العقد'!C9 | H10: قيمة العقد المعدلة | J10: =RevisedContract | L10: =IF(L8="","",L6-L8)
B11: الرقم الضريبي للمقاول | C11: =IF('بيانات العقد'!C37="","",'بيانات العقد'!C37) | H11: الفترة بالتاريخ الهجري | J11: =IF(J6="","",J6) | K11: =IF(J7="","",J7)
B12: أولاً: بيانات الفترة (إدخال)
B13: رصيد المواد الموردة بالموقع (نهاية الفترة) | H13: إفراج عن ضمان الأعمال خلال الفترة
B14: غرامات تأخير / خصومات أخرى خلال الفترة | H14: سبب الغرامة / الخصم
B15: المبلغ المحصل من هذا المستخلص | H15: تاريخ التحصيل
B16: رقم الفاتورة الضريبية (من نظام الفوترة الإلكترونية) | H16: تاريخ الفاتورة الضريبية
B17: ثانياً: الملخص المالي للمستخلص
B18: م | C18: البيان | H18: السابق | J18: الحالي | L18: الإجمالي التراكمي
B19: 1 | C19: قيمة الأعمال المنفذة طبقاً لحصر البنود | H19: ='مستخلص 09'!L19 | J19: =L19-H19 | L19: =M151
B20: 2 | C20: قيمة الأوامر التغييرية المعتمدة | H20: ='مستخلص 09'!L20 | J20: =L20-H20 | L20: =SUMIFS('الأوامر التغييرية'!$J$6:$J$55,'الأوامر التغييرية'!$H$6:$H$55,"معتمد",'الأوامر التغييرية'!$K$6:$K$55,"<="&$C$5)
B21: 3 | C21: المواد الموردة بالموقع (رصيد) | H21: ='مستخلص 09'!L21 | J21: =L21-H21 | L21: =N(E13)
B22: 4 | C22: إجمالي قيمة الأعمال | H22: ='مستخلص 09'!L22 | J22: =L22-H22 | L22: =SUM(L19:L21)
B23: 5 | C23: يُخصم: استرداد الدفعة المقدمة | H23: ='مستخلص 09'!L23 | J23: =L23-H23 | L23: =-ROUND(IF(L6>=RecFull,AdvAmount,MIN(AdvAmount,MAX(0,L19+L20-RecStart*ContractValue)*RecRate)),2)
B24: 6 | C24: يُخصم: ضمان الأعمال المحتسب | H24: ='مستخلص 09'!L24 | J24: =L24-H24 | L24: =-ROUND(MIN(L22*RetPct,RetCap),2)
B25: 7 | C25: يُضاف: المفرج عنه من ضمان الأعمال | H25: ='مستخلص 09'!L25 | J25: =L25-H25 | L25: =H25+N(K13)
B26: 8 | C26: يُخصم: الاستقطاعات الفنية المحتجزة | H26: ='مستخلص 09'!L26 | J26: =L26-H26 | L26: =-(SUMIFS('الاستقطاعات الفنية'!$I$6:$I$105,'الاستقطاعات الفنية'!$D$6:$D$105,"<="&$C$5)-SUMIFS('الاستقطاعات الفنية'!$I$6:$I$105,'الاستقطاعات الفنية'!$J$6:$J$105,"نعم",'الاستقطاعات الفنية'!$K$6:$K$105,"<="&$C$5))
B27: 9 | C27: يُخصم: الغرامات والخصومات الأخرى | H27: ='مستخلص 09'!L27 | J27: =L27-H27 | L27: =H27-N(E14)
B28: 10 | C28: صافي القيمة قبل الضرائب | H28: ='مستخلص 09'!L28 | J28: =L28-H28 | L28: =SUM(L22:L27)
B29: 11 | C29: يُضاف: ضريبة القيمة المضافة | H29: ='مستخلص 09'!L29 | J29: =L29-H29 | L29: =ROUND(VATPct*(L28+IF(VATBeforeRet="نعم",-(L24+L25),0)+IF(PenInVAT="لا",-L27,0)),2)
B30: 12 | C30: يُخصم: ضريبة الاستقطاع (غير المقيم) | H30: ='مستخلص 09'!L30 | J30: =L30-H30 | L30: =-ROUND(WHTPct*(L28-(L24+L25)),2)
